Workbook

Sheet LEEME
A1: Sistema integrado de control de la UGP — LÉEME
A2: DATOS SIMULADOS con fines de demostración metodológica — no son cifras reales del BID ni de la Dirección de Integración.
A4: Qué es
A5: Libro de control de ejecución para la Unidad Gestora del Programa (UGP) del Programa de Integración Académica y Comunitaria para Jóvenes en El Salvador (operaciones BID ES-L1175 / ES-J0003; Contrato de Préstamo 6153/OC-ES por US$100 M y Convenio no reembolsable 6154/GR-ES por US$4 M). Organiza el ciclo del TDR en cuatro pilares: planificación y control integral, gestión fiduciaria, cumplimiento normativo y articulación y reporte.
A6: ADVERTENCIA: todos los datos son SIMULADOS y la estructura de componentes es ILUSTRATIVA. Se tomaron del TDR solo los montos, números de operación y condiciones de la consultoría. Antes de usarlo con datos reales hay que contrastarlo con el Contrato de Préstamo, el MOP, el PEP, el Plan de Adquisiciones y los sistemas del BID.
A8: Código de colores
A9: Texto azul = dato que se ingresa o edita
A10: Texto negro sobre gris = fórmula (no editar)
A11: Semáforo verde / amarillo / rojo = según los umbrales de la hoja Parametros
A13: Ciclo de cierre mensual (informe a más tardar 3 días hábiles tras el cierre)
A14: 1. Registrar los gastos del mes en F2_Ejecucion y los desembolsos en F3_Desembolsos.
A15: 2. Actualizar % de avance físico en P1_POA, valores actuales en P1_Resultados y estados en F4/F5.
... A21: Índice de hojas
A22: Hoja | B22: Pilar | C22: Qué hace | D22: Mantiene | E22: Frecuencia
A23: Tablero | B23: Base | C23: Semáforos ejecutivos, mapa de calor de riesgos y gráficos | D23: Esp. Planificación | E23: Mensual
A24: Parametros | B24: Base | C24: Datos del TDR, fecha de corte, umbrales y pesos | D24: Coordinador General | E24: Mensual (fecha de corte)
A25: Controles | B25: Base | C25: 16 pruebas automáticas de consistencia entre hojas | D25: Esp. Planificación | E25: Mensual, antes del informe
A26: P1_Resultados | B26: 1 Planificación y control | C26: Matriz de resultados: metas anuales, esperado al corte, cumplimiento y semáforo | D26: Esp. Planificación | E26: Mensual / anual
A27: P1_POA | B27: 1 Planificación y control | C27: POA e hitos con valor ganado (EV, PV, AC, SPI, CPI) por actividad | D27: Esp. Planificación | E27: Mensual
A28: P1_Avance_FF | B28: 1 Planificación y control | C28: Avance físico y financiero consolidado por componente | D28: Esp. Planificación | E28: Mensual
A29: P1_Riesgos | B29: 1 Planificación y control | C29: Registro de riesgos, puntaje P×I, respuesta y riesgo residual | D29: Esp. Planificación | E29: Mensual
A30: P2_Focalizacion | B30: 1 Planificación y control | C30: Metas, cobertura, índice de focalización e inversión por departamento | D30: Esp. Social | E30: Mensual
A31: F1_Presupuesto_PEP | B31: 2 Gestión fiduciaria | C31: Presupuesto por componente y fuente, PEP a 5 años y ejecución | D31: Esp. Financiero | E31: Trimestral
A32: F2_Ejecucion | B32: 2 Gestión fiduciaria | C32: Libro de gastos: fuente única de la ejecución | D32: Esp. Financiero | E32: Continua
A33: F3_Desembolsos | B33: 2 Gestión fiduciaria | C33: Solicitudes de desembolso y control del anticipo (umbral de justificación) | D33: Esp. Financiero | E33: Quincenal / mensual
... A46: Listas | B46: Base | C46: Listas desplegables | D46: Esp. Planificación | E46: Cuando cambie

Sheet Tablero
A1: Tablero de control de la UGP — Programa de Integración Académica y Comunitaria para Jóvenes
A2: DATOS SIMULADOS con fines de demostración metodológica — no son cifras reales del BID ni de la Dirección de Integración.
A3: Fecha de corte: | B3: =Fecha_Corte -> 46568 | C3: =Estado_Controles -> TODOS LOS CONTROLES OK
A5: Indicador clave | B5: Valor | C5: Referencia | D5: Semáforo
A6: Presupuesto total del Programa (USD) | B6: =Total_Programa -> 104000000
A7: Ejecutado acumulado (USD) | B7: =F1_Presupuesto_PEP!N10 -> 2728350
A8: % ejecutado sobre el total del Programa | B8: =F1_Presupuesto_PEP!O10 -> 0.026234135
A9: Avance físico del POA (real vs. planificado a la fecha) | B9: =P1_Avance_FF!F10 -> 0.44792308 | C9: =P1_Avance_FF!G10 -> 0.52567146 | D9: =IF(B9/C9>=Umbral_Verde,"Verde",IF(B9/C9>=Umbral_Amarillo,"Amarillo","Rojo")) -> Amarillo
A10: Avance financiero del POA (ejecutado / presupuesto POA) | B10: =P1_Avance_FF!E10 -> 0.41974615 | C10: =P1_Avance_FF!G10 -> 0.52567146
A11: SPI — índice de desempeño del cronograma | B11: =P1_Avance_FF!J10 -> 0.852097 | C11: 1 | D11: =IF(B11>=EVM_Verde,"Verde",IF(B11>=EVM_Amarillo,"Amarillo","Rojo")) -> Amarillo
A12: CPI — índice de desempeño del costo | B12: =P1_Avance_FF!K10 -> 1.0671285 | C12: 1 | D12: =IF(B12>=EVM_Verde,"Verde",IF(B12>=EVM_Amarillo,"Amarillo","Rojo")) -> Verde
A13: Total desembolsado por el BID (USD) | B13: =F3_Desembolsos!L13 -> 2996450
A14: % de anticipos justificado | B14: =F3_Desembolsos!L8 -> 0.69822917 | C14: =Pct_Justif_Min -> 0.8 | D14: =IF(B14>=C14,"Verde",IF(B14>=C14-0.1,"Amarillo","Rojo")) -> Rojo
A15: Procesos de adquisición atrasados | B15: =COUNTIF(F4_Plan_Adquisiciones!$P$5:$P$200,"Atrasado") -> 1 | C15: 0 | D15: =IF(B15=0,"Verde",IF(B15<=2,"Amarillo","Rojo")) -> Amarillo
A16: No Objeciones pendientes fuera del plazo de referencia | B16: =COUNTIF(A3_No_Objeciones!$I$5:$I$200,"Pendiente fuera de referencia") -> 1 | C16: 0 | D16: =IF(B16=0,"Verde",IF(B16<=2,"Amarillo","Rojo")) -> Amarillo
A17: Compromisos con el BID vencidos | B17: =COUNTIFS(A2_Misiones_BID!$E$14:$E$100,"<"&Fecha_Corte,A2_Misiones_BID!$G$14:$G$100,"<>Cumplido",A2_Misiones_BID!$A$14:$A$100,"CM-*") -> 2 | C17: 0 | D17: =IF(B17=0,"Verde",IF(B17<=2,"Amarillo","Rojo")) -> Amarillo
A18: Riesgos altos abiertos | B18: =COUNTIFS(P1_Riesgos!$H$5:$H$200,"Alto",P1_Riesgos!$M$5:$M$200,"<>Cerrado") -> 3 | C18: 0 | D18: =IF(B18=0,"Verde",IF(B18<=2,"Amarillo","Rojo")) -> Rojo
A19: Obligaciones normativas vencidas | B19: =N1_Cumplimiento!O8 -> 1 | C19: 0 | D19: =IF(B19=0,"Verde",IF(B19<=2,"Amarillo","Rojo")) -> Amarillo
A20: % de cumplimiento de obligaciones exigibles | B20: =N1_Cumplimiento!O10 -> 0.88888889 | C20: 1 | D20: =IF(B20>=Umbral_Verde,"Verde",IF(B20>=Umbral_Amarillo,"Amarillo","Rojo")) -> Amarillo
A21: Cobertura de la meta de beneficiarios del año 1 (vs. fracción del año) | B21: =P2_Focalizacion!K19 -> 0.39666667 | C21: =Frac_Anio -> 0.49281314 | D21: =IF(B21/C21>=Umbral_Verde,"Verde",IF(B21/C21>=Umbral_Amarillo,"Amarillo","Rojo")) -> Amarillo
A24: Mapa de calor de riesgos abiertos (n.º de riesgos por probabilidad × impacto)
A25: Impacto ↓ / Probabilidad → | B25: 1 | C25: 2 | D25: 3 | E25: 4 | F25: 5
A26: 5 | B26: =COUNTIFS(P1_Riesgos!$E$5:$E$200,B$25,P1_Riesgos!$F$5:$F$200,$A26,P1_Riesgos!$M$5:$M$200,"<>Cerrado") -> 0 | C26: =COUNTIFS(P1_Riesgos!$E$5:$E$200,C$25,P1_Riesgos!$F$5:$F$200,$A26,P1_Riesgos!$M$5:$M$200,"<>Cerrado") -> 1 | D26: =COUNTIFS(P1_Riesgos!$E$5:$E$200,D$25,P1_Riesgos!$F$5:$F$200,$A26,P1_Riesgos!$M$5:$M$200,"<>Cerrado") -> 1 | E26: =COUNTIFS(P1_Riesgos!$E$5:$E$200,E$25,P1_Riesgos!$F$5:$F$200,$A26,P1_Riesgos!$M$5:$M$200,"<>Cerrado") -> 0 | F26: =COUNTIFS(P1_Riesgos!$E$5:$E$200,F$25,P1_Riesgos!$F$5:$F$200,$A26,P1_Riesgos!$M$5:$M$200,"<>Cerrado") -> 0
A27: 4 | B27: =COUNTIFS(P1_Riesgos!$E$5:$E$200,B$25,P1_Riesgos!$F$5:$F$200,$A27,P1_Riesgos!$M$5:$M$200,"<>Cerrado") -> 1 | C27: =COUNTIFS(P1_Riesgos!$E$5:$E$200,C$25,P1_Riesgos!$F$5:$F$200,$A27,P1_Riesgos!$M$5:$M$200,"<>Cerrado") -> 2 | D27: =COUNTIFS(P1_Riesgos!$E$5:$E$200,D$25,P1_Riesgos!$F$5:$F$200,$A27,P1_Riesgos!$M$5:$M$200,"<>Cerrado") -> 5 | E27: =COUNTIFS(P1_Riesgos!$E$5:$E$200,E$25,P1_Riesgos!$F$5:$F$200,$A27,P1_Riesgos!$M$5:$M$200,"<>Cerrado") -> 2 | F27: =COUNTIFS(P1_Riesgos!$E$5:$E$200,F$25,P1_Riesgos!$F$5:$F$200,$A27,P1_Riesgos!$M$5:$M$200,"<>Cerrado") -> 0
A28: 3 | B28: =COUNTIFS(P1_Riesgos!$E$5:$E$200,B$25,P1_Riesgos!$F$5:$F$200,$A28,P1_Riesgos!$M$5:$M$200,"<>Cerrado") -> 0 | C28: =COUNTIFS(P1_Riesgos!$E$5:$E$200,C$25,P1_Riesgos!$F$5:$F$200,$A28,P1_Riesgos!$M$5:$M$200,"<>Cerrado") -> 0 | D28: =COUNTIFS(P1_Riesgos!$E$5:$E$200,D$25,P1_Riesgos!$F$5:$F$200,$A28,P1_Riesgos!$M$5:$M$200,"<>Cerrado") -> 2 | E28: =COUNTIFS(P1_Riesgos!$E$5:$E$200,E$25,P1_Riesgos!$F$5:$F$200,$A28,P1_Riesgos!$M$5:$M$200,"<>Cerrado") -> 1 | F28: =COUNTIFS(P1_Riesgos!$E$5:$E$200,F$25,P1_Riesgos!$F$5:$F$200,$A28,P1_Riesgos!$M$5:$M$200,"<>Cerrado") -> 0
A29: 2 | B29: =COUNTIFS(P1_Riesgos!$E$5:$E$200,B$25,P1_Riesgos!$F$5:$F$200,$A29,P1_Riesgos!$M$5:$M$200,"<>Cerrado") -> 0 | C29: =COUNTIFS(P1_Riesgos!$E$5:$E$200,C$25,P1_Riesgos!$F$5:$F$200,$A29,P1_Riesgos!$M$5:$M$200,"<>Cerrado") -> 0 | D29: =COUNTIFS(P1_Riesgos!$E$5:$E$200,D$25,P1_Riesgos!$F$5:$F$200,$A29,P1_Riesgos!$M$5:$M$200,"<>Cerrado") -> 0 | E29: =COUNTIFS(P1_Riesgos!$E$5:$E$200,E$25,P1_Riesgos!$F$5:$F$200,$A29,P1_Riesgos!$M$5:$M$200,"<>Cerrado") -> 0 | F29: =COUNTIFS(P1_Riesgos!$E$5:$E$200,F$25,P1_Riesgos!$F$5:$F$200,$A29,P1_Riesgos!$M$5:$M$200,"<>Cerrado") -> 0
A30: 1 | B30: =COUNTIFS(P1_Riesgos!$E$5:$E$200,B$25,P1_Riesgos!$F$5:$F$200,$A30,P1_Riesgos!$M$5:$M$200,"<>Cerrado") -> 0 | C30: =COUNTIFS(P1_Riesgos!$E$5:$E$200,C$25,P1_Riesgos!$F$5:$F$200,$A30,P1_Riesgos!$M$5:$M$200,"<>Cerrado") -> 0 | D30: =COUNTIFS(P1_Riesgos!$E$5:$E$200,D$25,P1_Riesgos!$F$5:$F$200,$A30,P1_Riesgos!$M$5:$M$200,"<>Cerrado") -> 0 | E30: =COUNTIFS(P1_Riesgos!$E$5:$E$200,E$25,P1_Riesgos!$F$5:$F$200,$A30,P1_Riesgos!$M$5:$M$200,"<>Cerrado") -> 0 | F30: =COUNTIFS(P1_Riesgos!$E$5:$E$200,F$25,P1_Riesgos!$F$5:$F$200,$A30,P1_Riesgos!$M$5:$M$200,"<>Cerrado") -> 0

Sheet Parametros
A1: Parámetros del Programa y del sistema de control
A2: DATOS SIMULADOS con fines de demostración metodológica — no son cifras reales del BID ni de la Dirección de Integración.
A3: Celdas azules = entradas editables. Las celdas con nombre (p. ej. Fecha_Corte) alimentan todas las hojas.
A4: Grupo | B4: Parámetro | C4: Valor | D4: Unidad | E4: Nombre en fórmulas | F4: Fuente / nota
A5: Programa | B5: Programa | C5: Programa de Integración Académica y Comunitaria para Jóvenes en El Salvador | F5: TDR, carátula
A6: Programa | B6: Operaciones BID | C6: ES-L1175 y ES-J0003 | F6: TDR; CCLIP ES-O0023
A7: Programa | B7: Contrato de Préstamo | C7: 6153/OC-ES | F7: TDR (el texto del usuario decía «6153 OCS»; el TDR dice 6153/OC-ES)
A8: Programa | B8: Convenio de Financiamiento No Reembolsable | C8: 6154/GR-ES | F8: TDR
A9: Programa | B9: Resolución de aprobación BID | C9: DE-43/26 (24-jun-2026) | F9: TDR §I
A10: Programa | B10: Organismo Ejecutor | C10: Dirección de Integración | F10: TDR; la UGP está adscrita a la Gerencia de Cooperación Institucional
A11: Programa | B11: Monto del préstamo | C11: 100000000 | D11: USD | E11: Total_Prestamo | F11: TDR §I
A12: Programa | B12: Monto de la donación | C12: 4000000 | D12: USD | E12: Total_Donacion | F12: TDR §I
A13: Programa | B13: Total financiamiento BID | C13: =C11+C12 -> 104000000 | D13: USD | E13: Total_Programa | F13: Calculado
A14: Programa | B14: Duración | C14: 5 | D14: años | E14: Duracion_Anios | F14: TDR §I
A15: Calendario | B15: Fecha de inicio de ejecución (SUPUESTO) | C15: 46388 | D15: fecha | E15: Fecha_Inicio | F15: Supuesto de la demo: la fecha real depende de la entrada en vigencia
A16: Calendario | B16: Fecha de corte del reporte (SIMULADA) | C16: 46568 | D16: fecha | E16: Fecha_Corte | F16: Cambie esta fecha y todo el sistema se recalcula
A17: Calendario | B17: Año del programa a la fecha de corte | C17: =INT((Fecha_Corte-Fecha_Inicio)/365.25)+1 -> 1 | D17: año | E17: Anio_Programa | F17: Calculado
A18: Calendario | B18: Fracción transcurrida del año del programa | C18: =(Fecha_Corte-Fecha_Inicio)/365.25-(Anio_Programa-1) -> 0.49281314 | D18: % | E18: Frac_Anio | F18: Calculado
A19: Calendario | B19: Inicio de la consultoría del Coordinador General (SUPUESTO) | C19: 46391 | D19: fecha | E19: Inicio_Consultoria | F19: Supuesto: plazo de 12 meses desde la firma (TDR §VIII)
A20: Consultoría | B20: Honorario mensual del Coordinador General | C20: 4200 | D20: USD | E20: Pago_Mensual | F20: TDR §XII (US$50,400 en 12 pagos)
A21: Consultoría | B21: Plazo de entrega del informe mensual | C21: 3 | D21: días hábiles | E21: Plazo_Informe | F21: TDR §VII: tres días hábiles posteriores al cierre del mes
A22: Semáforos | B22: Indicadores: umbral verde (cumplimiento ≥) | C22: 0.9 | D22: ratio | E22: Umbral_Verde | F22: Criterio de gestión propuesto
A23: Semáforos | B23: Indicadores: umbral amarillo (cumplimiento ≥) | C23: 0.7 | D23: ratio | E23: Umbral_Amarillo | F23: Criterio de gestión propuesto
A24: Semáforos | B24: SPI/CPI: umbral verde (≥) | C24: 0.95 | D24: ratio | E24: EVM_Verde | F24: Criterio de gestión propuesto
A25: Semáforos | B25: SPI/CPI: umbral amarillo (≥) | C25: 0.85 | D25: ratio | E25: EVM_Amarillo | F25: Criterio de gestión propuesto
A26: Semáforos | B26: Riesgo ALTO si probabilidad×impacto ≥ | C26: 15 | D26: puntos | E26: Riesgo_Alto | F26: Escala 1-5 × 1-5
A27: Semáforos | B27: Riesgo MEDIO si probabilidad×impacto ≥ | C27: 8 | D27: puntos | E27: Riesgo_Medio | F27: Escala 1-5 × 1-5
A28: Semáforos | B28: Alerta de vencimiento (días antes) | C28: 30 | D28: días | E28: Dias_Alerta | F28: Criterio de gestión propuesto
A29: Fiduciario | B29: Justificación mínima de anticipos para pedir uno nuevo | C29: 0.8 | D29: % | E29: Pct_Justif_Min | F29: A VALIDAR con el Contrato de Préstamo / guía de gestión financiera del BID
A30: Fiduciario | B30: Plazo de referencia de trámite de No Objeción | C30: 15 | D30: días | E30: Plazo_NO | F30: Referencia INTERNA de la UGP, no un plazo del BID
... A38: Focalización | B38: Meta de beneficiarios a 5 años (SIMULADA) | C38: 60000 | D38: personas | E38: Meta_Benef_5A | F38: Dato sintético

Sheet Controles
A1: Controles de integridad del sistema
A2: DATOS SIMULADOS con fines de demostración metodológica — no son cifras reales del BID ni de la Dirección de Integración.
A3: Pruebas automáticas de consistencia entre hojas. Cualquier «REVISAR» debe corregirse antes de emitir el informe mensual.
A4: N.º | B4: Control | C4: Esperado | D4: Calculado | E4: Diferencia | F4: Estado
A5: 1 | B5: Presupuesto por componentes = total del Programa (USD) | C5: =Total_Programa -> 104000000 | D5: =F1_Presupuesto_PEP!E10 -> 104000000 | E5: =D5-C5 -> 0 | F5: =IF(ROUND(E5,0)=0,"OK","REVISAR") -> OK
A6: 2 | B6: Total préstamo asignado = monto del Contrato 6153/OC-ES | C6: =Total_Prestamo -> 100000000 | D6: =F1_Presupuesto_PEP!C10 -> 100000000 | E6: =D6-C6 -> 0 | F6: =IF(ROUND(E6,0)=0,"OK","REVISAR") -> OK
A7: 3 | B7: Total donación asignada = monto del Convenio 6154/GR-ES | C7: =Total_Donacion -> 4000000 | D7: =F1_Presupuesto_PEP!D10 -> 4000000 | E7: =D7-C7 -> 0 | F7: =IF(ROUND(E7,0)=0,"OK","REVISAR") -> OK
A8: 4 | B8: Componentes cuyo PEP a 5 años no coincide con lo asignado | C8: 0 | D8: =COUNTIF(F1_Presupuesto_PEP!M5:M9,"REVISAR") -> 0 | E8: =D8-C8 -> 0 | F8: =IF(ROUND(E8,0)=0,"OK","REVISAR") -> OK
A9: 5 | B9: Plan financiero del año 1 = presupuesto POA (USD) | C9: =P1_Avance_FF!C10 -> 6500000 | D9: =SUM(F3_Plan_Financiero!D5:D8) -> 6500000 | E9: =D9-C9 -> 0 | F9: =IF(ROUND(E9,0)=0,"OK","REVISAR") -> OK
A10: 6 | B10: Ejecución acumulada ≤ presupuesto total (USD) | C10: =F1_Presupuesto_PEP!E10 -> 104000000 | D10: =F1_Presupuesto_PEP!N10 -> 2728350 | E10: =D10-C10 -> -101271650 | F10: =IF(D10<=C10,"OK","REVISAR") -> OK
A11: 7 | B11: Actividades POA con ejecutado > presupuesto | C11: 0 | D11: =SUMPRODUCT(--(P1_POA!$J$5:$J$200>P1_POA!$G$5:$G$200)) -> 0 | E11: =D11-C11 -> 0 | F11: =IF(ROUND(E11,0)=0,"OK","REVISAR") -> OK
A12: 8 | B12: Contratos con pagos > monto contratado | C12: 0 | D12: =SUM(F5_Contratos!$P$5:$P$200) -> 0 | E12: =D12-C12 -> 0 | F12: =IF(ROUND(E12,0)=0,"OK","REVISAR") -> OK
A13: 9 | B13: Gastos cuyo componente no coincide con el de su actividad | C13: 0 | D13: =SUM(F2_Ejecucion!$N$5:$N$500) -> 0 | E13: =D13-C13 -> 0 | F13: =IF(ROUND(E13,0)=0,"OK","REVISAR") -> OK
A14: 10 | B14: Gastos fuera del período [inicio, corte] | C14: 0 | D14: =COUNTIFS(F2_Ejecucion!$B$5:$B$500,"<"&Fecha_Inicio)+COUNTIFS(F2_Ejecucion!$B$5:$B$500,">"&Fecha_Corte) -> 0 | E14: =D14-C14 -> 0 | F14: =IF(ROUND(E14,0)=0,"OK","REVISAR") -> OK
A15: 11 | B15: Gastos con contrato inexistente en F5 | C15: 0 | D15: =SUMPRODUCT((F2_Ejecucion!$E$5:$E$500<>"")*(COUNTIF(F5_Contratos!$A$5:$A$200,F2_Ejecucion!$E$5:$E$500)=0)) -> 0 | E15: =D15-C15 -> 0 | F15: =IF(ROUND(E15,0)=0,"OK","REVISAR") -> OK
A16: 12 | B16: Gastos con actividad inexistente en el POA | C16: 0 | D16: =SUMPRODUCT((F2_Ejecucion!$D$5:$D$500<>"")*(COUNTIF(P1_POA!$A$5:$A$200,F2_Ejecucion!$D$5:$D$500)=0)) -> 0 | E16: =D16-C16 -> 0 | F16: =IF(ROUND(E16,0)=0,"OK","REVISAR") -> OK
A17: 13 | B17: Pagos directos del libro = desembolsos por pago directo (USD) | C17: =F3_Desembolsos!L12 -> 596450 | D17: =F3_Desembolsos!L11 -> 596450 | E17: =D17-C17 -> 0 | F17: =IF(ROUND(E17,0)=0,"OK","REVISAR") -> OK
A18: 14 | B18: Meta nacional de beneficiarios = suma de departamentos | C18: =Meta_Benef_5A -> 60000 | D18: =P2_Focalizacion!E19 -> 60000 | E18: =D18-C18 -> 0 | F18: =IF(ROUND(E18,0)=0,"OK","REVISAR") -> OK
A19: 15 | B19: Inversión territorializada ≤ ejecución total (USD) | C19: =F1_Presupuesto_PEP!N10 -> 2728350 | D19: =P2_Focalizacion!P19 -> 735000 | E19: =D19-C19 -> -1993350 | F19: =IF(D19<=C19,"OK","REVISAR") -> OK
A20: 16 | B20: Procesos RACI sin una única «A» | C20: 0 | D20: =COUNTIF(A1_RACI!J5:J40,"REVISAR") -> 0 | E20: =D20-C20 -> 0 | F20: =IF(ROUND(E20,0)=0,"OK","REVISAR") -> OK
B22: Resultado global | C22: =IF(COUNTIF(F5:F20,"REVISAR")=0,"TODOS LOS CONTROLES OK","REVISAR "&COUNTIF(F5:F20,"REVISAR")&" CONTROL(ES)") -> TODOS LOS CONTROLES OK

Sheet P1_Resultados
A1: P1 · Matriz de resultados e indicadores (marco lógico ilustrativo)
A2: DATOS SIMULADOS con fines de demostración metodológica — no son cifras reales del BID ni de la Dirección de Integración.
A3: Meta esperada al corte: acumulativa = interpolación lineal dentro del año · anual = meta × fracción del año · nivel = meta del año. Cumplimiento = valor actual / esperado. Los indicadores sin medición en el período quedan «Sin dato».
A4: ID | B4: Nivel | C4: Indicador | D4: Unidad | E4: Comp. | F4: Línea base | G4: Tipo de meta | H4: Meta año 1 | I4: Meta año 2 | J4: Meta año 3 | K4: Meta año 4 | L4: Meta año 5 | M4: Meta final | N4: Valor actual | O4: Esperado al corte | P4: Cumplimiento | Q4: Semáforo | R4: Fuente de verificación | S4: Frecuencia | T4: Responsable
A5: I-01 | B5: Resultado | C5: Beneficiarios que continúan en educación postsecundaria al 2.º año | D5: % | E5: C2 | F5: 0.7 | G5: Nivel | H5: 0.7 | I5: 0.72 | J5: 0.76 | K5: 0.81 | L5: 0.85 | M5: =L5 -> 0.85 | O5: =IF(G5="Nivel",INDEX(H5:L5,Anio_Programa),IF(G5="Anual",INDEX(H5:L5,Anio_Programa)*Frac_Anio,IF(Anio_Programa=1,F5,INDEX(H5:L5,Anio_Programa-1))+(INDEX(H5:L5,Anio_Programa)-IF(Anio_Programa=1,F5,INDEX(H5:L5,Anio_Programa-1)))*Frac_Anio)) -> 0.7 | P5: =IF(N5="","Sin dato",IF(O5=0,"n/a",N5/O5)) -> Sin dato | Q5: =IF(NOT(ISNUMBER(P5)),"Sin dato",IF(P5>=Umbral_Verde,"Verde",IF(P5>=Umbral_Amarillo,"Amarillo","Rojo"))) -> Sin dato | R5: Sistema de información de trayectorias | S5: Anual | T5: Esp. Planificación, M&S
A6: I-02 | B6: Resultado | C6: Beneficiarios que se gradúan en el tiempo previsto | D6: % | E6: C2 | F6: 0.4 | G6: Nivel | H6: 0.4 | I6: 0.42 | J6: 0.48 | K6: 0.54 | L6: 0.6 | M6: =L6 -> 0.6 | O6: =IF(G6="Nivel",INDEX(H6:L6,Anio_Programa),IF(G6="Anual",INDEX(H6:L6,Anio_Programa)*Frac_Anio,IF(Anio_Programa=1,F6,INDEX(H6:L6,Anio_Programa-1))+(INDEX(H6:L6,Anio_Programa)-IF(Anio_Programa=1,F6,INDEX(H6:L6,Anio_Programa-1)))*Frac_Anio)) -> 0.4 | P6: =IF(N6="","Sin dato",IF(O6=0,"n/a",N6/O6)) -> Sin dato | Q6: =IF(NOT(ISNUMBER(P6)),"Sin dato",IF(P6>=Umbral_Verde,"Verde",IF(P6>=Umbral_Amarillo,"Amarillo","Rojo"))) -> Sin dato | R6: Registros de las instituciones | S6: Anual | T6: Esp. Planificación, M&S
A7: I-03 | B7: Resultado | C7: Personas graduadas vinculadas al empleo formal en 12 meses | D7: % | E7: C3 | F7: 0.25 | G7: Nivel | H7: 0.25 | I7: 0.25 | J7: 0.3 | K7: 0.38 | L7: 0.45 | M7: =L7 -> 0.45 | O7: =IF(G7="Nivel",INDEX(H7:L7,Anio_Programa),IF(G7="Anual",INDEX(H7:L7,Anio_Programa)*Frac_Anio,IF(Anio_Programa=1,F7,INDEX(H7:L7,Anio_Programa-1))+(INDEX(H7:L7,Anio_Programa)-IF(Anio_Programa=1,F7,INDEX(H7:L7,Anio_Programa-1)))*Frac_Anio)) -> 0.25 | P7: =IF(N7="","Sin dato",IF(O7=0,"n/a",N7/O7)) -> Sin dato | Q7: =IF(NOT(ISNUMBER(P7)),"Sin dato",IF(P7>=Umbral_Verde,"Verde",IF(P7>=Umbral_Amarillo,"Amarillo","Rojo"))) -> Sin dato | R7: Encuesta de seguimiento y registros de empleo | S7: Anual | T7: Esp. Planificación, M&S
A8: P-01 | B8: Producto | C8: Estudiantes de educación media con orientación vocacional (acum.) | D8: personas | E8: C1 | F8: 0 | G8: Acumulativa | H8: 4000 | I8: 12000 | J8: 24000 | K8: 38000 | L8: 50000 | M8: =L8 -> 50000 | N8: 1650 | O8: =IF(G8="Nivel",INDEX(H8:L8,Anio_Programa),IF(G8="Anual",INDEX(H8:L8,Anio_Programa)*Frac_Anio,IF(Anio_Programa=1,F8,INDEX(H8:L8,Anio_Programa-1))+(INDEX(H8:L8,Anio_Programa)-IF(Anio_Programa=1,F8,INDEX(H8:L8,Anio_Programa-1)))*Frac_Anio)) -> 1971.2526 | P8: =IF(N8="","Sin dato",IF(O8=0,"n/a",N8/O8)) -> 0.83703125 | Q8: =IF(NOT(ISNUMBER(P8)),"Sin dato",IF(P8>=Umbral_Verde,"Verde",IF(P8>=Umbral_Amarillo,"Amarillo","Rojo"))) -> Amarillo | R8: Registro de participantes | S8: Mensual | T8: Esp. Social
A9: P-02 | B9: Producto | C9: Jóvenes beneficiarios con apoyo y acompañamiento (acum.) | D9: personas | E9: C2 | F9: 0 | G9: Acumulativa | H9: 6000 | I9: 16000 | J9: 30000 | K9: 46000 | L9: 60000 | M9: =L9 -> 60000 | N9: =P2_Focalizacion!G19 -> 2380 | O9: =IF(G9="Nivel",INDEX(H9:L9,Anio_Programa),IF(G9="Anual",INDEX(H9:L9,Anio_Programa)*Frac_Anio,IF(Anio_Programa=1,F9,INDEX(H9:L9,Anio_Programa-1))+(INDEX(H9:L9,Anio_Programa)-IF(Anio_Programa=1,F9,INDEX(H9:L9,Anio_Programa-1)))*Frac_Anio)) -> 2956.8789 | P9: =IF(N9="","Sin dato",IF(O9=0,"n/a",N9/O9)) -> 0.80490278 | Q9: =IF(NOT(ISNUMBER(P9)),"Sin dato",IF(P9>=Umbral_Verde,"Verde",IF(P9>=Umbral_Amarillo,"Amarillo","Rojo"))) -> Amarillo | R9: P2_Focalizacion | S9: Mensual | T9: Esp. Social
A10: P-03 | B10: Producto | C10: Madres jóvenes atendidas (acum.) | D10: personas | E10: C2 | F10: 0 | G10: Acumulativa | H10: 540 | I10: 1440 | J10: 2700 | K10: 4140 | L10: 5400 | M10: =L10 -> 5400 | N10: =P2_Focalizacion!H19 -> 223 | O10: =IF(G10="Nivel",INDEX(H10:L10,Anio_Programa),IF(G10="Anual",INDEX(H10:L10,Anio_Programa)*Frac_Anio,IF(Anio_Programa=1,F10,INDEX(H10:L10,Anio_Programa-1))+(INDEX(H10:L10,Anio_Programa)-IF(Anio_Programa=1,F10,INDEX(H10:L10,Anio_Programa-1)))*Frac_Anio)) -> 266.1191 | P10: =IF(N10="","Sin dato",IF(O10=0,"n/a",N10/O10)) -> 0.83797068 | Q10: =IF(NOT(ISNUMBER(P10)),"Sin dato",IF(P10>=Umbral_Verde,"Verde",IF(P10>=Umbral_Amarillo,"Amarillo","Rojo"))) -> Amarillo | R10: P2_Focalizacion | S10: Mensual | T10: Esp. Social
A11: P-04 | B11: Producto | C11: Personas con discapacidad atendidas (acum.) | D11: personas | E11: C2 | F11: 0 | G11: Acumulativa | H11: 240 | I11: 640 | J11: 1200 | K11: 1840 | L11: 2400 | M11: =L11 -> 2400 | N11: =P2_Focalizacion!I19 -> 90 | O11: =IF(G11="Nivel",INDEX(H11:L11,Anio_Programa),IF(G11="Anual",INDEX(H11:L11,Anio_Programa)*Frac_Anio,IF(Anio_Programa=1,F11,INDEX(H11:L11,Anio_Programa-1))+(INDEX(H11:L11,Anio_Programa)-IF(Anio_Programa=1,F11,INDEX(H11:L11,Anio_Programa-1)))*Frac_Anio)) -> 118.27515 | P11: =IF(N11="","Sin dato",IF(O11=0,"n/a",N11/O11)) -> 0.7609375 | Q11: =IF(NOT(ISNUMBER(P11)),"Sin dato",IF(P11>=Umbral_Verde,"Verde",IF(P11>=Umbral_Amarillo,"Amarillo","Rojo"))) -> Amarillo | R11: P2_Focalizacion | S11: Mensual | T11: Esp. Social
A12: P-05 | B12: Producto | C12: Personas retornadas atendidas (acum.) | D12: personas | E12: C2 | F12: 0 | G12: Acumulativa | H12: 180 | I12: 480 | J12: 900 | K12: 1380 | L12: 1800 | M12: =L12 -> 1800 | N12: =P2_Focalizacion!J19 -> 75 | O12: =IF(G12="Nivel",INDEX(H12:L12,Anio_Programa),IF(G12="Anual",INDEX(H12:L12,Anio_Programa)*Frac_Anio,IF(Anio_Programa=1,F12,INDEX(H12:L12,Anio_Programa-1))+(INDEX(H12:L12,Anio_Programa)-IF(Anio_Programa=1,F12,INDEX(H12:L12,Anio_Programa-1)))*Frac_Anio)) -> 88.706366 | P12: =IF(N12="","Sin dato",IF(O12=0,"n/a",N12/O12)) -> 0.84548611 | Q12: =IF(NOT(ISNUMBER(P12)),"Sin dato",IF(P12>=Umbral_Verde,"Verde",IF(P12>=Umbral_Amarillo,"Amarillo","Rojo"))) -> Amarillo | R12: P2_Focalizacion | S12: Mensual | T12: Esp. Social
A13: P-06 | B13: Producto | C13: Convenios firmados con instituciones de educación postsecundaria (acum.) | D13: convenios | E13: C4 | F13: 0 | G13: Acumulativa | H13: 8 | I13: 20 | J13: 30 | K13: 36 | L13: 40 | M13: =L13 -> 40 | N13: 6 | O13: =IF(G13="Nivel",INDEX(H13:L13,Anio_Programa),IF(G13="Anual",INDEX(H13:L13,Anio_Programa)*Frac_Anio,IF(Anio_Programa=1,F13,INDEX(H13:L13,Anio_Programa-1))+(INDEX(H13:L13,Anio_Programa)-IF(Anio_Programa=1,F13,INDEX(H13:L13,Anio_Programa-1)))*Frac_Anio)) -> 3.9425051 | P13: =IF(N13="","Sin dato",IF(O13=0,"n/a",N13/O13)) -> 1.521875 | Q13: =IF(NOT(ISNUMBER(P13)),"Sin dato",IF(P13>=Umbral_Verde,"Verde",IF(P13>=Umbral_Amarillo,"Amarillo","Rojo"))) -> Verde | R13: Convenios archivados | S13: Mensual | T13: Esp. Social
A14: P-07 | B14: Producto | C14: Empleadores aliados activos (acum.) | D14: empleadores | E14: C3 | F14: 0 | G14: Acumulativa | H14: 20 | I14: 60 | J14: 120 | K14: 180 | L14: 250 | M14: =L14 -> 250 | N14: 7 | O14: =IF(G14="Nivel",INDEX(H14:L14,Anio_Programa),IF(G14="Anual",INDEX(H14:L14,Anio_Programa)*Frac_Anio,IF(Anio_Programa=1,F14,INDEX(H14:L14,Anio_Programa-1))+(INDEX(H14:L14,Anio_Programa)-IF(Anio_Programa=1,F14,INDEX(H14:L14,Anio_Programa-1)))*Frac_Anio)) -> 9.8562628 | P14: =IF(N14="","Sin dato",IF(O14=0,"n/a",N14/O14)) -> 0.71020833 | Q14: =IF(NOT(ISNUMBER(P14)),"Sin dato",IF(P14>=Umbral_Verde,"Verde",IF(P14>=Umbral_Amarillo,"Amarillo","Rojo"))) -> Amarillo | R14: Alianzas firmadas | S14: Mensual | T14: Esp. Social
A15: P-08 | B15: Producto | C15: Instituciones con plan de fortalecimiento en implementación (acum.) | D15: instituciones | E15: C4 | F15: 0 | G15: Acumulativa | H15: 3 | I15: 12 | J15: 25 | K15: 35 | L15: 40 | M15: =L15 -> 40 | N15: 0 | O15: =IF(G15="Nivel",INDEX(H15:L15,Anio_Programa),IF(G15="Anual",INDEX(H15:L15,Anio_Programa)*Frac_Anio,IF(Anio_Programa=1,F15,INDEX(H15:L15,Anio_Programa-1))+(INDEX(H15:L15,Anio_Programa)-IF(Anio_Programa=1,F15,INDEX(H15:L15,Anio_Programa-1)))*Frac_Anio)) -> 1.4784394 | P15: =IF(N15="","Sin dato",IF(O15=0,"n/a",N15/O15)) -> 0 | Q15: =IF(NOT(ISNUMBER(P15)),"Sin dato",IF(P15>=Umbral_Verde,"Verde",IF(P15>=Umbral_Amarillo,"Amarillo","Rojo"))) -> Rojo | R15: Informes de capacitación | S15: Trimestral | T15: Esp. Social
A16: P-09 | B16: Producto | C16: Sistema de información de trayectorias: módulos operativos | D16: % | E16: C4 | F16: 0 | G16: Acumulativa | H16: 0.8 | I16: 1 | J16: 1 | K16: 1 | L16: 1 | M16: =L16 -> 1 | N16: 0.35 | O16: =IF(G16="Nivel",INDEX(H16:L16,Anio_Programa),IF(G16="Anual",INDEX(H16:L16,Anio_Programa)*Frac_Anio,IF(Anio_Programa=1,F16,INDEX(H16:L16,Anio_Programa-1))+(INDEX(H16:L16,Anio_Programa)-IF(Anio_Programa=1,F16,INDEX(H16:L16,Anio_Programa-1)))*Frac_Anio)) -> 0.39425051 | P16: =IF(N16="","Sin dato",IF(O16=0,"n/a",N16/O16)) -> 0.88776042 | Q16: =IF(NOT(ISNUMBER(P16)),"Sin dato",IF(P16>=Umbral_Verde,"Verde",IF(P16>=Umbral_Amarillo,"Amarillo","Rojo"))) -> Amarillo | R16: Actas de recepción por módulo | S16: Mensual | T16: Esp. Planificación, M&S
A17: G-01 | B17: Gestión | C17: Ejecución financiera acumulada del Programa (% del total) | D17: % | E17: Todos | F17: 0 | G17: Acumulativa | H17: =SUM(F1_Presupuesto_PEP!$G$10:G$10)/Total_Programa -> 0.0625 | I17: =SUM(F1_Presupuesto_PEP!$G$10:H$10)/Total_Programa -> 0.26865385 | J17: =SUM(F1_Presupuesto_PEP!$G$10:I$10)/Total_Programa -> 0.54990385 | K17: =SUM(F1_Presupuesto_PEP!$G$10:J$10)/Total_Programa -> 0.8125 | L17: =SUM(F1_Presupuesto_PEP!$G$10:K$10)/Total_Programa -> 1 | M17: =L17 -> 1 | N17: =F1_Presupuesto_PEP!O10 -> 0.026234135 | O17: =IF(G17="Nivel",INDEX(H17:L17,Anio_Programa),IF(G17="Anual",INDEX(H17:L17,Anio_Programa)*Frac_Anio,IF(Anio_Programa=1,F17,INDEX(H17:L17,Anio_Programa-1))+(INDEX(H17:L17,Anio_Programa)-IF(Anio_Programa=1,F17,INDEX(H17:L17,Anio_Programa-1)))*Frac_Anio)) -> 0.030800821 | P17: =IF(N17="","Sin dato",IF(O17=0,"n/a",N17/O17)) -> 0.8517349 | Q17: =IF(NOT(ISNUMBER(P17)),"Sin dato",IF(P17>=Umbral_Verde,"Verde",IF(P17>=Umbral_Amarillo,"Amarillo","Rojo"))) -> Amarillo | R17: F1_Presupuesto_PEP | S17: Mensual | T17: Esp. Financiero
A18: G-02 | B18: Gestión | C18: Avance físico ponderado del POA vigente | D18: % | E18: Todos | F18: 0 | G18: Anual | H18: 1 | I18: 1 | J18: 1 | K18: 1 | L18: 1 | M18: =L18 -> 1 | N18: =P1_Avance_FF!F10 -> 0.44792308 | O18: =IF(G18="Nivel",INDEX(H18:L18,Anio_Programa),IF(G18="Anual",INDEX(H18:L18,Anio_Programa)*Frac_Anio,IF(Anio_Programa=1,F18,INDEX(H18:L18,Anio_Programa-1))+(INDEX(H18:L18,Anio_Programa)-IF(Anio_Programa=1,F18,INDEX(H18:L18,Anio_Programa-1)))*Frac_Anio)) -> 0.49281314 | P18: =IF(N18="","Sin dato",IF(O18=0,"n/a",N18/O18)) -> 0.90891058 | Q18: =IF(NOT(ISNUMBER(P18)),"Sin dato",IF(P18>=Umbral_Verde,"Verde",IF(P18>=Umbral_Amarillo,"Amarillo","Rojo"))) -> Verde | R18: P1_POA | S18: Mensual | T18: Esp. Planificación, M&S
A19: G-03 | B19: Gestión | C19: Procesos del Plan de Adquisiciones con contrato firmado | D19: % | E19: Todos | F19: 0 | G19: Nivel | H19: 0.9 | I19: 0.9 | J19: 0.9 | K19: 0.9 | L19: 0.9 | M19: =L19 -> 0.9 | N19: =COUNTIF(F4_Plan_Adquisiciones!$I$5:$I$200,"Contratado")/COUNTIF(F4_Plan_Adquisiciones!$A$5:$A$200,"PA-*") -> 0.8 | O19: =IF(G19="Nivel",INDEX(H19:L19,Anio_Programa),IF(G19="Anual",INDEX(H19:L19,Anio_Programa)*Frac_Anio,IF(Anio_Programa=1,F19,INDEX(H19:L19,Anio_Programa-1))+(INDEX(H19:L19,Anio_Programa)-IF(Anio_Programa=1,F19,INDEX(H19:L19,Anio_Programa-1)))*Frac_Anio)) -> 0.9 | P19: =IF(N19="","Sin dato",IF(O19=0,"n/a",N19/O19)) -> 0.88888889 | Q19: =IF(NOT(ISNUMBER(P19)),"Sin dato",IF(P19>=Umbral_Verde,"Verde",IF(P19>=Umbral_Amarillo,"Amarillo","Rojo"))) -> Amarillo | R19: F4_Plan_Adquisiciones | S19: Mensual | T19: Esp. Adquisiciones
A20: G-04 | B20: Gestión | C20: Informes mensuales entregados a tiempo | D20: % | E20: UGP | F20: 1 | G20: Nivel | H20: 1 | I20: 1 | J20: 1 | K20: 1 | L20: 1 | M20: =L20 -> 1 | N20: =COUNTIF(A5_Calendario_Informes!$F$5:$F$30,"Entregado a tiempo")/COUNTIF(A5_Calendario_Informes!$F$5:$F$30,"Entregado*") -> 0.8 | O20: =IF(G20="Nivel",INDEX(H20:L20,Anio_Programa),IF(G20="Anual",INDEX(H20:L20,Anio_Programa)*Frac_Anio,IF(Anio_Programa=1,F20,INDEX(H20:L20,Anio_Programa-1))+(INDEX(H20:L20,Anio_Programa)-IF(Anio_Programa=1,F20,INDEX(H20:L20,Anio_Programa-1)))*Frac_Anio)) -> 1 | P20: =IF(N20="","Sin dato",IF(O20=0,"n/a",N20/O20)) -> 0.8 | Q20: =IF(NOT(ISNUMBER(P20)),"Sin dato",IF(P20>=Umbral_Verde,"Verde",IF(P20>=Umbral_Amarillo,"Amarillo","Rojo"))) -> Amarillo | R20: A5_Calendario_Informes | S20: Mensual | T20: Coordinador General
A21: G-05 | B21: Gestión | C21: Compromisos con el BID cumplidos en plazo | D21: % | E21: UGP | F21: 1 | G21: Nivel | H21: 1 | I21: 1 | J21: 1 | K21: 1 | L21: 1 | M21: =L21 -> 1 | N21: =IFERROR(COUNTIF(A2_Misiones_BID!$I$14:$I$100,"Sí")/(COUNTIF(A2_Misiones_BID!$G$14:$G$100,"Cumplido")+COUNTIFS(A2_Misiones_BID!$E$14:$E$100,"<"&Fecha_Corte,A2_Misiones_BID!$G$14:$G$100,"<>Cumplido",A2_Misiones_BID!$A$14:$A$100,"CM-*")),"") -> 0.625 | O21: =IF(G21="Nivel",INDEX(H21:L21,Anio_Programa),IF(G21="Anual",INDEX(H21:L21,Anio_Programa)*Frac_Anio,IF(Anio_Programa=1,F21,INDEX(H21:L21,Anio_Programa-1))+(INDEX(H21:L21,Anio_Programa)-IF(Anio_Programa=1,F21,INDEX(H21:L21,Anio_Programa-1)))*Frac_Anio)) -> 1 | P21: =IF(N21="","Sin dato",IF(O21=0,"n/a",N21/O21)) -> 0.625 | Q21: =IF(NOT(ISNUMBER(P21)),"Sin dato",IF(P21>=Umbral_Verde,"Verde",IF(P21>=Umbral_Amarillo,"Amarillo","Rojo"))) -> Rojo | R21: A2_Misiones_BID | S21: Por misión | T21: Coordinador General
A22: G-06 | B22: Gestión | C22: Quejas atendidas dentro del plazo del mecanismo | D22: % | E22: C5 | F22: 0.9 | G22: Nivel | H22: 0.9 | I22: 0.9 | J22: 0.9 | K22: 0.9 | L22: 0.9 | M22: =L22 -> 0.9 | N22: 0.88 | O22: =IF(G22="Nivel",INDEX(H22:L22,Anio_Programa),IF(G22="Anual",INDEX(H22:L22,Anio_Programa)*Frac_Anio,IF(Anio_Programa=1,F22,INDEX(H22:L22,Anio_Programa-1))+(INDEX(H22:L22,Anio_Programa)-IF(Anio_Programa=1,F22,INDEX(H22:L22,Anio_Programa-1)))*Frac_Anio)) -> 0.9 | P22: =IF(N22="","Sin dato",IF(O22=0,"n/a",N22/O22)) -> 0.97777778 | Q22: =IF(NOT(ISNUMBER(P22)),"Sin dato",IF(P22>=Umbral_Verde,"Verde",IF(P22>=Umbral_Amarillo,"Amarillo","Rojo"))) -> Verde | R22: Registro del mecanismo de quejas | S22: Mensual | T22: Esp. Social

Sheet P1_POA
A1: P1 · Plan Operativo Anual (POA) e hitos — avance físico y financiero por actividad
A2: DATOS SIMULADOS con fines de demostración metodológica — no son cifras reales del BID ni de la Dirección de Integración.
A3: Valor ganado: EV = presupuesto × % avance físico · PV = presupuesto × % planificado a la fecha de corte · AC = ejecutado (libro F2). SPI = EV/PV · CPI = EV/AC.
A4: ID | B4: Comp. | C4: Actividad | D4: Responsable | E4: Inicio | F4: Fin | G4: Presupuesto POA USD | H4: % avance físico | I4: % planificado a corte | J4: Ejecutado USD (AC) | K4: % ejecución financiera | L4: EV USD | M4: PV USD | N4: SPI | O4: CPI | P4: Días de atraso | Q4: Estado | R4: Semáforo | S4: Hito / entregable
A5: C1-01 | B5: C1 | C5: Diseño del modelo de captación y orientación vocacional | D5: Esp. Social | E5: 46402 | F5: 46477 | G5: 130000 | H5: 1 | I5: =IF(Fecha_Corte<=E5,0,IF(Fecha_Corte>=F5,1,(Fecha_Corte-E5)/(F5-E5))) -> 1 | J5: =SUMIFS(F2_Ejecucion!$J$5:$J$500,F2_Ejecucion!$D$5:$D$500,A5) -> 124000 | K5: =IF(G5=0,0,J5/G5) -> 0.95384615 | L5: =G5*H5 -> 130000 | M5: =G5*I5 -> 130000 | N5: =IF(M5=0,"n/a",L5/M5) -> 1 | O5: =IF(J5=0,"n/a",L5/J5) -> 1.0483871 | P5: =IF(H5>=1,0,MAX(0,Fecha_Corte-F5)) -> 0 | Q5: =IF(H5>=1,"Completada",IF(Fecha_Corte<E5,"No iniciada",IF(Fecha_Corte>F5,"Vencida sin completar",IF(NOT(ISNUMBER(N5)),"En curso",IF(N5>=EVM_Verde,"En curso a tiempo",IF(N5>=EVM_Amarillo,"En curso con retraso leve","En curso con retraso crítico")))))) -> Completada | R5: =IF(H5>=1,"Verde",IF(NOT(ISNUMBER(N5)),"Gris",IF(N5>=EVM_Verde,"Verde",IF(N5>=EVM_Amarillo,"Amarillo","Rojo")))) -> Verde | S5: Modelo de captación aprobado
A6: C1-02 | B6: C1 | C6: Convenios con centros de educación media | D6: Esp. Social | E6: 46419 | F6: 46538 | G6: 160000 | H6: 0.9 | I6: =IF(Fecha_Corte<=E6,0,IF(Fecha_Corte>=F6,1,(Fecha_Corte-E6)/(F6-E6))) -> 1 | J6: =SUMIFS(F2_Ejecucion!$J$5:$J$500,F2_Ejecucion!$D$5:$D$500,A6) -> 128000 | K6: =IF(G6=0,0,J6/G6) -> 0.8 | L6: =G6*H6 -> 144000 | M6: =G6*I6 -> 160000 | N6: =IF(M6=0,"n/a",L6/M6) -> 0.9 | O6: =IF(J6=0,"n/a",L6/J6) -> 1.125 | P6: =IF(H6>=1,0,MAX(0,Fecha_Corte-F6)) -> 30 | Q6: =IF(H6>=1,"Completada",IF(Fecha_Corte<E6,"No iniciada",IF(Fecha_Corte>F6,"Vencida sin completar",IF(NOT(ISNUMBER(N6)),"En curso",IF(N6>=EVM_Verde,"En curso a tiempo",IF(N6>=EVM_Amarillo,"En curso con retraso leve","En curso con retraso crítico")))))) -> Vencida sin completar | R6: =IF(H6>=1,"Verde",IF(NOT(ISNUMBER(N6)),"Gris",IF(N6>=EVM_Verde,"Verde",IF(N6>=EVM_Amarillo,"Amarillo","Rojo")))) -> Amarillo | S6: Convenios firmados con centros educativos
A7: C1-03 | B7: C1 | C7: Campaña nacional de difusión | D7: Esp. Planificación, M&S | E7: 46447 | F7: 46630 | G7: 310000 | H7: 0.58 | I7: =IF(Fecha_Corte<=E7,0,IF(Fecha_Corte>=F7,1,(Fecha_Corte-E7)/(F7-E7))) -> 0.66120219 | J7: =SUMIFS(F2_Ejecucion!$J$5:$J$500,F2_Ejecucion!$D$5:$D$500,A7) -> 162500 | K7: =IF(G7=0,0,J7/G7) -> 0.52419355 | L7: =G7*H7 -> 179800 | M7: =G7*I7 -> 204972.68 | N7: =IF(M7=0,"n/a",L7/M7) -> 0.87719008 | O7: =IF(J7=0,"n/a",L7/J7) -> 1.1064615 | P7: =IF(H7>=1,0,MAX(0,Fecha_Corte-F7)) -> 0 | Q7: =IF(H7>=1,"Completada",IF(Fecha_Corte<E7,"No iniciada",IF(Fecha_Corte>F7,"Vencida sin completar",IF(NOT(ISNUMBER(N7)),"En curso",IF(N7>=EVM_Verde,"En curso a tiempo",IF(N7>=EVM_Amarillo,"En curso con retraso leve","En curso con retraso crítico")))))) -> En curso con retraso leve | R7: =IF(H7>=1,"Verde",IF(NOT(ISNUMBER(N7)),"Gris",IF(N7>=EVM_Verde,"Verde",IF(N7>=EVM_Amarillo,"Amarillo","Rojo")))) -> Amarillo | S7: Campaña lanzada (fase 1)
A8: C1-04 | B8: C1 | C8: Plataforma de registro de aspirantes | D8: Esp. Planificación, M&S | E8: 46433 | F8: 46583 | G8: 290000 | H8: 0.78 | I8: =IF(Fecha_Corte<=E8,0,IF(Fecha_Corte>=F8,1,(Fecha_Corte-E8)/(F8-E8))) -> 0.9 | J8: =SUMIFS(F2_Ejecucion!$J$5:$J$500,F2_Ejecucion!$D$5:$D$500,A8) -> 199100 | K8: =IF(G8=0,0,J8/G8) -> 0.68655172 | L8: =G8*H8 -> 226200 | M8: =G8*I8 -> 261000 | N8: =IF(M8=0,"n/a",L8/M8) -> 0.86666667 | O8: =IF(J8=0,"n/a",L8/J8) -> 1.1361125 | P8: =IF(H8>=1,0,MAX(0,Fecha_Corte-F8)) -> 0 | Q8: =IF(H8>=1,"Completada",IF(Fecha_Corte<E8,"No iniciada",IF(Fecha_Corte>F8,"Vencida sin completar",IF(NOT(ISNUMBER(N8)),"En curso",IF(N8>=EVM_Verde,"En curso a tiempo",IF(N8>=EVM_Amarillo,"En curso con retraso leve","En curso con retraso crítico")))))) -> En curso con retraso leve | R8: =IF(H8>=1,"Verde",IF(NOT(ISNUMBER(N8)),"Gris",IF(N8>=EVM_Verde,"Verde",IF(N8>=EVM_Amarillo,"Amarillo","Rojo")))) -> Amarillo | S8: Plataforma en producción
A9: C1-05 | B9: C1 | C9: Ferias de orientación departamentales | D9: Esp. Social | E9: 46539 | F9: 46721 | G9: 140000 | H9: 0.14 | I9: =IF(Fecha_Corte<=E9,0,IF(Fecha_Corte>=F9,1,(Fecha_Corte-E9)/(F9-E9))) -> 0.15934066 | J9: =SUMIFS(F2_Ejecucion!$J$5:$J$500,F2_Ejecucion!$D$5:$D$500,A9) -> 14000 | K9: =IF(G9=0,0,J9/G9) -> 0.1 | L9: =G9*H9 -> 19600 | M9: =G9*I9 -> 22307.692 | N9: =IF(M9=0,"n/a",L9/M9) -> 0.87862069 | O9: =IF(J9=0,"n/a",L9/J9) -> 1.4 | P9: =IF(H9>=1,0,MAX(0,Fecha_Corte-F9)) -> 0 | Q9: =IF(H9>=1,"Completada",IF(Fecha_Corte<E9,"No iniciada",IF(Fecha_Corte>F9,"Vencida sin completar",IF(NOT(ISNUMBER(N9)),"En curso",IF(N9>=EVM_Verde,"En curso a tiempo",IF(N9>=EVM_Amarillo,"En curso con retraso leve","En curso con retraso crítico")))))) -> En curso con retraso leve | R9: =IF(H9>=1,"Verde",IF(NOT(ISNUMBER(N9)),"Gris",IF(N9>=EVM_Verde,"Verde",IF(N9>=EVM_Amarillo,"Amarillo","Rojo")))) -> Amarillo | S9: Primera feria realizada
A10: C2-01 | B10: C2 | C10: Esquema de apoyos y criterios de elegibilidad | D10: Esp. Social | E10: 46402 | F10: 46461 | G10: 70000 | H10: 1 | I10: =IF(Fecha_Corte<=E10,0,IF(Fecha_Corte>=F10,1,(Fecha_Corte-E10)/(F10-E10))) -> 1 | J10: =SUMIFS(F2_Ejecucion!$J$5:$J$500,F2_Ejecucion!$D$5:$D$500,A10) -> 63800 | K10: =IF(G10=0,0,J10/G10) -> 0.91142857 | L10: =G10*H10 -> 70000 | M10: =G10*I10 -> 70000 | N10: =IF(M10=0,"n/a",L10/M10) -> 1 | O10: =IF(J10=0,"n/a",L10/J10) -> 1.0971787 | P10: =IF(H10>=1,0,MAX(0,Fecha_Corte-F10)) -> 0 | Q10: =IF(H10>=1,"Completada",IF(Fecha_Corte<E10,"No iniciada",IF(Fecha_Corte>F10,"Vencida sin completar",IF(NOT(ISNUMBER(N10)),"En curso",IF(N10>=EVM_Verde,"En curso a tiempo",IF(N10>=EVM_Amarillo,"En curso con retraso leve","En curso con retraso crítico")))))) -> Completada | R10: =IF(H10>=1,"Verde",IF(NOT(ISNUMBER(N10)),"Gris",IF(N10>=EVM_Verde,"Verde",IF(N10>=EVM_Amarillo,"Amarillo","Rojo")))) -> Verde | S10: Esquema de apoyos aprobado (MOP)
A11: C2-02 | B11: C2 | C11: Selección de la primera cohorte | D11: Esp. Social | E11: 46447 | F11: 46553 | G11: 180000 | H11: 0.85 | I11: =IF(Fecha_Corte<=E11,0,IF(Fecha_Corte>=F11,1,(Fecha_Corte-E11)/(F11-E11))) -> 1 | J11: =SUMIFS(F2_Ejecucion!$J$5:$J$500,F2_Ejecucion!$D$5:$D$500,A11) -> 150000 | K11: =IF(G11=0,0,J11/G11) -> 0.83333333 | L11: =G11*H11 -> 153000 | M11: =G11*I11 -> 180000 | N11: =IF(M11=0,"n/a",L11/M11) -> 0.85 | O11: =IF(J11=0,"n/a",L11/J11) -> 1.02 | P11: =IF(H11>=1,0,MAX(0,Fecha_Corte-F11)) -> 15 | Q11: =IF(H11>=1,"Completada",IF(Fecha_Corte<E11,"No iniciada",IF(Fecha_Corte>F11,"Vencida sin completar",IF(NOT(ISNUMBER(N11)),"En curso",IF(N11>=EVM_Verde,"En curso a tiempo",IF(N11>=EVM_Amarillo,"En curso con retraso leve","En curso con retraso crítico")))))) -> Vencida sin completar | R11: =IF(H11>=1,"Verde",IF(NOT(ISNUMBER(N11)),"Gris",IF(N11>=EVM_Verde,"Verde",IF(N11>=EVM_Amarillo,"Amarillo","Rojo")))) -> Amarillo | S11: Cohorte 1 seleccionada
A12: C2-03 | B12: C2 | C12: Apoyos económicos primera cohorte | D12: Esp. Financiero | E12: 46478 | F12: 46736 | G12: 900000 | H12: 0.4 | I12: =IF(Fecha_Corte<=E12,0,IF(Fecha_Corte>=F12,1,(Fecha_Corte-E12)/(F12-E12))) -> 0.34883721 | J12: =SUMIFS(F2_Ejecucion!$J$5:$J$500,F2_Ejecucion!$D$5:$D$500,A12) -> 330000 | K12: =IF(G12=0,0,J12/G12) -> 0.36666667 | L12: =G12*H12 -> 360000 | M12: =G12*I12 -> 313953.49 | N12: =IF(M12=0,"n/a",L12/M12) -> 1.1466667 | O12: =IF(J12=0,"n/a",L12/J12) -> 1.0909091 | P12: =IF(H12>=1,0,MAX(0,Fecha_Corte-F12)) -> 0 | Q12: =IF(H12>=1,"Completada",IF(Fecha_Corte<E12,"No iniciada",IF(Fecha_Corte>F12,"Vencida sin completar",IF(NOT(ISNUMBER(N12)),"En curso",IF(N12>=EVM_Verde,"En curso a tiempo",IF(N12>=EVM_Amarillo,"En curso con retraso leve","En curso con retraso crítico")))))) -> En curso a tiempo | R12: =IF(H12>=1,"Verde",IF(NOT(ISNUMBER(N12)),"Gris",IF(N12>=EVM_Verde,"Verde",IF(N12>=EVM_Amarillo,"Amarillo","Rojo")))) -> Verde | S12: Primer pago de apoyos
A13: C2-04 | B13: C2 | C13: Acompañamiento socioeducativo (tutorías) | D13: Esp. Social | E13: 46492 | F13: 46736 | G13: 420000 | H13: 0.3 | I13: =IF(Fecha_Corte<=E13,0,IF(Fecha_Corte>=F13,1,(Fecha_Corte-E13)/(F13-E13))) -> 0.31147541 | J13: =SUMIFS(F2_Ejecucion!$J$5:$J$500,F2_Ejecucion!$D$5:$D$500,A13) -> 138500 | K13: =IF(G13=0,0,J13/G13) -> 0.3297619 | L13: =G13*H13 -> 126000 | M13: =G13*I13 -> 130819.67 | N13: =IF(M13=0,"n/a",L13/M13) -> 0.96315789 | O13: =IF(J13=0,"n/a",L13/J13) -> 0.90974729 | P13: =IF(H13>=1,0,MAX(0,Fecha_Corte-F13)) -> 0 | Q13: =IF(H13>=1,"Completada",IF(Fecha_Corte<E13,"No iniciada",IF(Fecha_Corte>F13,"Vencida sin completar",IF(NOT(ISNUMBER(N13)),"En curso",IF(N13>=EVM_Verde,"En curso a tiempo",IF(N13>=EVM_Amarillo,"En curso con retraso leve","En curso con retraso crítico")))))) -> En curso a tiempo | R13: =IF(H13>=1,"Verde",IF(NOT(ISNUMBER(N13)),"Gris",IF(N13>=EVM_Verde,"Verde",IF(N13>=EVM_Amarillo,"Amarillo","Rojo")))) -> Verde | S13: Tutorías en marcha
A14: C2-05 | B14: C2 | C14: Servicios de accesibilidad para personas con discapacidad | D14: Esp. Social | E14: 46508 | F14: 46736 | G14: 150000 | H14: 0.24 | I14: =IF(Fecha_Corte<=E14,0,IF(Fecha_Corte>=F14,1,(Fecha_Corte-E14)/(F14-E14))) -> 0.26315789 | J14: =SUMIFS(F2_Ejecucion!$J$5:$J$500,F2_Ejecucion!$D$5:$D$500,A14) -> 34000 | K14: =IF(G14=0,0,J14/G14) -> 0.22666667 | L14: =G14*H14 -> 36000 | M14: =G14*I14 -> 39473.684 | N14: =IF(M14=0,"n/a",L14/M14) -> 0.912 | O14: =IF(J14=0,"n/a",L14/J14) -> 1.0588235 | P14: =IF(H14>=1,0,MAX(0,Fecha_Corte-F14)) -> 0 | Q14: =IF(H14>=1,"Completada",IF(Fecha_Corte<E14,"No iniciada",IF(Fecha_Corte>F14,"Vencida sin completar",IF(NOT(ISNUMBER(N14)),"En curso",IF(N14>=EVM_Verde,"En curso a tiempo",IF(N14>=EVM_Amarillo,"En curso con retraso leve","En curso con retraso crítico")))))) -> En curso con retraso leve | R14: =IF(H14>=1,"Verde",IF(NOT(ISNUMBER(N14)),"Gris",IF(N14>=EVM_Verde,"Verde",IF(N14>=EVM_Amarillo,"Amarillo","Rojo")))) -> Amarillo | S14: Servicios de accesibilidad contratados
A15: C2-06 | B15: C2 | C15: Atención a madres jóvenes y personas retornadas | D15: Esp. Social | E15: 46508 | F15: 46736 | G15: 80000 | H15: 0.25 | I15: =IF(Fecha_Corte<=E15,0,IF(Fecha_Corte>=F15,1,(Fecha_Corte-E15)/(F15-E15))) -> 0.26315789 | J15: =SUMIFS(F2_Ejecucion!$J$5:$J$500,F2_Ejecucion!$D$5:$D$500,A15) -> 19000 | K15: =IF(G15=0,0,J15/G15) -> 0.2375 | L15: =G15*H15 -> 20000 | M15: =G15*I15 -> 21052.632 | N15: =IF(M15=0,"n/a",L15/M15) -> 0.95 | O15: =IF(J15=0,"n/a",L15/J15) -> 1.0526316 | P15: =IF(H15>=1,0,MAX(0,Fecha_Corte-F15)) -> 0 | Q15: =IF(H15>=1,"Completada",IF(Fecha_Corte<E15,"No iniciada",IF(Fecha_Corte>F15,"Vencida sin completar",IF(NOT(ISNUMBER(N15)),"En curso",IF(N15>=EVM_Verde,"En curso a tiempo",IF(N15>=EVM_Amarillo,"En curso con retraso leve","En curso con retraso crítico")))))) -> En curso a tiempo | R15: =IF(H15>=1,"Verde",IF(NOT(ISNUMBER(N15)),"Gris",IF(N15>=EVM_Verde,"Verde",IF(N15>=EVM_Amarillo,"Amarillo","Rojo")))) -> Verde | S15: Protocolo de atención aprobado
A16: C3-01 | B16: C3 | C16: Diagnóstico de demanda laboral | D16: Esp. Planificación, M&S | E16: 46419 | F16: 46538 | G16: 195000 | H16: 1 | I16: =IF(Fecha_Corte<=E16,0,IF(Fecha_Corte>=F16,1,(Fecha_Corte-E16)/(F16-E16))) -> 1 | J16: =SUMIFS(F2_Ejecucion!$J$5:$J$500,F2_Ejecucion!$D$5:$D$500,A16) -> 189000 | K16: =IF(G16=0,0,J16/G16) -> 0.96923077 | L16: =G16*H16 -> 195000 | M16: =G16*I16 -> 195000 | N16: =IF(M16=0,"n/a",L16/M16) -> 1 | O16: =IF(J16=0,"n/a",L16/J16) -> 1.031746 | P16: =IF(H16>=1,0,MAX(0,Fecha_Corte-F16)) -> 0 | Q16: =IF(H16>=1,"Completada",IF(Fecha_Corte<E16,"No iniciada",IF(Fecha_Corte>F16,"Vencida sin completar",IF(NOT(ISNUMBER(N16)),"En curso",IF(N16>=EVM_Verde,"En curso a tiempo",IF(N16>=EVM_Amarillo,"En curso con retraso leve","En curso con retraso crítico")))))) -> Completada | R16: =IF(H16>=1,"Verde",IF(NOT(ISNUMBER(N16)),"Gris",IF(N16>=EVM_Verde,"Verde",IF(N16>=EVM_Amarillo,"Amarillo","Rojo")))) -> Verde | S16: Informe de diagnóstico aprobado
... A28: C5-05 | B28: C5 | C28: Comunicación y gestión del conocimiento | D28: Esp. Planificación, M&S | E28: 46447 | F28: 46736 | G28: 80000 | H28: 0.36 | I28: =IF(Fecha_Corte<=E28,0,IF(Fecha_Corte>=F28,1,(Fecha_Corte-E28)/(F28-E28))) -> 0.41868512 | J28: =SUMIFS(F2_Ejecucion!$J$5:$J$500,F2_Ejecucion!$D$5:$D$500,A28) -> 28000 | K28: =IF(G28=0,0,J28/G28) -> 0.35 | L28: =G28*H28 -> 28800 | M28: =G28*I28 -> 33494.81 | N28: =IF(M28=0,"n/a",L28/M28) -> 0.85983471 | O28: =IF(J28=0,"n/a",L28/J28) -> 1.0285714 | P28: =IF(H28>=1,0,MAX(0,Fecha_Corte-F28)) -> 0 | Q28: =IF(H28>=1,"Completada",IF(Fecha_Corte<E28,"No iniciada",IF(Fecha_Corte>F28,"Vencida sin completar",IF(NOT(ISNUMBER(N28)),"En curso",IF(N28>=EVM_Verde,"En curso a tiempo",IF(N28>=EVM_Amarillo,"En curso con retraso leve","En curso con retraso crítico")))))) -> En curso con retraso leve | R28: =IF(H28>=1,"Verde",IF(NOT(ISNUMBER(N28)),"Gris",IF(N28>=EVM_Verde,"Verde",IF(N28>=EVM_Amarillo,"Amarillo","Rojo")))) -> Amarillo | S28: Plan de comunicación implementado

Sheet P1_Avance_FF
A1: P1 · Avance físico y financiero consolidado por componente (POA del año vigente)
A2: DATOS SIMULADOS con fines de demostración metodológica — no son cifras reales del BID ni de la Dirección de Integración.
A3: Lectura: SPI < 1 = atraso físico frente a lo planificado; CPI < 1 = se gastó más de lo que el avance físico justifica.
A4: Comp. | B4: Componente | C4: Presupuesto POA | D4: Ejecutado (AC) | E4: % financiero | F4: % físico ponderado | G4: % planificado | H4: EV | I4: PV | J4: SPI | K4: CPI | L4: Brecha físico − financiero | M4: N.º actividades | N4: N.º con alerta | O4: Semáforo
A5: C1 | B5: Acceso y orientación | C5: =SUMIFS(P1_POA!$G$5:$G$200,P1_POA!$B$5:$B$200,A5) -> 1030000 | D5: =SUMIFS(P1_POA!$J$5:$J$200,P1_POA!$B$5:$B$200,A5) -> 627600 | E5: =IF(C5=0,0,D5/C5) -> 0.60932039 | F5: =IF(C5=0,0,H5/C5) -> 0.6792233 | G5: =IF(C5=0,0,I5/C5) -> 0.75561201 | H5: =SUMIFS(P1_POA!$L$5:$L$200,P1_POA!$B$5:$B$200,A5) -> 699600 | I5: =SUMIFS(P1_POA!$M$5:$M$200,P1_POA!$B$5:$B$200,A5) -> 778280.37 | J5: =IF(I5=0,"n/a",H5/I5) -> 0.89890485 | K5: =IF(D5=0,"n/a",H5/D5) -> 1.1147228 | L5: =F5-E5 -> 0.069902913 | M5: =COUNTIFS(P1_POA!$B$5:$B$200,A5) -> 5 | N5: =COUNTIFS(P1_POA!$B$5:$B$200,A5,P1_POA!$R$5:$R$200,"Rojo")+COUNTIFS(P1_POA!$B$5:$B$200,A5,P1_POA!$R$5:$R$200,"Amarillo") -> 4 | O5: =IF(NOT(ISNUMBER(J5)),"Gris",IF(MIN(J5,IF(ISNUMBER(K5),K5,J5))>=EVM_Verde,"Verde",IF(MIN(J5,IF(ISNUMBER(K5),K5,J5))>=EVM_Amarillo,"Amarillo","Rojo"))) -> Amarillo
A6: C2 | B6: Permanencia y graduación | C6: =SUMIFS(P1_POA!$G$5:$G$200,P1_POA!$B$5:$B$200,A6) -> 1800000 | D6: =SUMIFS(P1_POA!$J$5:$J$200,P1_POA!$B$5:$B$200,A6) -> 735300 | E6: =IF(C6=0,0,D6/C6) -> 0.4085 | F6: =IF(C6=0,0,H6/C6) -> 0.425 | G6: =IF(C6=0,0,I6/C6) -> 0.41961082 | H6: =SUMIFS(P1_POA!$L$5:$L$200,P1_POA!$B$5:$B$200,A6) -> 765000 | I6: =SUMIFS(P1_POA!$M$5:$M$200,P1_POA!$B$5:$B$200,A6) -> 755299.48 | J6: =IF(I6=0,"n/a",H6/I6) -> 1.0128433 | K6: =IF(D6=0,"n/a",H6/D6) -> 1.0403917 | L6: =F6-E6 -> 0.0165 | M6: =COUNTIFS(P1_POA!$B$5:$B$200,A6) -> 6 | N6: =COUNTIFS(P1_POA!$B$5:$B$200,A6,P1_POA!$R$5:$R$200,"Rojo")+COUNTIFS(P1_POA!$B$5:$B$200,A6,P1_POA!$R$5:$R$200,"Amarillo") -> 2 | O6: =IF(NOT(ISNUMBER(J6)),"Gris",IF(MIN(J6,IF(ISNUMBER(K6),K6,J6))>=EVM_Verde,"Verde",IF(MIN(J6,IF(ISNUMBER(K6),K6,J6))>=EVM_Amarillo,"Amarillo","Rojo"))) -> Verde
A7: C3 | B7: Vinculación laboral y trayectorias | C7: =SUMIFS(P1_POA!$G$5:$G$200,P1_POA!$B$5:$B$200,A7) -> 500000 | D7: =SUMIFS(P1_POA!$J$5:$J$200,P1_POA!$B$5:$B$200,A7) -> 268200 | E7: =IF(C7=0,0,D7/C7) -> 0.5364 | F7: =IF(C7=0,0,H7/C7) -> 0.5462 | G7: =IF(C7=0,0,I7/C7) -> 0.56501853 | H7: =SUMIFS(P1_POA!$L$5:$L$200,P1_POA!$B$5:$B$200,A7) -> 273100 | I7: =SUMIFS(P1_POA!$M$5:$M$200,P1_POA!$B$5:$B$200,A7) -> 282509.27 | J7: =IF(I7=0,"n/a",H7/I7) -> 0.96669396 | K7: =IF(D7=0,"n/a",H7/D7) -> 1.0182699 | L7: =F7-E7 -> 0.0098 | M7: =COUNTIFS(P1_POA!$B$5:$B$200,A7) -> 4 | N7: =COUNTIFS(P1_POA!$B$5:$B$200,A7,P1_POA!$R$5:$R$200,"Rojo")+COUNTIFS(P1_POA!$B$5:$B$200,A7,P1_POA!$R$5:$R$200,"Amarillo") -> 2 | O7: =IF(NOT(ISNUMBER(J7)),"Gris",IF(MIN(J7,IF(ISNUMBER(K7),K7,J7))>=EVM_Verde,"Verde",IF(MIN(J7,IF(ISNUMBER(K7),K7,J7))>=EVM_Amarillo,"Amarillo","Rojo"))) -> Verde
A8: C4 | B8: Fortalecimiento institucional | C8: =SUMIFS(P1_POA!$G$5:$G$200,P1_POA!$B$5:$B$200,A8) -> 2300000 | D8: =SUMIFS(P1_POA!$J$5:$J$200,P1_POA!$B$5:$B$200,A8) -> 722850 | E8: =IF(C8=0,0,D8/C8) -> 0.31428261 | F8: =IF(C8=0,0,H8/C8) -> 0.33804348 | G8: =IF(C8=0,0,I8/C8) -> 0.49791352 | H8: =SUMIFS(P1_POA!$L$5:$L$200,P1_POA!$B$5:$B$200,A8) -> 777500 | I8: =SUMIFS(P1_POA!$M$5:$M$200,P1_POA!$B$5:$B$200,A8) -> 1145201.1 | J8: =IF(I8=0,"n/a",H8/I8) -> 0.67892006 | K8: =IF(D8=0,"n/a",H8/D8) -> 1.0756035 | L8: =F8-E8 -> 0.02376087 | M8: =COUNTIFS(P1_POA!$B$5:$B$200,A8) -> 4 | N8: =COUNTIFS(P1_POA!$B$5:$B$200,A8,P1_POA!$R$5:$R$200,"Rojo")+COUNTIFS(P1_POA!$B$5:$B$200,A8,P1_POA!$R$5:$R$200,"Amarillo") -> 3 | O8: =IF(NOT(ISNUMBER(J8)),"Gris",IF(MIN(J8,IF(ISNUMBER(K8),K8,J8))>=EVM_Verde,"Verde",IF(MIN(J8,IF(ISNUMBER(K8),K8,J8))>=EVM_Amarillo,"Amarillo","Rojo"))) -> Rojo
A9: C5 | B9: Administración, M&E y auditoría | C9: =SUMIFS(P1_POA!$G$5:$G$200,P1_POA!$B$5:$B$200,A9) -> 870000 | D9: =SUMIFS(P1_POA!$J$5:$J$200,P1_POA!$B$5:$B$200,A9) -> 374400 | E9: =IF(C9=0,0,D9/C9) -> 0.43034483 | F9: =IF(C9=0,0,H9/C9) -> 0.45551724 | G9: =IF(C9=0,0,I9/C9) -> 0.52364863 | H9: =SUMIFS(P1_POA!$L$5:$L$200,P1_POA!$B$5:$B$200,A9) -> 396300 | I9: =SUMIFS(P1_POA!$M$5:$M$200,P1_POA!$B$5:$B$200,A9) -> 455574.31 | J9: =IF(I9=0,"n/a",H9/I9) -> 0.86989102 | K9: =IF(D9=0,"n/a",H9/D9) -> 1.0584936 | L9: =F9-E9 -> 0.025172414 | M9: =COUNTIFS(P1_POA!$B$5:$B$200,A9) -> 5 | N9: =COUNTIFS(P1_POA!$B$5:$B$200,A9,P1_POA!$R$5:$R$200,"Rojo")+COUNTIFS(P1_POA!$B$5:$B$200,A9,P1_POA!$R$5:$R$200,"Amarillo") -> 3 | O9: =IF(NOT(ISNUMBER(J9)),"Gris",IF(MIN(J9,IF(ISNUMBER(K9),K9,J9))>=EVM_Verde,"Verde",IF(MIN(J9,IF(ISNUMBER(K9),K9,J9))>=EVM_Amarillo,"Amarillo","Rojo"))) -> Amarillo
A10: TOTAL | B10: Programa | C10: =SUM(C5:C9) -> 6500000 | D10: =SUM(D5:D9) -> 2728350 | E10: =D10/C10 -> 0.41974615 | F10: =H10/C10 -> 0.44792308 | G10: =I10/C10 -> 0.52567146 | H10: =SUM(H5:H9) -> 2911500 | I10: =SUM(I5:I9) -> 3416864.5 | J10: =IF(I10=0,"n/a",H10/I10) -> 0.852097 | K10: =IF(D10=0,"n/a",H10/D10) -> 1.0671285 | L10: =F10-E10 -> 0.028176923 | M10: =SUM(M5:M9) -> 24 | N10: =SUM(N5:N9) -> 14 | O10: =IF(NOT(ISNUMBER(J10)),"Gris",IF(MIN(J10,K10)>=EVM_Verde,"Verde",IF(MIN(J10,K10)>=EVM_Amarillo,"Amarillo","Rojo"))) -> Amarillo
A12: Presupuesto POA = actividades del año 1 (reconciliado con el PEP en la hoja Controles). Umbrales en Parametros (EVM_Verde / EVM_Amarillo).

Sheet P1_Riesgos
A1: P1 · Registro y matriz de riesgos (técnicos, fiduciarios, institucionales, ambientales y sociales)
A2: DATOS SIMULADOS con fines de demostración metodológica — no son cifras reales del BID ni de la Dirección de Integración.
A3: Puntaje = probabilidad × impacto (escala 1-5). Las columnas S-T son auxiliares para el ranking del informe mensual.
A4: ID | B4: Categoría | C4: Riesgo | D4: Causa / disparador | E4: Prob. (1-5) | F4: Impacto (1-5) | G4: Puntaje | H4: Nivel | I4: Respuesta | J4: Acción de mitigación | K4: Responsable | L4: Fecha límite | M4: Estado | N4: Prob. residual | O4: Impacto residual | P4: Puntaje residual | Q4: Nivel residual | R4: Días a la fecha límite | S4: Aux. puntaje | T4: Ranking
A5: R-01 | B5: Institucional | C5: Rotación o vacantes del personal clave de la UGP | D5: Contratos anuales y alta demanda de perfiles | E5: 3 | F5: 4 | G5: =E5*F5 -> 12 | H5: =IF(G5>=Riesgo_Alto,"Alto",IF(G5>=Riesgo_Medio,"Medio","Bajo")) -> Medio | I5: Mitigar | J5: Plan de sucesión, manual de funciones y prórrogas anticipadas | K5: Coordinador General | L5: 46660 | M5: En mitigación | N5: 2 | O5: 3 | P5: =N5*O5 -> 6 | Q5: =IF(P5>=Riesgo_Alto,"Alto",IF(P5>=Riesgo_Medio,"Medio","Bajo")) -> Bajo | R5: =IF(M5="Cerrado","",L5-Fecha_Corte) -> 92 | S5: =IF(M5="Cerrado",0,G5+(1000-ROW())/100000) -> 12.00995 | T5: =RANK(S5,$S$5:$S$200) -> 4
A6: R-02 | B6: Fiduciario | C6: Retrasos en adquisiciones por observaciones en las No Objeciones | D6: Expedientes incompletos o términos de referencia ambiguos | E6: 4 | F6: 4 | G6: =E6*F6 -> 16 | H6: =IF(G6>=Riesgo_Alto,"Alto",IF(G6>=Riesgo_Medio,"Medio","Bajo")) -> Alto | I6: Mitigar | J6: Listas de verificación previas al envío, plantillas estándar y calendario de No Objeciones | K6: Esp. Adquisiciones | L6: 46599 | M6: En mitigación | N6: 3 | O6: 3 | P6: =N6*O6 -> 9 | Q6: =IF(P6>=Riesgo_Alto,"Alto",IF(P6>=Riesgo_Medio,"Medio","Bajo")) -> Medio | R6: =IF(M6="Cerrado","",L6-Fecha_Corte) -> 31 | S6: =IF(M6="Cerrado",0,G6+(1000-ROW())/100000) -> 16.00994 | T6: =RANK(S6,$S$5:$S$200) -> 1
A7: R-03 | B7: Fiduciario | C7: Ejecución presupuestaria por debajo del PEP | D7: Retrasos físicos y de contratación | E7: 4 | F7: 4 | G7: =E7*F7 -> 16 | H7: =IF(G7>=Riesgo_Alto,"Alto",IF(G7>=Riesgo_Medio,"Medio","Bajo")) -> Alto | I7: Mitigar | J7: Seguimiento mensual SPI/CPI y reprogramación trimestral con alertas tempranas | K7: Coordinador General | L7: 46660 | M7: Abierto | N7: 3 | O7: 3 | P7: =N7*O7 -> 9 | Q7: =IF(P7>=Riesgo_Alto,"Alto",IF(P7>=Riesgo_Medio,"Medio","Bajo")) -> Medio | R7: =IF(M7="Cerrado","",L7-Fecha_Corte) -> 92 | S7: =IF(M7="Cerrado",0,G7+(1000-ROW())/100000) -> 16.00993 | T7: =RANK(S7,$S$5:$S$200) -> 2
A8: R-04 | B8: Fiduciario | C8: Justificación tardía de anticipos retrasa nuevos desembolsos | D8: Rendiciones atrasadas y soporte incompleto | E8: 3 | F8: 4 | G8: =E8*F8 -> 12 | H8: =IF(G8>=Riesgo_Alto,"Alto",IF(G8>=Riesgo_Medio,"Medio","Bajo")) -> Medio | I8: Mitigar | J8: Justificación quincenal y control del umbral del 80 % de anticipos | K8: Esp. Financiero | L8: 46583 | M8: En mitigación | N8: 2 | O8: 3 | P8: =N8*O8 -> 6 | Q8: =IF(P8>=Riesgo_Alto,"Alto",IF(P8>=Riesgo_Medio,"Medio","Bajo")) -> Bajo | R8: =IF(M8="Cerrado","",L8-Fecha_Corte) -> 15 | S8: =IF(M8="Cerrado",0,G8+(1000-ROW())/100000) -> 12.00992 | T8: =RANK(S8,$S$5:$S$200) -> 5
A9: R-05 | B9: Técnico | C9: Bajo alcance en departamentos de prioridad alta | D9: Barreras de acceso, difusión insuficiente en zonas rurales | E9: 3 | F9: 4 | G9: =E9*F9 -> 12 | H9: =IF(G9>=Riesgo_Alto,"Alto",IF(G9>=Riesgo_Medio,"Medio","Bajo")) -> Medio | I9: Mitigar | J9: Focalización por índice, ferias departamentales y alianzas locales | K9: Esp. Social | L9: 46691 | M9: Abierto | N9: 2 | O9: 3 | P9: =N9*O9 -> 6 | Q9: =IF(P9>=Riesgo_Alto,"Alto",IF(P9>=Riesgo_Medio,"Medio","Bajo")) -> Bajo | R9: =IF(M9="Cerrado","",L9-Fecha_Corte) -> 123 | S9: =IF(M9="Cerrado",0,G9+(1000-ROW())/100000) -> 12.00991 | T9: =RANK(S9,$S$5:$S$200) -> 6
A10: R-06 | B10: Técnico | C10: Retraso en el desarrollo del sistema de información de trayectorias | D10: Requisitos cambiantes e integración con instituciones | E10: 4 | F10: 3 | G10: =E10*F10 -> 12 | H10: =IF(G10>=Riesgo_Alto,"Alto",IF(G10>=Riesgo_Medio,"Medio","Bajo")) -> Medio | I10: Mitigar | J10: Entregas por módulos, pruebas tempranas y gobierno de requisitos | K10: Esp. Planificación, M&S | L10: 46630 | M10: En mitigación | N10: 3 | O10: 3 | P10: =N10*O10 -> 9 | Q10: =IF(P10>=Riesgo_Alto,"Alto",IF(P10>=Riesgo_Medio,"Medio","Bajo")) -> Medio | R10: =IF(M10="Cerrado","",L10-Fecha_Corte) -> 62 | S10: =IF(M10="Cerrado",0,G10+(1000-ROW())/100000) -> 12.0099 | T10: =RANK(S10,$S$5:$S$200) -> 7
A11: R-07 | B11: Institucional | C11: Débil articulación con instituciones de educación postsecundaria | D11: Capacidades y prioridades distintas | E11: 3 | F11: 3 | G11: =E11*F11 -> 9 | H11: =IF(G11>=Riesgo_Alto,"Alto",IF(G11>=Riesgo_Medio,"Medio","Bajo")) -> Medio | I11: Mitigar | J11: Convenios con compromisos medibles y mesa de coordinación | K11: Coordinador General | L11: 46660 | M11: Abierto | N11: 2 | O11: 3 | P11: =N11*O11 -> 6 | Q11: =IF(P11>=Riesgo_Alto,"Alto",IF(P11>=Riesgo_Medio,"Medio","Bajo")) -> Bajo | R11: =IF(M11="Cerrado","",L11-Fecha_Corte) -> 92 | S11: =IF(M11="Cerrado",0,G11+(1000-ROW())/100000) -> 9.00989 | T11: =RANK(S11,$S$5:$S$200) -> 11
A12: R-08 | B12: Ambiental y social | C12: Exclusión de grupos prioritarios (discapacidad, madres jóvenes, retornados) | D12: Barreras de accesibilidad y de información | E12: 3 | F12: 5 | G12: =E12*F12 -> 15 | H12: =IF(G12>=Riesgo_Alto,"Alto",IF(G12>=Riesgo_Medio,"Medio","Bajo")) -> Alto | I12: Mitigar | J12: Ajustes razonables, metas por grupo y monitoreo de cobertura | K12: Esp. Social | L12: 46630 | M12: En mitigación | N12: 2 | O12: 4 | P12: =N12*O12 -> 8 | Q12: =IF(P12>=Riesgo_Alto,"Alto",IF(P12>=Riesgo_Medio,"Medio","Bajo")) -> Medio | R12: =IF(M12="Cerrado","",L12-Fecha_Corte) -> 62 | S12: =IF(M12="Cerrado",0,G12+(1000-ROW())/100000) -> 15.00988 | T12: =RANK(S12,$S$5:$S$200) -> 3
A13: R-09 | B13: Ambiental y social | C13: Incidente de protección de datos personales de beneficiarios | D13: Manejo de información sensible en varias entidades | E13: 2 | F13: 5 | G13: =E13*F13 -> 10 | H13: =IF(G13>=Riesgo_Alto,"Alto",IF(G13>=Riesgo_Medio,"Medio","Bajo")) -> Medio | I13: Mitigar | J13: Protocolo de datos, accesos por rol y capacitación | K13: Esp. Social | L13: 46599 | M13: En mitigación | N13: 1 | O13: 5 | P13: =N13*O13 -> 5 | Q13: =IF(P13>=Riesgo_Alto,"Alto",IF(P13>=Riesgo_Medio,"Medio","Bajo")) -> Bajo | R13: =IF(M13="Cerrado","",L13-Fecha_Corte) -> 31 | S13: =IF(M13="Cerrado",0,G13+(1000-ROW())/100000) -> 10.00987 | T13: =RANK(S13,$S$5:$S$200) -> 10
A14: R-10 | B14: Cumplimiento | C14: Incumplimiento de plazos de informes al BID | D14: Cierres contables y de indicadores desfasados | E14: 2 | F14: 4 | G14: =E14*F14 -> 8 | H14: =IF(G14>=Riesgo_Alto,"Alto",IF(G14>=Riesgo_Medio,"Medio","Bajo")) -> Medio | I14: Mitigar | J14: Calendario de reportes con alertas a 30 días | K14: Esp. Planificación, M&S | L14: 46599 | M14: En mitigación | N14: 1 | O14: 4 | P14: =N14*O14 -> 4 | Q14: =IF(P14>=Riesgo_Alto,"Alto",IF(P14>=Riesgo_Medio,"Medio","Bajo")) -> Bajo | R14: =IF(M14="Cerrado","",L14-Fecha_Corte) -> 31 | S14: =IF(M14="Cerrado",0,G14+(1000-ROW())/100000) -> 8.00986 | T14: =RANK(S14,$S$5:$S$200) -> 13
A15: R-11 | B15: Cumplimiento | C15: Modificar el MOP o reasignar fondos sin No Objeción previa | D15: Cambios operativos urgentes | E15: 1 | F15: 4 | G15: =E15*F15 -> 4 | H15: =IF(G15>=Riesgo_Alto,"Alto",IF(G15>=Riesgo_Medio,"Medio","Bajo")) -> Bajo | I15: Evitar | J15: Regla: ningún cambio sin No Objeción; registro de cambios (CCB) | K15: Coordinador General | L15: 46752 | M15: Abierto | N15: 1 | O15: 4 | P15: =N15*O15 -> 4 | Q15: =IF(P15>=Riesgo_Alto,"Alto",IF(P15>=Riesgo_Medio,"Medio","Bajo")) -> Bajo | R15: =IF(M15="Cerrado","",L15-Fecha_Corte) -> 184 | S15: =IF(M15="Cerrado",0,G15+(1000-ROW())/100000) -> 4.00985 | T15: =RANK(S15,$S$5:$S$200) -> 15
A16: R-12 | B16: Externo | C16: Cambios de prioridades o transición institucional | D16: Contexto político | E16: 2 | F16: 4 | G16: =E16*F16 -> 8 | H16: =IF(G16>=Riesgo_Alto,"Alto",IF(G16>=Riesgo_Medio,"Medio","Bajo")) -> Medio | I16: Aceptar | J16: Comunicación periódica con la Dirección General y la Gerencia de Cooperación | K16: Coordinador General | L16: 46752 | M16: Abierto | N16: 2 | O16: 4 | P16: =N16*O16 -> 8 | Q16: =IF(P16>=Riesgo_Alto,"Alto",IF(P16>=Riesgo_Medio,"Medio","Bajo")) -> Medio | R16: =IF(M16="Cerrado","",L16-Fecha_Corte) -> 184 | S16: =IF(M16="Cerrado",0,G16+(1000-ROW())/100000) -> 8.00984 | T16: =RANK(S16,$S$5:$S$200) -> 14
... A19: R-15 | B19: Técnico | C19: Dificultad para medir resultados (línea base y trayectorias) | D19: Sistemas de información fragmentados | E19: 3 | F19: 4 | G19: =E19*F19 -> 12 | H19: =IF(G19>=Riesgo_Alto,"Alto",IF(G19>=Riesgo_Medio,"Medio","Bajo")) -> Medio | I19: Mitigar | J19: Línea base temprana y definición de fuentes de verificación | K19: Esp. Planificación, M&S | L19: 46583 | M19: En mitigación | N19: 2 | O19: 3 | P19: =N19*O19 -> 6 | Q19: =IF(P19>=Riesgo_Alto,"Alto",IF(P19>=Riesgo_Medio,"Medio","Bajo")) -> Bajo | R19: =IF(M19="Cerrado","",L19-Fecha_Corte) -> 15 | S19: =IF(M19="Cerrado",0,G19+(1000-ROW())/100000) -> 12.00981 | T19: =RANK(S19,$S$5:$S$200) -> 9

Sheet P2_Focalizacion
A1: P2 · Focalización territorial: metas, cobertura e inversión por departamento
A2: DATOS SIMULADOS con fines de demostración metodológica — no son cifras reales del BID ni de la Dirección de Integración.
A3: Índice de focalización = W_Vuln×vulnerabilidad + W_Pob×población relativa + W_Brecha×brecha de cobertura (pesos en Parametros). Población y vulnerabilidad son valores sintéticos.
A4: Departamento | B4: ISO 3166-2 | C4: Peso población objetivo | D4: Vulnerabilidad (0-1) | E4: Meta 5 años (personas) | F4: Meta año 1 | G4: Alcanzado acumulado | H4: Madres jóvenes | I4: Personas con discapacidad | J4: Retornadas/os | K4: Cobertura meta año 1 | L4: Población relativa | M4: Brecha de cobertura | N4: Índice de focalización | O4: Prioridad | P4: Inversión ejecutada USD (territorializada) | Q4: USD por beneficiario | R4: Ranking
A5: Ahuachapán | B5: SV-AH | C5: 0.06 | D5: 0.72 | E5: 4070 | F5: =ROUND(E5*Pct_Anio1_Benef,0) -> 407 | G5: 116 | H5: 13 | I5: 4 | J5: 3 | K5: =IF(F5=0,0,G5/F5) -> 0.28501229 | L5: =C5/MAX($C$5:$C$18) -> 0.27272727 | M5: =1-MIN(1,K5) -> 0.71498771 | N5: =W_Vuln*D5+W_Pob*L5+W_Brecha*M5 -> 0.62904177 | O5: =IF(N5>=Prior_Alta,"Alta",IF(N5>=Prior_Media,"Media","Baja")) -> Alta | P5: =SUMIFS(F2_Ejecucion!$J$5:$J$500,F2_Ejecucion!$F$5:$F$500,A5) -> 50000 | Q5: =IF(G5=0,"",P5/G5) -> 431.03448 | R5: =RANK(N5,$N$5:$N$18) -> 2
A6: Cabañas | B6: SV-CA | C6: 0.03 | D6: 0.76 | E6: 2090 | F6: =ROUND(E6*Pct_Anio1_Benef,0) -> 209 | G6: 57 | H6: 5 | I6: 2 | J6: 2 | K6: =IF(F6=0,0,G6/F6) -> 0.27272727 | L6: =C6/MAX($C$5:$C$18) -> 0.13636364 | M6: =1-MIN(1,K6) -> 0.72727273 | N6: =W_Vuln*D6+W_Pob*L6+W_Brecha*M6 -> 0.62545455 | O6: =IF(N6>=Prior_Alta,"Alta",IF(N6>=Prior_Media,"Media","Baja")) -> Alta | P6: =SUMIFS(F2_Ejecucion!$J$5:$J$500,F2_Ejecucion!$F$5:$F$500,A6) -> 7900 | Q6: =IF(G6=0,"",P6/G6) -> 138.59649 | R6: =RANK(N6,$N$5:$N$18) -> 3
A7: Chalatenango | B7: SV-CH | C7: 0.04 | D7: 0.7 | E7: 2680 | F7: =ROUND(E7*Pct_Anio1_Benef,0) -> 268 | G7: 98 | H7: 8 | I7: 4 | J7: 3 | K7: =IF(F7=0,0,G7/F7) -> 0.36567164 | L7: =C7/MAX($C$5:$C$18) -> 0.18181818 | M7: =1-MIN(1,K7) -> 0.63432836 | N7: =W_Vuln*D7+W_Pob*L7+W_Brecha*M7 -> 0.57666214 | O7: =IF(N7>=Prior_Alta,"Alta",IF(N7>=Prior_Media,"Media","Baja")) -> Media | P7: =SUMIFS(F2_Ejecucion!$J$5:$J$500,F2_Ejecucion!$F$5:$F$500,A7) -> 13590 | Q7: =IF(G7=0,"",P7/G7) -> 138.67347 | R7: =RANK(N7,$N$5:$N$18) -> 5
A8: Cuscatlán | B8: SV-CU | C8: 0.04 | D8: 0.52 | E8: 2340 | F8: =ROUND(E8*Pct_Anio1_Benef,0) -> 234 | G8: 96 | H8: 10 | I8: 4 | J8: 2 | K8: =IF(F8=0,0,G8/F8) -> 0.41025641 | L8: =C8/MAX($C$5:$C$18) -> 0.18181818 | M8: =1-MIN(1,K8) -> 0.58974359 | N8: =W_Vuln*D8+W_Pob*L8+W_Brecha*M8 -> 0.47328671 | O8: =IF(N8>=Prior_Alta,"Alta",IF(N8>=Prior_Media,"Media","Baja")) -> Media | P8: =SUMIFS(F2_Ejecucion!$J$5:$J$500,F2_Ejecucion!$F$5:$F$500,A8) -> 32200 | Q8: =IF(G8=0,"",P8/G8) -> 335.41667 | R8: =RANK(N8,$N$5:$N$18) -> 13
A9: La Libertad | B9: SV-LI | C9: 0.12 | D9: 0.42 | E9: 6480 | F9: =ROUND(E9*Pct_Anio1_Benef,0) -> 648 | G9: 315 | H9: 32 | I9: 12 | J9: 8 | K9: =IF(F9=0,0,G9/F9) -> 0.48611111 | L9: =C9/MAX($C$5:$C$18) -> 0.54545455 | M9: =1-MIN(1,K9) -> 0.51388889 | N9: =W_Vuln*D9+W_Pob*L9+W_Brecha*M9 -> 0.47325758 | O9: =IF(N9>=Prior_Alta,"Alta",IF(N9>=Prior_Media,"Media","Baja")) -> Media | P9: =SUMIFS(F2_Ejecucion!$J$5:$J$500,F2_Ejecucion!$F$5:$F$500,A9) -> 115870 | Q9: =IF(G9=0,"",P9/G9) -> 367.84127 | R9: =RANK(N9,$N$5:$N$18) -> 14
A10: La Paz | B10: SV-PA | C10: 0.05 | D10: 0.6 | E10: 3110 | F10: =ROUND(E10*Pct_Anio1_Benef,0) -> 311 | G10: 139 | H10: 13 | I10: 5 | J10: 6 | K10: =IF(F10=0,0,G10/F10) -> 0.44694534 | L10: =C10/MAX($C$5:$C$18) -> 0.22727273 | M10: =1-MIN(1,K10) -> 0.55305466 | N10: =W_Vuln*D10+W_Pob*L10+W_Brecha*M10 -> 0.51137094 | O10: =IF(N10>=Prior_Alta,"Alta",IF(N10>=Prior_Media,"Media","Baja")) -> Media | P10: =SUMIFS(F2_Ejecucion!$J$5:$J$500,F2_Ejecucion!$F$5:$F$500,A10) -> 124040 | Q10: =IF(G10=0,"",P10/G10) -> 892.3741 | R10: =RANK(N10,$N$5:$N$18) -> 12
A11: La Unión | B11: SV-UN | C11: 0.05 | D11: 0.74 | E11: 3440 | F11: =ROUND(E11*Pct_Anio1_Benef,0) -> 344 | G11: 93 | H11: 9 | I11: 3 | J11: 2 | K11: =IF(F11=0,0,G11/F11) -> 0.27034884 | L11: =C11/MAX($C$5:$C$18) -> 0.22727273 | M11: =1-MIN(1,K11) -> 0.72965116 | N11: =W_Vuln*D11+W_Pob*L11+W_Brecha*M11 -> 0.63434989 | O11: =IF(N11>=Prior_Alta,"Alta",IF(N11>=Prior_Media,"Media","Baja")) -> Alta | P11: =SUMIFS(F2_Ejecucion!$J$5:$J$500,F2_Ejecucion!$F$5:$F$500,A11) -> 31890 | Q11: =IF(G11=0,"",P11/G11) -> 342.90323 | R11: =RANK(N11,$N$5:$N$18) -> 1
A12: Morazán | B12: SV-MO | C12: 0.03 | D12: 0.78 | E12: 2120 | F12: =ROUND(E12*Pct_Anio1_Benef,0) -> 212 | G12: 66 | H12: 5 | I12: 3 | J12: 2 | K12: =IF(F12=0,0,G12/F12) -> 0.31132075 | L12: =C12/MAX($C$5:$C$18) -> 0.13636364 | M12: =1-MIN(1,K12) -> 0.68867925 | N12: =W_Vuln*D12+W_Pob*L12+W_Brecha*M12 -> 0.6238765 | O12: =IF(N12>=Prior_Alta,"Alta",IF(N12>=Prior_Media,"Media","Baja")) -> Alta | P12: =SUMIFS(F2_Ejecucion!$J$5:$J$500,F2_Ejecucion!$F$5:$F$500,A12) -> 75910 | Q12: =IF(G12=0,"",P12/G12) -> 1150.1515 | R12: =RANK(N12,$N$5:$N$18) -> 4
A13: San Miguel | B13: SV-SM | C13: 0.09 | D13: 0.58 | E13: 5520 | F13: =ROUND(E13*Pct_Anio1_Benef,0) -> 552 | G13: 226 | H13: 21 | I13: 8 | J13: 6 | K13: =IF(F13=0,0,G13/F13) -> 0.40942029 | L13: =C13/MAX($C$5:$C$18) -> 0.40909091 | M13: =1-MIN(1,K13) -> 0.59057971 | N13: =W_Vuln*D13+W_Pob*L13+W_Brecha*M13 -> 0.54899209 | O13: =IF(N13>=Prior_Alta,"Alta",IF(N13>=Prior_Media,"Media","Baja")) -> Media | P13: =SUMIFS(F2_Ejecucion!$J$5:$J$500,F2_Ejecucion!$F$5:$F$500,A13) -> 36110 | Q13: =IF(G13=0,"",P13/G13) -> 159.77876 | R13: =RANK(N13,$N$5:$N$18) -> 8
A14: San Salvador | B14: SV-SS | C14: 0.22 | D14: 0.35 | E14: 11170 | F14: =ROUND(E14*Pct_Anio1_Benef,0) -> 1117 | G14: 406 | H14: 41 | I14: 14 | J14: 15 | K14: =IF(F14=0,0,G14/F14) -> 0.36347359 | L14: =C14/MAX($C$5:$C$18) -> 1 | M14: =1-MIN(1,K14) -> 0.63652641 | N14: =W_Vuln*D14+W_Pob*L14+W_Brecha*M14 -> 0.56595792 | O14: =IF(N14>=Prior_Alta,"Alta",IF(N14>=Prior_Media,"Media","Baja")) -> Media | P14: =SUMIFS(F2_Ejecucion!$J$5:$J$500,F2_Ejecucion!$F$5:$F$500,A14) -> 93190 | Q14: =IF(G14=0,"",P14/G14) -> 229.53202 | R14: =RANK(N14,$N$5:$N$18) -> 6
A15: San Vicente | B15: SV-SV | C15: 0.04 | D15: 0.66 | E15: 2600 | F15: =ROUND(E15*Pct_Anio1_Benef,0) -> 260 | G15: 125 | H15: 11 | I15: 5 | J15: 4 | K15: =IF(F15=0,0,G15/F15) -> 0.48076923 | L15: =C15/MAX($C$5:$C$18) -> 0.18181818 | M15: =1-MIN(1,K15) -> 0.51923077 | N15: =W_Vuln*D15+W_Pob*L15+W_Brecha*M15 -> 0.52213287 | O15: =IF(N15>=Prior_Alta,"Alta",IF(N15>=Prior_Media,"Media","Baja")) -> Media | P15: =SUMIFS(F2_Ejecucion!$J$5:$J$500,F2_Ejecucion!$F$5:$F$500,A15) -> 28790 | Q15: =IF(G15=0,"",P15/G15) -> 230.32 | R15: =RANK(N15,$N$5:$N$18) -> 11
A16: Santa Ana | B16: SV-SA | C16: 0.1 | D16: 0.55 | E16: 6000 | F16: =ROUND(E16*Pct_Anio1_Benef,0) -> 600 | G16: 265 | H16: 19 | I16: 12 | J16: 8 | K16: =IF(F16=0,0,G16/F16) -> 0.44166667 | L16: =C16/MAX($C$5:$C$18) -> 0.45454545 | M16: =1-MIN(1,K16) -> 0.55833333 | N16: =W_Vuln*D16+W_Pob*L16+W_Brecha*M16 -> 0.53340909 | O16: =IF(N16>=Prior_Alta,"Alta",IF(N16>=Prior_Media,"Media","Baja")) -> Media | P16: =SUMIFS(F2_Ejecucion!$J$5:$J$500,F2_Ejecucion!$F$5:$F$500,A16) -> 73080 | Q16: =IF(G16=0,"",P16/G16) -> 275.77358 | R16: =RANK(N16,$N$5:$N$18) -> 10
... A18: Usulután | B18: SV-US | C18: 0.06 | D18: 0.68 | E18: 3960 | F18: =ROUND(E18*Pct_Anio1_Benef,0) -> 396 | G18: 186 | H18: 15 | I18: 7 | J18: 7 | K18: =IF(F18=0,0,G18/F18) -> 0.46969697 | L18: =C18/MAX($C$5:$C$18) -> 0.27272727 | M18: =1-MIN(1,K18) -> 0.53030303 | N18: =W_Vuln*D18+W_Pob*L18+W_Brecha*M18 -> 0.55363636 | O18: =IF(N18>=Prior_Alta,"Alta",IF(N18>=Prior_Media,"Media","Baja")) -> Media | P18: =SUMIFS(F2_Ejecucion!$J$5:$J$500,F2_Ejecucion!$F$5:$F$500,A18) -> 25810 | Q18: =IF(G18=0,"",P18/G18) -> 138.76344 | R18: =RANK(N18,$N$5:$N$18) -> 7
A19: NACIONAL | C19: =SUM(C5:C18) -> 1 | E19: =SUM(E5:E18) -> 60000 | F19: =SUM(F5:F18) -> 6000 | G19: =SUM(G5:G18) -> 2380 | H19: =SUM(H5:H18) -> 223 | I19: =SUM(I5:I18) -> 90 | J19: =SUM(J5:J18) -> 75 | K19: =G19/F19 -> 0.39666667 | P19: =SUM(P5:P18) -> 735000 | Q19: =P19/G19 -> 308.82353
A21: La inversión territorializada solo incluye gastos con departamento asignado; los gastos «Nacional» (UGP, sistemas, campañas) no se reparten.

Sheet F1_Presupuesto_PEP
A1: F1 · Presupuesto y Plan de Ejecución Plurianual (PEP) por componente
A2: DATOS SIMULADOS con fines de demostración metodológica — no son cifras reales del BID ni de la Dirección de Integración.
A3: Estructura de componentes ILUSTRATIVA. Año 1 = suma del POA (fórmula); años 2-5 son el plan plurianual (editable).
A4: Comp. | B4: Componente | C4: Préstamo 6153/OC-ES | D4: Donación 6154/GR-ES | E4: Total asignado | F4: % del total | G4: PEP Año 1 | H4: PEP Año 2 | I4: PEP Año 3 | J4: PEP Año 4 | K4: PEP Año 5 | L4: Total PEP | M4: PEP = Asignado | N4: Ejecutado acumulado | O4: % ejecución s/ total | P4: % ejecución s/ PEP año vigente | Q4: Saldo por ejecutar
A5: C1 | B5: Acceso y orientación | C5: 13500000 | D5: 500000 | E5: =C5+D5 -> 14000000 | F5: =E5/$E$10 -> 0.13461538 | G5: =SUMIFS(P1_POA!$G$5:$G$200,P1_POA!$B$5:$B$200,A5) -> 1030000 | H5: 2850000 | I5: 3890000 | J5: 3630000 | K5: 2600000 | L5: =SUM(G5:K5) -> 14000000 | M5: =IF(ROUND(L5-E5,0)=0,"OK","REVISAR") -> OK | N5: =SUMIFS(F2_Ejecucion!$J$5:$J$500,F2_Ejecucion!$C$5:$C$500,A5) -> 627600 | O5: =N5/E5 -> 0.044828571 | P5: =N5/INDEX(G5:K5,Anio_Programa) -> 0.60932039 | Q5: =E5-N5 -> 13372400
A6: C2 | B6: Permanencia y graduación | C6: 44000000 | D6: 2000000 | E6: =C6+D6 -> 46000000 | F6: =E6/$E$10 -> 0.44230769 | G6: =SUMIFS(P1_POA!$G$5:$G$200,P1_POA!$B$5:$B$200,A6) -> 1800000 | H6: 9720000 | I6: 13260000 | J6: 12380000 | K6: 8840000 | L6: =SUM(G6:K6) -> 46000000 | M6: =IF(ROUND(L6-E6,0)=0,"OK","REVISAR") -> OK | N6: =SUMIFS(F2_Ejecucion!$J$5:$J$500,F2_Ejecucion!$C$5:$C$500,A6) -> 735300 | O6: =N6/E6 -> 0.015984783 | P6: =N6/INDEX(G6:K6,Anio_Programa) -> 0.4085 | Q6: =E6-N6 -> 45264700
A7: C3 | B7: Vinculación laboral y trayectorias | C7: 20000000 | D7: 0 | E7: =C7+D7 -> 20000000 | F7: =E7/$E$10 -> 0.19230769 | G7: =SUMIFS(P1_POA!$G$5:$G$200,P1_POA!$B$5:$B$200,A7) -> 500000 | H7: 4290000 | I7: 5850000 | J7: 5460000 | K7: 3900000 | L7: =SUM(G7:K7) -> 20000000 | M7: =IF(ROUND(L7-E7,0)=0,"OK","REVISAR") -> OK | N7: =SUMIFS(F2_Ejecucion!$J$5:$J$500,F2_Ejecucion!$C$5:$C$500,A7) -> 268200 | O7: =N7/E7 -> 0.01341 | P7: =N7/INDEX(G7:K7,Anio_Programa) -> 0.5364 | Q7: =E7-N7 -> 19731800
A8: C4 | B8: Fortalecimiento institucional | C8: 16000000 | D8: 1000000 | E8: =C8+D8 -> 17000000 | F8: =E8/$E$10 -> 0.16346154 | G8: =SUMIFS(P1_POA!$G$5:$G$200,P1_POA!$B$5:$B$200,A8) -> 2300000 | H8: 3230000 | I8: 4410000 | J8: 4120000 | K8: 2940000 | L8: =SUM(G8:K8) -> 17000000 | M8: =IF(ROUND(L8-E8,0)=0,"OK","REVISAR") -> OK | N8: =SUMIFS(F2_Ejecucion!$J$5:$J$500,F2_Ejecucion!$C$5:$C$500,A8) -> 722850 | O8: =N8/E8 -> 0.042520588 | P8: =N8/INDEX(G8:K8,Anio_Programa) -> 0.31428261 | Q8: =E8-N8 -> 16277150
A9: C5 | B9: Administración, M&E y auditoría | C9: 6500000 | D9: 500000 | E9: =C9+D9 -> 7000000 | F9: =E9/$E$10 -> 0.067307692 | G9: =SUMIFS(P1_POA!$G$5:$G$200,P1_POA!$B$5:$B$200,A9) -> 870000 | H9: 1350000 | I9: 1840000 | J9: 1720000 | K9: 1220000 | L9: =SUM(G9:K9) -> 7000000 | M9: =IF(ROUND(L9-E9,0)=0,"OK","REVISAR") -> OK | N9: =SUMIFS(F2_Ejecucion!$J$5:$J$500,F2_Ejecucion!$C$5:$C$500,A9) -> 374400 | O9: =N9/E9 -> 0.053485714 | P9: =N9/INDEX(G9:K9,Anio_Programa) -> 0.43034483 | Q9: =E9-N9 -> 6625600
A10: TOTAL | B10: Programa | C10: =SUM(C5:C9) -> 100000000 | D10: =SUM(D5:D9) -> 4000000 | E10: =SUM(E5:E9) -> 104000000 | F10: =E10/E10 -> 1 | G10: =SUM(G5:G9) -> 6500000 | H10: =SUM(H5:H9) -> 21440000 | I10: =SUM(I5:I9) -> 29250000 | J10: =SUM(J5:J9) -> 27310000 | K10: =SUM(K5:K9) -> 19500000 | L10: =SUM(L5:L9) -> 104000000 | M10: =IF(AND(ROUND(E10-Total_Programa,0)=0,ROUND(C10-Total_Prestamo,0)=0,ROUND(D10-Total_Donacion,0)=0),"OK","REVISAR") -> OK | N10: =SUM(N5:N9) -> 2728350 | O10: =N10/E10 -> 0.026234135 | P10: =N10/INDEX(G10:K10,Anio_Programa) -> 0.41974615 | Q10: =SUM(Q5:Q9) -> 101271650
A12: Ejecución por fuente de financiamiento
A13: Fuente | C13: Asignado | D13: Ejecutado | E13: % ejecución | F13: Saldo
A14: Préstamo | C14: =Total_Prestamo -> 100000000 | D14: =SUMIFS(F2_Ejecucion!$J$5:$J$500,F2_Ejecucion!$I$5:$I$500,A14) -> 2608350 | E14: =IF(C14=0,0,D14/C14) -> 0.0260835 | F14: =C14-D14 -> 97391650
A15: Donación | C15: =Total_Donacion -> 4000000 | D15: =SUMIFS(F2_Ejecucion!$J$5:$J$500,F2_Ejecucion!$I$5:$I$500,A15) -> 120000 | E15: =IF(C15=0,0,D15/C15) -> 0.03 | F15: =C15-D15 -> 3880000
A17: Año vigente del programa y fecha de corte: ver hoja Parametros. Los años 2-5 se actualizan en cada revisión del PEP (con No Objeción del BID si hay reasignaciones).

Sheet F2_Ejecucion
A1: F2 · Libro de ejecución de gastos (devengado)
A2: DATOS SIMULADOS con fines de demostración metodológica — no son cifras reales del BID ni de la Dirección de Integración.
A3: Fuente única de la ejecución: alimenta presupuesto, POA, contratos, anticipos, focalización y tablero. Para agregar un gasto copie la última fila (incluida la columna de chequeo).
A4: ID gasto | B4: Fecha | C4: Comp. | D4: Actividad POA | E4: Contrato | F4: Departamento | G4: Concepto | H4: Categoría | I4: Fuente | J4: Monto USD | K4: Estado de pago | L4: Mecanismo | M4: Justificado al BID | N4: Chequeo comp.
A5: G-0001 | B5: 46409 | C5: C5 | D5: C5-01 | E5: CT-10 | F5: Nacional | G5: Pago Consultoría individual (TDR: US$50,400) (1/3) | H5: Consultoría | I5: Préstamo | J5: 16680 | K5: Pagado | L5: Anticipo de fondos | M5: Sí | N5: =IF(D5="","",IF(INDEX(P1_POA!$B$5:$B$200,MATCH(D5,P1_POA!$A$5:$A$200,0))=C5,0,1)) -> 0
A6: G-0002 | B6: 46419 | C6: C5 | D6: C5-01 | E6: CT-10 | F6: Nacional | G6: Pago Consultoría individual (TDR: US$50,400) (2/3) | H6: Consultoría | I6: Préstamo | J6: 1700 | K6: Pagado | L6: Anticipo de fondos | M6: Sí | N6: =IF(D6="","",IF(INDEX(P1_POA!$B$5:$B$200,MATCH(D6,P1_POA!$A$5:$A$200,0))=C6,0,1)) -> 0
A7: G-0003 | B7: 46427 | C7: C5 | D7: C5-01 | E7: CT-10 | F7: Nacional | G7: Pago Consultoría individual (TDR: US$50,400) (3/3) | H7: Consultoría | I7: Préstamo | J7: 6820 | K7: Pagado | L7: Anticipo de fondos | M7: Sí | N7: =IF(D7="","",IF(INDEX(P1_POA!$B$5:$B$200,MATCH(D7,P1_POA!$A$5:$A$200,0))=C7,0,1)) -> 0
A8: G-0004 | B8: 46435 | C8: C5 | D8: C5-01 | E8: CT-11 | F8: Nacional | G8: Pago Consultoría individual (1/3) | H8: Consultoría | I8: Préstamo | J8: 5690 | K8: Pagado | L8: Anticipo de fondos | M8: Sí | N8: =IF(D8="","",IF(INDEX(P1_POA!$B$5:$B$200,MATCH(D8,P1_POA!$A$5:$A$200,0))=C8,0,1)) -> 0
A9: G-0005 | B9: 46443 | C9: C5 | D9: C5-01 | E9: CT-11 | F9: Nacional | G9: Pago Consultoría individual (2/3) | H9: Consultoría | I9: Préstamo | J9: 11500 | K9: Pagado | L9: Anticipo de fondos | M9: Sí | N9: =IF(D9="","",IF(INDEX(P1_POA!$B$5:$B$200,MATCH(D9,P1_POA!$A$5:$A$200,0))=C9,0,1)) -> 0
A10: G-0006 | B10: 46451 | C10: C4 | D10: C4-01 | E10: CT-08 | F10: Nacional | G10: Pago Diagnóstico institucional (1/2) | H10: Consultoría | I10: Préstamo | J10: 140870 | K10: Pagado | L10: Anticipo de fondos | M10: Sí | N10: =IF(D10="","",IF(INDEX(P1_POA!$B$5:$B$200,MATCH(D10,P1_POA!$A$5:$A$200,0))=C10,0,1)) -> 0
A11: G-0007 | B11: 46451 | C11: C5 | D11: C5-01 | E11: CT-11 | F11: Nacional | G11: Pago Consultoría individual (3/3) | H11: Consultoría | I11: Préstamo | J11: 6810 | K11: Pagado | L11: Anticipo de fondos | M11: Sí | N11: =IF(D11="","",IF(INDEX(P1_POA!$B$5:$B$200,MATCH(D11,P1_POA!$A$5:$A$200,0))=C11,0,1)) -> 0
A12: G-0008 | B12: 46451 | C12: C5 | D12: C5-02 | E12: CT-15 | F12: Nacional | G12: Pago Línea base y plan de M&E (1/2) | H12: Consultoría | I12: Préstamo | J12: 24870 | K12: Pagado | L12: Anticipo de fondos | M12: Sí | N12: =IF(D12="","",IF(INDEX(P1_POA!$B$5:$B$200,MATCH(D12,P1_POA!$A$5:$A$200,0))=C12,0,1)) -> 0
A13: G-0009 | B13: 46458 | C13: C5 | D13: C5-01 | E13: CT-12 | F13: Nacional | G13: Pago Consultoría individual (1/3) | H13: Consultoría | I13: Préstamo | J13: 11650 | K13: Pagado | L13: Anticipo de fondos | M13: Sí | N13: =IF(D13="","",IF(INDEX(P1_POA!$B$5:$B$200,MATCH(D13,P1_POA!$A$5:$A$200,0))=C13,0,1)) -> 0
A14: G-0010 | B14: 46464 | C14: C1 | D14: C1-01 | E14: CT-01 | F14: Nacional | G14: Pago Diseño del modelo de captación (1/1) | H14: Consultoría | I14: Préstamo | J14: 118000 | K14: Pagado | L14: Anticipo de fondos | M14: Sí | N14: =IF(D14="","",IF(INDEX(P1_POA!$B$5:$B$200,MATCH(D14,P1_POA!$A$5:$A$200,0))=C14,0,1)) -> 0
A15: G-0011 | B15: 46464 | C15: C1 | D15: C1-02 | F15: Ahuachapán | G15: Logística de reuniones y convenios regionales (1/3) | H15: Servicios de no consultoría | I15: Préstamo | J15: 33920 | K15: Pagado | L15: Anticipo de fondos | M15: Sí | N15: =IF(D15="","",IF(INDEX(P1_POA!$B$5:$B$200,MATCH(D15,P1_POA!$A$5:$A$200,0))=C15,0,1)) -> 0
A16: G-0012 | B16: 46464 | C16: C2 | D16: C2-01 | E16: CT-04 | F16: Nacional | G16: Pago Esquema de apoyos (1/1) | H16: Consultoría | I16: Préstamo | J16: 58800 | K16: Pagado | L16: Anticipo de fondos | M16: Sí | N16: =IF(D16="","",IF(INDEX(P1_POA!$B$5:$B$200,MATCH(D16,P1_POA!$A$5:$A$200,0))=C16,0,1)) -> 0
A17: G-0013 | B17: 46464 | C17: C3 | D17: C3-01 | E17: CT-06 | F17: Nacional | G17: Pago Diagnóstico de demanda laboral (1/2) | H17: Consultoría | I17: Préstamo | J17: 61360 | K17: Pagado | L17: Anticipo de fondos | M17: Sí | N17: =IF(D17="","",IF(INDEX(P1_POA!$B$5:$B$200,MATCH(D17,P1_POA!$A$5:$A$200,0))=C17,0,1)) -> 0
A18: G-0014 | B18: 46464 | C18: C5 | D18: C5-04 | E18: CT-16 | F18: Nacional | G18: Pago Gestión ambiental y social (1/1) | H18: Consultoría | I18: Donación | J18: 18000 | K18: Pagado | L18: Anticipo de fondos | M18: Sí | N18: =IF(D18="","",IF(INDEX(P1_POA!$B$5:$B$200,MATCH(D18,P1_POA!$A$5:$A$200,0))=C18,0,1)) -> 0
A19: G-0015 | B19: 46468 | C19: C5 | D19: C5-01 | E19: CT-12 | F19: Nacional | G19: Pago Consultoría individual (2/3) | H19: Consultoría | I19: Préstamo | J19: 710 | K19: Pagado | L19: Anticipo de fondos | M19: Sí | N19: =IF(D19="","",IF(INDEX(P1_POA!$B$5:$B$200,MATCH(D19,P1_POA!$A$5:$A$200,0))=C19,0,1)) -> 0
A20: G-0016 | B20: 46469 | C20: C1 | D20: C1-04 | E20: CT-02 | F20: Nacional | G20: Pago Plataforma de registro (1/2) | H20: Servicios de no consultoría | I20: Préstamo | J20: 45930 | K20: Pagado | L20: Pago directo | M20: N/A | N20: =IF(D20="","",IF(INDEX(P1_POA!$B$5:$B$200,MATCH(D20,P1_POA!$A$5:$A$200,0))=C20,0,1)) -> 0
A21: G-0017 | B21: 46476 | C21: C5 | D21: C5-01 | E21: CT-12 | F21: Nacional | G21: Pago Consultoría individual (3/3) | H21: Consultoría | I21: Préstamo | J21: 11640 | K21: Pagado | L21: Anticipo de fondos | M21: Sí | N21: =IF(D21="","",IF(INDEX(P1_POA!$B$5:$B$200,MATCH(D21,P1_POA!$A$5:$A$200,0))=C21,0,1)) -> 0
A22: G-0018 | B22: 46479 | C22: C1 | D22: C1-03 | E22: CT-03 | F22: Nacional | G22: Pago Campaña nacional de difusión (1/2) | H22: Servicios de no consultoría | I22: Préstamo | J22: 105820 | K22: Pagado | L22: Pago directo | M22: N/A | N22: =IF(D22="","",IF(INDEX(P1_POA!$B$5:$B$200,MATCH(D22,P1_POA!$A$5:$A$200,0))=C22,0,1)) -> 0
A23: G-0019 | B23: 46479 | C23: C4 | D23: C4-02 | E23: CT-09 | F23: Nacional | G23: Pago Sistema de información de trayectorias (1/2) | H23: Servicios de no consultoría | I23: Préstamo | J23: 195720 | K23: Pagado | L23: Pago directo | M23: N/A | N23: =IF(D23="","",IF(INDEX(P1_POA!$B$5:$B$200,MATCH(D23,P1_POA!$A$5:$A$200,0))=C23,0,1)) -> 0
A24: G-0020 | B24: 46484 | C24: C5 | D24: C5-01 | E24: CT-13 | F24: Nacional | G24: Pago Consultoría individual (1/3) | H24: Consultoría | I24: Préstamo | J24: 8740 | K24: Pagado | L24: Anticipo de fondos | M24: Sí | N24: =IF(D24="","",IF(INDEX(P1_POA!$B$5:$B$200,MATCH(D24,P1_POA!$A$5:$A$200,0))=C24,0,1)) -> 0
A25: G-0021 | B25: 46485 | C25: C2 | D25: C2-02 | F25: San Salvador | G25: Operativo de selección y verificación (1/3) | H25: Servicios de no consultoría | I25: Préstamo | J25: 36900 | K25: Pagado | L25: Anticipo de fondos | M25: Sí | N25: =IF(D25="","",IF(INDEX(P1_POA!$B$5:$B$200,MATCH(D25,P1_POA!$A$5:$A$200,0))=C25,0,1)) -> 0
A26: G-0022 | B26: 46490 | C26: C4 | D26: C4-01 | E26: CT-08 | F26: Nacional | G26: Pago Diagnóstico institucional (2/2) | H26: Consultoría | I26: Préstamo | J26: 191130 | K26: Pagado | L26: Anticipo de fondos | M26: Sí | N26: =IF(D26="","",IF(INDEX(P1_POA!$B$5:$B$200,MATCH(D26,P1_POA!$A$5:$A$200,0))=C26,0,1)) -> 0
A27: G-0023 | B27: 46490 | C27: C5 | D27: C5-02 | E27: CT-15 | F27: Nacional | G27: Pago Línea base y plan de M&E (2/2) | H27: Consultoría | I27: Préstamo | J27: 77330 | K27: Pagado | L27: Anticipo de fondos | M27: Sí | N27: =IF(D27="","",IF(INDEX(P1_POA!$B$5:$B$200,MATCH(D27,P1_POA!$A$5:$A$200,0))=C27,0,1)) -> 0
A28: G-0024 | B28: 46492 | C28: C5 | D28: C5-01 | E28: CT-13 | F28: Nacional | G28: Pago Consultoría individual (2/3) | H28: Consultoría | I28: Préstamo | J28: 10430 | K28: Pagado | L28: Anticipo de fondos | M28: Sí | N28: =IF(D28="","",IF(INDEX(P1_POA!$B$5:$B$200,MATCH(D28,P1_POA!$A$5:$A$200,0))=C28,0,1)) -> 0
A29: G-0025 | B29: 46493 | C29: C1 | D29: C1-04 | E29: CT-02 | F29: Nacional | G29: Pago Plataforma de registro (2/2) | H29: Servicios de no consultoría | I29: Préstamo | J29: 103170 | K29: Pagado | L29: Pago directo | M29: N/A | N29: =IF(D29="","",IF(INDEX(P1_POA!$B$5:$B$200,MATCH(D29,P1_POA!$A$5:$A$200,0))=C29,0,1)) -> 0
A30: G-0026 | B30: 46493 | C30: C2 | D30: C2-03 | F30: Ahuachapán | G30: Apoyos económicos a beneficiarios — Ahuachapán | H30: Transferencias a beneficiarios | I30: Préstamo | J30: 16080 | K30: Pagado | L30: Anticipo de fondos | M30: Sí | N30: =IF(D30="","",IF(INDEX(P1_POA!$B$5:$B$200,MATCH(D30,P1_POA!$A$5:$A$200,0))=C30,0,1)) -> 0
A31: G-0027 | B31: 46493 | C31: C5 | D31: C5-05 | F31: Nacional | G31: Productos de comunicación (1/2) | H31: Servicios de no consultoría | I31: Préstamo | J31: 15890 | K31: Pagado | L31: Anticipo de fondos | M31: Sí | N31: =IF(D31="","",IF(INDEX(P1_POA!$B$5:$B$200,MATCH(D31,P1_POA!$A$5:$A$200,0))=C31,0,1)) -> 0
A32: G-0028 | B32: 46498 | C32: C1 | D32: C1-02 | F32: La Paz | G32: Logística de reuniones y convenios regionales (2/3) | H32: Servicios de no consultoría | I32: Préstamo | J32: 27320 | K32: Pagado | L32: Anticipo de fondos | M32: Sí | N32: =IF(D32="","",IF(INDEX(P1_POA!$B$5:$B$200,MATCH(D32,P1_POA!$A$5:$A$200,0))=C32,0,1)) -> 0
A33: G-0029 | B33: 46498 | C33: C3 | D33: C3-01 | E33: CT-06 | F33: Nacional | G33: Pago Diagnóstico de demanda laboral (2/2) | H33: Consultoría | I33: Préstamo | J33: 123640 | K33: Pagado | L33: Anticipo de fondos | M33: Sí | N33: =IF(D33="","",IF(INDEX(P1_POA!$B$5:$B$200,MATCH(D33,P1_POA!$A$5:$A$200,0))=C33,0,1)) -> 0
A34: G-0030 | B34: 46498 | C34: C5 | D34: C5-04 | F34: Nacional | G34: Capacitación y mecanismo de quejas (1/2) | H34: Servicios de no consultoría | I34: Donación | J34: 13640 | K34: Pagado | L34: Anticipo de fondos | M34: Sí | N34: =IF(D34="","",IF(INDEX(P1_POA!$B$5:$B$200,MATCH(D34,P1_POA!$A$5:$A$200,0))=C34,0,1)) -> 0
A35: G-0031 | B35: 46500 | C35: C1 | D35: C1-03 | E35: CT-03 | F35: Nacional | G35: Pago Campaña nacional de difusión (2/2) | H35: Servicios de no consultoría | I35: Préstamo | J35: 36680 | K35: Pagado | L35: Pago directo | M35: N/A | N35: =IF(D35="","",IF(INDEX(P1_POA!$B$5:$B$200,MATCH(D35,P1_POA!$A$5:$A$200,0))=C35,0,1)) -> 0
A36: G-0032 | B36: 46500 | C36: C2 | D36: C2-03 | F36: Cabañas | G36: Apoyos económicos a beneficiarios — Cabañas | H36: Transferencias a beneficiarios | I36: Préstamo | J36: 7900 | K36: Pagado | L36: Anticipo de fondos | M36: Sí | N36: =IF(D36="","",IF(INDEX(P1_POA!$B$5:$B$200,MATCH(D36,P1_POA!$A$5:$A$200,0))=C36,0,1)) -> 0
A37: G-0033 | B37: 46500 | C37: C4 | D37: C4-02 | E37: CT-09 | F37: Nacional | G37: Pago Sistema de información de trayectorias (2/2) | H37: Servicios de no consultoría | I37: Préstamo | J37: 109130 | K37: Pagado | L37: Pago directo | M37: N/A | N37: =IF(D37="","",IF(INDEX(P1_POA!$B$5:$B$200,MATCH(D37,P1_POA!$A$5:$A$200,0))=C37,0,1)) -> 0
A38: G-0034 | B38: 46500 | C38: C5 | D38: C5-01 | E38: CT-13 | F38: Nacional | G38: Pago Consultoría individual (3/3) | H38: Consultoría | I38: Préstamo | J38: 4830 | K38: Pagado | L38: Anticipo de fondos | M38: Sí | N38: =IF(D38="","",IF(INDEX(P1_POA!$B$5:$B$200,MATCH(D38,P1_POA!$A$5:$A$200,0))=C38,0,1)) -> 0
A39: G-0035 | B39: 46505 | C39: C2 | D39: C2-03 | F39: Chalatenango | G39: Apoyos económicos a beneficiarios — Chalatenango | H39: Transferencias a beneficiarios | I39: Préstamo | J39: 13590 | K39: Pagado | L39: Anticipo de fondos | M39: Sí | N39: =IF(D39="","",IF(INDEX(P1_POA!$B$5:$B$200,MATCH(D39,P1_POA!$A$5:$A$200,0))=C39,0,1)) -> 0
A40: G-0036 | B40: 46507 | C40: C5 | D40: C5-01 | E40: CT-14 | F40: Nacional | G40: Pago Consultoría individual (1/3) | H40: Consultoría | I40: Préstamo | J40: 10770 | K40: Pagado | L40: Anticipo de fondos | M40: Sí | N40: =IF(D40="","",IF(INDEX(P1_POA!$B$5:$B$200,MATCH(D40,P1_POA!$A$5:$A$200,0))=C40,0,1)) -> 0
A41: G-0037 | B41: 46510 | C41: C2 | D41: C2-03 | F41: Cuscatlán | G41: Apoyos económicos a beneficiarios — Cuscatlán | H41: Transferencias a beneficiarios | I41: Préstamo | J41: 13310 | K41: Pagado | L41: Anticipo de fondos | M41: Sí | N41: =IF(D41="","",IF(INDEX(P1_POA!$B$5:$B$200,MATCH(D41,P1_POA!$A$5:$A$200,0))=C41,0,1)) -> 0
A42: G-0038 | B42: 46512 | C42: C2 | D42: C2-02 | F42: La Paz | G42: Operativo de selección y verificación (2/3) | H42: Servicios de no consultoría | I42: Préstamo | J42: 54910 | K42: Pagado | L42: Anticipo de fondos | M42: Sí | N42: =IF(D42="","",IF(INDEX(P1_POA!$B$5:$B$200,MATCH(D42,P1_POA!$A$5:$A$200,0))=C42,0,1)) -> 0
A43: G-0039 | B43: 46514 | C43: C1 | D43: C1-01 | F43: Nacional | G43: Talleres de validación del modelo | H43: Servicios de no consultoría | I43: Préstamo | J43: 6000 | K43: Pagado | L43: Anticipo de fondos | M43: Sí | N43: =IF(D43="","",IF(INDEX(P1_POA!$B$5:$B$200,MATCH(D43,P1_POA!$A$5:$A$200,0))=C43,0,1)) -> 0
A44: G-0040 | B44: 46514 | C44: C2 | D44: C2-01 | F44: Nacional | G44: Talleres de consulta de criterios | H44: Servicios de no consultoría | I44: Préstamo | J44: 5000 | K44: Pagado | L44: Anticipo de fondos | M44: Sí | N44: =IF(D44="","",IF(INDEX(P1_POA!$B$5:$B$200,MATCH(D44,P1_POA!$A$5:$A$200,0))=C44,0,1)) -> 0
A45: G-0041 | B45: 46514 | C45: C2 | D45: C2-03 | F45: La Libertad | G45: Apoyos económicos a beneficiarios — La Libertad | H45: Transferencias a beneficiarios | I45: Préstamo | J45: 43680 | K45: Pagado | L45: Anticipo de fondos | M45: Sí | N45: =IF(D45="","",IF(INDEX(P1_POA!$B$5:$B$200,MATCH(D45,P1_POA!$A$5:$A$200,0))=C45,0,1)) -> 0
A46: G-0042 | B46: 46514 | C46: C2 | D46: C2-04 | E46: CT-05 | F46: Nacional | G46: Pago Tutorías y acompañamiento (1/2) | H46: Consultoría | I46: Préstamo | J46: 77120 | K46: Pagado | L46: Anticipo de fondos | M46: Sí | N46: =IF(D46="","",IF(INDEX(P1_POA!$B$5:$B$200,MATCH(D46,P1_POA!$A$5:$A$200,0))=C46,0,1)) -> 0
A47: G-0043 | B47: 46514 | C47: C3 | D47: C3-02 | E47: CT-07 | F47: Nacional | G47: Pago Alianzas con empleadores (1/1) | H47: Consultoría | I47: Préstamo | J47: 27200 | K47: Pagado | L47: Anticipo de fondos | M47: Sí | N47: =IF(D47="","",IF(INDEX(P1_POA!$B$5:$B$200,MATCH(D47,P1_POA!$A$5:$A$200,0))=C47,0,1)) -> 0
A48: G-0044 | B48: 46514 | C48: C4 | D48: C4-04 | F48: Nacional | G48: Especificaciones técnicas (1/2) | H48: Servicios de no consultoría | I48: Préstamo | J48: 17640 | K48: Pagado | L48: Anticipo de fondos | M48: Sí | N48: =IF(D48="","",IF(INDEX(P1_POA!$B$5:$B$200,MATCH(D48,P1_POA!$A$5:$A$200,0))=C48,0,1)) -> 0
A49: G-0045 | B49: 46517 | C49: C1 | D49: C1-04 | F49: Nacional | G49: Licencias y alojamiento en la nube (1/2) | H49: Bienes | I49: Préstamo | J49: 27860 | K49: Pagado | L49: Anticipo de fondos | M49: Sí | N49: =IF(D49="","",IF(INDEX(P1_POA!$B$5:$B$200,MATCH(D49,P1_POA!$A$5:$A$200,0))=C49,0,1)) -> 0
A50: G-0046 | B50: 46517 | C50: C5 | D50: C5-01 | E50: CT-14 | F50: Nacional | G50: Pago Consultoría individual (2/3) | H50: Consultoría | I50: Préstamo | J50: 2210 | K50: Pagado | L50: Anticipo de fondos | M50: Sí | N50: =IF(D50="","",IF(INDEX(P1_POA!$B$5:$B$200,MATCH(D50,P1_POA!$A$5:$A$200,0))=C50,0,1)) -> 0
A51: G-0047 | B51: 46520 | C51: C2 | D51: C2-03 | F51: La Paz | G51: Apoyos económicos a beneficiarios — La Paz | H51: Transferencias a beneficiarios | I51: Préstamo | J51: 19270 | K51: Pagado | L51: Anticipo de fondos | M51: Sí | N51: =IF(D51="","",IF(INDEX(P1_POA!$B$5:$B$200,MATCH(D51,P1_POA!$A$5:$A$200,0))=C51,0,1)) -> 0
A52: G-0048 | B52: 46521 | C52: C1 | D52: C1-03 | F52: Nacional | G52: Producción de materiales de difusión (1/2) | H52: Bienes | I52: Préstamo | J52: 6200 | K52: Pagado | L52: Anticipo de fondos | M52: Sí | N52: =IF(D52="","",IF(INDEX(P1_POA!$B$5:$B$200,MATCH(D52,P1_POA!$A$5:$A$200,0))=C52,0,1)) -> 0
A53: G-0049 | B53: 46521 | C53: C4 | D53: C4-02 | F53: Nacional | G53: Infraestructura y pruebas (1/2) | H53: Bienes | I53: Préstamo | J53: 15560 | K53: Pagado | L53: Anticipo de fondos | M53: Sí | N53: =IF(D53="","",IF(INDEX(P1_POA!$B$5:$B$200,MATCH(D53,P1_POA!$A$5:$A$200,0))=C53,0,1)) -> 0
A54: G-0050 | B54: 46525 | C54: C2 | D54: C2-03 | F54: La Unión | G54: Apoyos económicos a beneficiarios — La Unión | H54: Transferencias a beneficiarios | I54: Préstamo | J54: 12890 | K54: Pagado | L54: Anticipo de fondos | M54: Sí | N54: =IF(D54="","",IF(INDEX(P1_POA!$B$5:$B$200,MATCH(D54,P1_POA!$A$5:$A$200,0))=C54,0,1)) -> 0
A55: G-0051 | B55: 46525 | C55: C5 | D55: C5-01 | E55: CT-14 | F55: Nacional | G55: Pago Consultoría individual (3/3) | H55: Consultoría | I55: Préstamo | J55: 11020 | K55: Pagado | L55: Anticipo de fondos | M55: Sí | N55: =IF(D55="","",IF(INDEX(P1_POA!$B$5:$B$200,MATCH(D55,P1_POA!$A$5:$A$200,0))=C55,0,1)) -> 0
A56: G-0052 | B56: 46528 | C56: C2 | D56: C2-03 | F56: Morazán | G56: Apoyos económicos a beneficiarios — Morazán | H56: Transferencias a beneficiarios | I56: Préstamo | J56: 9150 | K56: Pagado | L56: Anticipo de fondos | M56: Sí | N56: =IF(D56="","",IF(INDEX(P1_POA!$B$5:$B$200,MATCH(D56,P1_POA!$A$5:$A$200,0))=C56,0,1)) -> 0
A57: G-0053 | B57: 46528 | C57: C2 | D57: C2-04 | E57: CT-05 | F57: Nacional | G57: Pago Tutorías y acompañamiento (2/2) | H57: Consultoría | I57: Préstamo | J57: 41380 | K57: Pagado | L57: Anticipo de fondos | M57: Sí | N57: =IF(D57="","",IF(INDEX(P1_POA!$B$5:$B$200,MATCH(D57,P1_POA!$A$5:$A$200,0))=C57,0,1)) -> 0
A58: G-0054 | B58: 46528 | C58: C4 | D58: C4-01 | F58: Nacional | G58: Talleres con instituciones | H58: Servicios de no consultoría | I58: Préstamo | J58: 6000 | K58: Pagado | L58: Anticipo de fondos | M58: Sí | N58: =IF(D58="","",IF(INDEX(P1_POA!$B$5:$B$200,MATCH(D58,P1_POA!$A$5:$A$200,0))=C58,0,1)) -> 0
A59: G-0055 | B59: 46528 | C59: C5 | D59: C5-02 | F59: Nacional | G59: Trabajo de campo línea base | H59: Servicios de no consultoría | I59: Préstamo | J59: 15000 | K59: Pagado | L59: Anticipo de fondos | M59: Sí | N59: =IF(D59="","",IF(INDEX(P1_POA!$B$5:$B$200,MATCH(D59,P1_POA!$A$5:$A$200,0))=C59,0,1)) -> 0
A60: G-0056 | B60: 46528 | C60: C5 | D60: C5-05 | F60: Nacional | G60: Productos de comunicación (2/2) | H60: Servicios de no consultoría | I60: Préstamo | J60: 12110 | K60: Pagado | L60: Anticipo de fondos | M60: Sí | N60: =IF(D60="","",IF(INDEX(P1_POA!$B$5:$B$200,MATCH(D60,P1_POA!$A$5:$A$200,0))=C60,0,1)) -> 0
A61: G-0057 | B61: 46532 | C61: C1 | D61: C1-02 | F61: Morazán | G61: Logística de reuniones y convenios regionales (3/3) | H61: Servicios de no consultoría | I61: Préstamo | J61: 66760 | K61: Pagado | L61: Anticipo de fondos | M61: Sí | N61: =IF(D61="","",IF(INDEX(P1_POA!$B$5:$B$200,MATCH(D61,P1_POA!$A$5:$A$200,0))=C61,0,1)) -> 0
A62: G-0058 | B62: 46532 | C62: C3 | D62: C3-01 | F62: Nacional | G62: Levantamiento de información | H62: Servicios de no consultoría | I62: Préstamo | J62: 4000 | K62: Pagado | L62: Anticipo de fondos | M62: Sí | N62: =IF(D62="","",IF(INDEX(P1_POA!$B$5:$B$200,MATCH(D62,P1_POA!$A$5:$A$200,0))=C62,0,1)) -> 0
A63: G-0059 | B63: 46532 | C63: C5 | D63: C5-04 | F63: Nacional | G63: Capacitación y mecanismo de quejas (2/2) | H63: Servicios de no consultoría | I63: Donación | J63: 6360 | K63: Pagado | L63: Anticipo de fondos | M63: Sí | N63: =IF(D63="","",IF(INDEX(P1_POA!$B$5:$B$200,MATCH(D63,P1_POA!$A$5:$A$200,0))=C63,0,1)) -> 0
A64: G-0060 | B64: 46533 | C64: C5 | D64: C5-01 | F64: Nacional | G64: Equipo de oficina y servicios (1/2) | H64: Costos operativos | I64: Préstamo | J64: 26220 | K64: Pagado | L64: Anticipo de fondos | M64: Sí | N64: =IF(D64="","",IF(INDEX(P1_POA!$B$5:$B$200,MATCH(D64,P1_POA!$A$5:$A$200,0))=C64,0,1)) -> 0
A65: G-0061 | B65: 46535 | C65: C2 | D65: C2-03 | F65: San Miguel | G65: Apoyos económicos a beneficiarios — San Miguel | H65: Transferencias a beneficiarios | I65: Préstamo | J65: 31340 | K65: Pagado | L65: Anticipo de fondos | M65: Sí | N65: =IF(D65="","",IF(INDEX(P1_POA!$B$5:$B$200,MATCH(D65,P1_POA!$A$5:$A$200,0))=C65,0,1)) -> 0
A66: G-0062 | B66: 46535 | C66: C2 | D66: C2-05 | F66: San Vicente | G66: Consultas y ajustes razonables (1/2) | H66: Servicios de no consultoría | I66: Donación | J66: 11460 | K66: Pagado | L66: Anticipo de fondos | M66: Sí | N66: =IF(D66="","",IF(INDEX(P1_POA!$B$5:$B$200,MATCH(D66,P1_POA!$A$5:$A$200,0))=C66,0,1)) -> 0
A67: G-0063 | B67: 46535 | C67: C3 | D67: C3-03 | F67: Cuscatlán | G67: Talleres de diseño de rutas (1/2) | H67: Servicios de no consultoría | I67: Préstamo | J67: 18890 | K67: Pagado | L67: Anticipo de fondos | M67: Sí | N67: =IF(D67="","",IF(INDEX(P1_POA!$B$5:$B$200,MATCH(D67,P1_POA!$A$5:$A$200,0))=C67,0,1)) -> 0
A68: G-0064 | B68: 46539 | C68: C2 | D68: C2-02 | F68: La Libertad | G68: Operativo de selección y verificación (3/3) | H68: Servicios de no consultoría | I68: Préstamo | J68: 58190 | K68: Pagado | L68: Anticipo de fondos | M68: No | N68: =IF(D68="","",IF(INDEX(P1_POA!$B$5:$B$200,MATCH(D68,P1_POA!$A$5:$A$200,0))=C68,0,1)) -> 0
A69: G-0065 | B69: 46540 | C69: C2 | D69: C2-03 | F69: San Salvador | G69: Apoyos económicos a beneficiarios — San Salvador | H69: Transferencias a beneficiarios | I69: Préstamo | J69: 56290 | K69: Pagado | L69: Anticipo de fondos | M69: No | N69: =IF(D69="","",IF(INDEX(P1_POA!$B$5:$B$200,MATCH(D69,P1_POA!$A$5:$A$200,0))=C69,0,1)) -> 0
... A88: G-0084 | B88: 46560 | C88: C2 | D88: C2-03 | F88: Usulután | G88: Apoyos económicos a beneficiarios — Usulután | H88: Transferencias a beneficiarios | I88: Préstamo | J88: 25810 | K88: Pagado | L88: Anticipo de fondos | M88: No | N88: =IF(D88="","",IF(INDEX(P1_POA!$B$5:$B$200,MATCH(D88,P1_POA!$A$5:$A$200,0))=C88,0,1)) -> 0

Sheet F3_Desembolsos
A1: F3 · Solicitudes de desembolso y control de anticipos
A2: DATOS SIMULADOS con fines de demostración metodológica — no son cifras reales del BID ni de la Dirección de Integración.
A3: Mecanismos: anticipo de fondos, reembolso de gastos y pago directo a proveedores. Bloque derecho = control del anticipo.
A4: ID solicitud | B4: Fecha solicitud | C4: Mecanismo | D4: Fuente | E4: Monto solicitado | F4: Estado | G4: Fecha desembolso | H4: Monto desembolsado | I4: Días de trámite | K4: Control de anticipos | L4: Valor
A5: DS-01 | B5: 46415 | C5: Anticipo de fondos | D5: Préstamo | E5: 2400000 | F5: Desembolsado | G5: 46428 | H5: 2400000 | I5: =IF(G5<>"",G5-B5,IF(AND(B5<>"",F5="Solicitado"),Fecha_Corte-B5,"")) -> 13 | K5: Anticipos desembolsados (USD) | L5: =SUMIFS($H$5:$H$500,$C$5:$C$500,"Anticipo de fondos",$F$5:$F$500,"Desembolsado") -> 2400000
A6: DS-02 | B6: 46460 | C6: Pago directo | D6: Préstamo | E6: 149100 | F6: Desembolsado | G6: 46469 | H6: 149100 | I6: =IF(G6<>"",G6-B6,IF(AND(B6<>"",F6="Solicitado"),Fecha_Corte-B6,"")) -> 9 | K6: Gasto pagado con anticipo (USD) | L6: =SUMIFS(F2_Ejecucion!$J$5:$J$500,F2_Ejecucion!$L$5:$L$500,"Anticipo de fondos",F2_Ejecucion!$K$5:$K$500,"Pagado") -> 2131900
A7: DS-03 | B7: 46470 | C7: Pago directo | D7: Préstamo | E7: 142500 | F7: Desembolsado | G7: 46479 | H7: 142500 | I7: =IF(G7<>"",G7-B7,IF(AND(B7<>"",F7="Solicitado"),Fecha_Corte-B7,"")) -> 9 | K7: Gasto justificado ante el BID (USD) | L7: =SUMIFS(F2_Ejecucion!$J$5:$J$500,F2_Ejecucion!$M$5:$M$500,"Sí") -> 1675750
A8: DS-04 | B8: 46470 | C8: Pago directo | D8: Préstamo | E8: 304850 | F8: Desembolsado | G8: 46479 | H8: 304850 | I8: =IF(G8<>"",G8-B8,IF(AND(B8<>"",F8="Solicitado"),Fecha_Corte-B8,"")) -> 9 | K8: % justificado sobre anticipos | L8: =IF(L5=0,"n/a",L7/L5) -> 0.69822917
A9: DS-05 | C9: Anticipo de fondos | D9: Préstamo | E9: 1800000 | F9: En preparación | I9: =IF(G9<>"",G9-B9,IF(AND(B9<>"",F9="Solicitado"),Fecha_Corte-B9,"")) | K9: Saldo de anticipo por justificar (USD) | L9: =L5-L7 -> 724250
K10: Fondos disponibles de anticipo (USD) | L10: =L5-L6 -> 268100
K11: Pagos directos desembolsados (USD) | L11: =SUMIFS($H$5:$H$500,$C$5:$C$500,"Pago directo",$F$5:$F$500,"Desembolsado") -> 596450
K12: Pagos directos registrados en el libro (USD) | L12: =SUMIFS(F2_Ejecucion!$J$5:$J$500,F2_Ejecucion!$L$5:$L$500,"Pago directo",F2_Ejecucion!$K$5:$K$500,"Pagado") -> 596450
K13: Total desembolsado por el BID (USD) | L13: =L5+L11 -> 2996450
K14: Desembolsado / total del Programa | L14: =L13/Total_Programa -> 0.028812019
K15: Alerta para solicitar nuevo anticipo | L15: =IF(L8="n/a","",IF(L8>=Pct_Justif_Min,"Puede solicitar nuevo anticipo","NO solicitar: justificar al "&ROUND(Pct_Justif_Min*100,0)&"% (faltan US$ "&ROUND(Pct_Justif_Min*L5-L7,0)&")")) -> NO solicitar: justificar al 80% (faltan US$ 244250)
K17: El umbral de justificación (Pct_Justif_Min) es un parámetro a validar con el Contrato de Préstamo.

Sheet F3_Plan_Financiero
A1: F3 · Plan financiero trimestral (proyectado vs. real)
A2: DATOS SIMULADOS con fines de demostración metodológica — no son cifras reales del BID ni de la Dirección de Integración.
A3: Proyección de gasto por trimestre (base para calcular anticipos). Real = suma del libro de gastos en el trimestre.
A4: Trimestre | B4: Inicio | C4: Fin | D4: Proyectado USD | E4: Real USD | F4: Proyectado acumulado | G4: Real acumulado | H4: Variación acumulada | I4: Cumplimiento acumulado
A5: 2027-T1 | B5: 46388 | C5: 46477 | D5: 780000 | E5: =SUMIFS(F2_Ejecucion!$J$5:$J$500,F2_Ejecucion!$B$5:$B$500,">="&B5,F2_Ejecucion!$B$5:$B$500,"<="&C5) -> 574950 | F5: =SUM($D$5:D5) -> 780000 | G5: =IF(B5>Fecha_Corte,"",SUM($E$5:E5)) -> 574950 | H5: =IF(G5="","",G5-F5) -> -205050 | I5: =IF(G5="","",G5/F5) -> 0.73711538
A6: 2027-T2 | B6: 46478 | C6: 46568 | D6: 1950000 | E6: =SUMIFS(F2_Ejecucion!$J$5:$J$500,F2_Ejecucion!$B$5:$B$500,">="&B6,F2_Ejecucion!$B$5:$B$500,"<="&C6) -> 2153400 | F6: =SUM($D$5:D6) -> 2730000 | G6: =IF(B6>Fecha_Corte,"",SUM($E$5:E6)) -> 2728350 | H6: =IF(G6="","",G6-F6) -> -1650 | I6: =IF(G6="","",G6/F6) -> 0.9993956
A7: 2027-T3 | B7: 46569 | C7: 46660 | D7: 1820000 | E7: =SUMIFS(F2_Ejecucion!$J$5:$J$500,F2_Ejecucion!$B$5:$B$500,">="&B7,F2_Ejecucion!$B$5:$B$500,"<="&C7) -> 0 | F7: =SUM($D$5:D7) -> 4550000 | G7: =IF(B7>Fecha_Corte,"",SUM($E$5:E7)) | H7: =IF(G7="","",G7-F7) | I7: =IF(G7="","",G7/F7)
A8: 2027-T4 | B8: 46661 | C8: 46752 | D8: 1950000 | E8: =SUMIFS(F2_Ejecucion!$J$5:$J$500,F2_Ejecucion!$B$5:$B$500,">="&B8,F2_Ejecucion!$B$5:$B$500,"<="&C8) -> 0 | F8: =SUM($D$5:D8) -> 6500000 | G8: =IF(B8>Fecha_Corte,"",SUM($E$5:E8)) | H8: =IF(G8="","",G8-F8) | I8: =IF(G8="","",G8/F8)
A9: 2028-T1 | B9: 46753 | C9: 46843 | D9: 4720000 | E9: =SUMIFS(F2_Ejecucion!$J$5:$J$500,F2_Ejecucion!$B$5:$B$500,">="&B9,F2_Ejecucion!$B$5:$B$500,"<="&C9) -> 0 | F9: =SUM($D$5:D9) -> 11220000 | G9: =IF(B9>Fecha_Corte,"",SUM($E$5:E9)) | H9: =IF(G9="","",G9-F9) | I9: =IF(G9="","",G9/F9)
A10: 2028-T2 | B10: 46844 | C10: 46934 | D10: 5360000 | E10: =SUMIFS(F2_Ejecucion!$J$5:$J$500,F2_Ejecucion!$B$5:$B$500,">="&B10,F2_Ejecucion!$B$5:$B$500,"<="&C10) -> 0 | F10: =SUM($D$5:D10) -> 16580000 | G10: =IF(B10>Fecha_Corte,"",SUM($E$5:E10)) | H10: =IF(G10="","",G10-F10) | I10: =IF(G10="","",G10/F10)
A11: 2028-T3 | B11: 46935 | C11: 47026 | D11: 5570000 | E11: =SUMIFS(F2_Ejecucion!$J$5:$J$500,F2_Ejecucion!$B$5:$B$500,">="&B11,F2_Ejecucion!$B$5:$B$500,"<="&C11) -> 0 | F11: =SUM($D$5:D11) -> 22150000 | G11: =IF(B11>Fecha_Corte,"",SUM($E$5:E11)) | H11: =IF(G11="","",G11-F11) | I11: =IF(G11="","",G11/F11)
A12: 2028-T4 | B12: 47027 | C12: 47118 | D12: 5790000 | E12: =SUMIFS(F2_Ejecucion!$J$5:$J$500,F2_Ejecucion!$B$5:$B$500,">="&B12,F2_Ejecucion!$B$5:$B$500,"<="&C12) -> 0 | F12: =SUM($D$5:D12) -> 27940000 | G12: =IF(B12>Fecha_Corte,"",SUM($E$5:E12)) | H12: =IF(G12="","",G12-F12) | I12: =IF(G12="","",G12/F12)
A14: La proyección del año 1 suma el POA vigente; la del año 2 suma el PEP. Se revisa cada trimestre y sustenta la solicitud de anticipos.

Sheet F4_Plan_Adquisiciones
A1: F4 · Plan de Adquisiciones (PA) y seguimiento de procesos
A2: DATOS SIMULADOS con fines de demostración metodológica — no son cifras reales del BID ni de la Dirección de Integración.
A3: Métodos según políticas GN-2349-15 (bienes, obras y servicios de no consultoría) y GN-2350-15 (consultorías). Los montos umbral de cada método están en el PA aprobado por el BID (no se reproducen aquí).
A4: ID PA | B4: Comp. | C4: Actividad POA | D4: Descripción | E4: Categoría | F4: Método | G4: Revisión | H4: Monto estimado | I4: Estado del proceso | J4: Publicación prevista | K4: Publicación real | L4: Adjudicación prevista | M4: Adjudicación real | N4: Desvío adjudicación (días) | O4: Monto contratado | P4: Alerta
A5: PA-01 | B5: C1 | C5: C1-01 | D5: Consultoría: diseño del modelo de captación | E5: Consultoría (firma) | F5: SBCC | G5: Ex ante | H5: 125000 | I5: Contratado | J5: 46419 | K5: 46420 | L5: 46456 | M5: 46455 | N5: =IF(M5<>"",M5-L5,IF(L5<>"",MAX(0,Fecha_Corte-L5),"")) -> -1 | O5: =SUMIFS(F5_Contratos!$G$5:$G$200,F5_Contratos!$B$5:$B$200,A5) -> 118000 | P5: =IF(OR(I5="Contratado",I5="Cerrado"),IF(N5>0,"Contratado con atraso","Contratado a tiempo"),IF(AND(K5="",J5<>"",Fecha_Corte>J5),"Atrasado",IF(L5="","Sin fecha prevista",IF(Fecha_Corte>L5,"Atrasado",IF(L5-Fecha_Corte<=Dias_Alerta,"Próximo a vencer","En plazo"))))) -> Contratado a tiempo
A6: PA-02 | B6: C1 | C6: C1-04 | D6: Plataforma de registro de aspirantes | E6: Servicios de no consultoría | F6: LPN | G6: Ex ante | H6: 260000 | I6: Contratado | J6: 46433 | K6: 46438 | L6: 46492 | M6: 46503 | N6: =IF(M6<>"",M6-L6,IF(L6<>"",MAX(0,Fecha_Corte-L6),"")) -> 11 | O6: =SUMIFS(F5_Contratos!$G$5:$G$200,F5_Contratos!$B$5:$B$200,A6) -> 248500 | P6: =IF(OR(I6="Contratado",I6="Cerrado"),IF(N6>0,"Contratado con atraso","Contratado a tiempo"),IF(AND(K6="",J6<>"",Fecha_Corte>J6),"Atrasado",IF(L6="","Sin fecha prevista",IF(Fecha_Corte>L6,"Atrasado",IF(L6-Fecha_Corte<=Dias_Alerta,"Próximo a vencer","En plazo"))))) -> Contratado con atraso
A7: PA-03 | B7: C1 | C7: C1-03 | D7: Campaña nacional de difusión | E7: Servicios de no consultoría | F7: Comparación de precios | G7: Ex post | H7: 300000 | I7: Contratado | J7: 46447 | K7: 46449 | L7: 46497 | M7: 46499 | N7: =IF(M7<>"",M7-L7,IF(L7<>"",MAX(0,Fecha_Corte-L7),"")) -> 2 | O7: =SUMIFS(F5_Contratos!$G$5:$G$200,F5_Contratos!$B$5:$B$200,A7) -> 285000 | P7: =IF(OR(I7="Contratado",I7="Cerrado"),IF(N7>0,"Contratado con atraso","Contratado a tiempo"),IF(AND(K7="",J7<>"",Fecha_Corte>J7),"Atrasado",IF(L7="","Sin fecha prevista",IF(Fecha_Corte>L7,"Atrasado",IF(L7-Fecha_Corte<=Dias_Alerta,"Próximo a vencer","En plazo"))))) -> Contratado con atraso
A8: PA-04 | B8: C2 | C8: C2-01 | D8: Consultoría individual: esquema de apoyos | E8: Consultor individual | F8: 3CV | G8: Ex ante | H8: 60000 | I8: Contratado | J8: 46405 | K8: 46405 | L8: 46433 | M8: 46430 | N8: =IF(M8<>"",M8-L8,IF(L8<>"",MAX(0,Fecha_Corte-L8),"")) -> -3 | O8: =SUMIFS(F5_Contratos!$G$5:$G$200,F5_Contratos!$B$5:$B$200,A8) -> 58800 | P8: =IF(OR(I8="Contratado",I8="Cerrado"),IF(N8>0,"Contratado con atraso","Contratado a tiempo"),IF(AND(K8="",J8<>"",Fecha_Corte>J8),"Atrasado",IF(L8="","Sin fecha prevista",IF(Fecha_Corte>L8,"Atrasado",IF(L8-Fecha_Corte<=Dias_Alerta,"Próximo a vencer","En plazo"))))) -> Contratado a tiempo
A9: PA-05 | B9: C2 | C9: C2-04 | D9: Servicios de tutorías y acompañamiento | E9: Consultoría (firma) | F9: SBCC | G9: Ex ante | H9: 400000 | I9: Contratado | J9: 46461 | K9: 46464 | L9: 46517 | M9: 46531 | N9: =IF(M9<>"",M9-L9,IF(L9<>"",MAX(0,Fecha_Corte-L9),"")) -> 14 | O9: =SUMIFS(F5_Contratos!$G$5:$G$200,F5_Contratos!$B$5:$B$200,A9) -> 395000 | P9: =IF(OR(I9="Contratado",I9="Cerrado"),IF(N9>0,"Contratado con atraso","Contratado a tiempo"),IF(AND(K9="",J9<>"",Fecha_Corte>J9),"Atrasado",IF(L9="","Sin fecha prevista",IF(Fecha_Corte>L9,"Atrasado",IF(L9-Fecha_Corte<=Dias_Alerta,"Próximo a vencer","En plazo"))))) -> Contratado con atraso
A10: PA-06 | B10: C2 | C10: C2-05 | D10: Equipamiento de accesibilidad | E10: Bienes | F10: LPN | G10: Ex ante | H10: 240000 | I10: Publicado | J10: 46522 | K10: 46539 | L10: 46614 | N10: =IF(M10<>"",M10-L10,IF(L10<>"",MAX(0,Fecha_Corte-L10),"")) -> 0 | O10: =SUMIFS(F5_Contratos!$G$5:$G$200,F5_Contratos!$B$5:$B$200,A10) -> 0 | P10: =IF(OR(I10="Contratado",I10="Cerrado"),IF(N10>0,"Contratado con atraso","Contratado a tiempo"),IF(AND(K10="",J10<>"",Fecha_Corte>J10),"Atrasado",IF(L10="","Sin fecha prevista",IF(Fecha_Corte>L10,"Atrasado",IF(L10-Fecha_Corte<=Dias_Alerta,"Próximo a vencer","En plazo"))))) -> En plazo
A11: PA-07 | B11: C3 | C11: C3-01 | D11: Consultoría: diagnóstico de demanda laboral | E11: Consultoría (firma) | F11: SBCC | G11: Ex ante | H11: 190000 | I11: Contratado | J11: 46419 | K11: 46421 | L11: 46477 | M11: 46475 | N11: =IF(M11<>"",M11-L11,IF(L11<>"",MAX(0,Fecha_Corte-L11),"")) -> -2 | O11: =SUMIFS(F5_Contratos!$G$5:$G$200,F5_Contratos!$B$5:$B$200,A11) -> 185000 | P11: =IF(OR(I11="Contratado",I11="Cerrado"),IF(N11>0,"Contratado con atraso","Contratado a tiempo"),IF(AND(K11="",J11<>"",Fecha_Corte>J11),"Atrasado",IF(L11="","Sin fecha prevista",IF(Fecha_Corte>L11,"Atrasado",IF(L11-Fecha_Corte<=Dias_Alerta,"Próximo a vencer","En plazo"))))) -> Contratado a tiempo
A12: PA-08 | B12: C3 | C12: C3-02 | D12: Consultoría individual: alianzas con empleadores | E12: Consultor individual | F12: 3CV | G12: Ex ante | H12: 70000 | I12: Contratado | J12: 46461 | K12: 46462 | L12: 46507 | M12: 46514 | N12: =IF(M12<>"",M12-L12,IF(L12<>"",MAX(0,Fecha_Corte-L12),"")) -> 7 | O12: =SUMIFS(F5_Contratos!$G$5:$G$200,F5_Contratos!$B$5:$B$200,A12) -> 68000 | P12: =IF(OR(I12="Contratado",I12="Cerrado"),IF(N12>0,"Contratado con atraso","Contratado a tiempo"),IF(AND(K12="",J12<>"",Fecha_Corte>J12),"Atrasado",IF(L12="","Sin fecha prevista",IF(Fecha_Corte>L12,"Atrasado",IF(L12-Fecha_Corte<=Dias_Alerta,"Próximo a vencer","En plazo"))))) -> Contratado con atraso
A13: PA-09 | B13: C4 | C13: C4-01 | D13: Consultoría: diagnóstico institucional | E13: Consultoría (firma) | F13: SBCC | G13: Ex ante | H13: 340000 | I13: Contratado | J13: 46407 | K13: 46409 | L13: 46461 | M13: 46458 | N13: =IF(M13<>"",M13-L13,IF(L13<>"",MAX(0,Fecha_Corte-L13),"")) -> -3 | O13: =SUMIFS(F5_Contratos!$G$5:$G$200,F5_Contratos!$B$5:$B$200,A13) -> 332000 | P13: =IF(OR(I13="Contratado",I13="Cerrado"),IF(N13>0,"Contratado con atraso","Contratado a tiempo"),IF(AND(K13="",J13<>"",Fecha_Corte>J13),"Atrasado",IF(L13="","Sin fecha prevista",IF(Fecha_Corte>L13,"Atrasado",IF(L13-Fecha_Corte<=Dias_Alerta,"Próximo a vencer","En plazo"))))) -> Contratado a tiempo
A14: PA-10 | B14: C4 | C14: C4-02 | D14: Sistema de información de trayectorias | E14: Servicios de no consultoría | F14: LPI | G14: Ex ante | H14: 900000 | I14: Contratado | J14: 46447 | K14: 46454 | L14: 46522 | M14: 46534 | N14: =IF(M14<>"",M14-L14,IF(L14<>"",MAX(0,Fecha_Corte-L14),"")) -> 12 | O14: =SUMIFS(F5_Contratos!$G$5:$G$200,F5_Contratos!$B$5:$B$200,A14) -> 871000 | P14: =IF(OR(I14="Contratado",I14="Cerrado"),IF(N14>0,"Contratado con atraso","Contratado a tiempo"),IF(AND(K14="",J14<>"",Fecha_Corte>J14),"Atrasado",IF(L14="","Sin fecha prevista",IF(Fecha_Corte>L14,"Atrasado",IF(L14-Fecha_Corte<=Dias_Alerta,"Próximo a vencer","En plazo"))))) -> Contratado con atraso
A15: PA-11 | B15: C4 | C15: C4-04 | D15: Equipamiento tecnológico para instituciones | E15: Bienes | F15: LPI | G15: Ex ante | H15: 600000 | I15: Evaluación | J15: 46492 | K15: 46537 | L15: 46583 | N15: =IF(M15<>"",M15-L15,IF(L15<>"",MAX(0,Fecha_Corte-L15),"")) -> 0 | O15: =SUMIFS(F5_Contratos!$G$5:$G$200,F5_Contratos!$B$5:$B$200,A15) -> 0 | P15: =IF(OR(I15="Contratado",I15="Cerrado"),IF(N15>0,"Contratado con atraso","Contratado a tiempo"),IF(AND(K15="",J15<>"",Fecha_Corte>J15),"Atrasado",IF(L15="","Sin fecha prevista",IF(Fecha_Corte>L15,"Atrasado",IF(L15-Fecha_Corte<=Dias_Alerta,"Próximo a vencer","En plazo"))))) -> Próximo a vencer
A16: PA-12 | B16: C4 | C16: C4-03 | D16: Consultoría: capacitación a instituciones | E16: Consultoría (firma) | F16: SBCC | G16: Ex ante | H16: 380000 | I16: Preparación | J16: 46522 | L16: 46614 | N16: =IF(M16<>"",M16-L16,IF(L16<>"",MAX(0,Fecha_Corte-L16),"")) -> 0 | O16: =SUMIFS(F5_Contratos!$G$5:$G$200,F5_Contratos!$B$5:$B$200,A16) -> 0 | P16: =IF(OR(I16="Contratado",I16="Cerrado"),IF(N16>0,"Contratado con atraso","Contratado a tiempo"),IF(AND(K16="",J16<>"",Fecha_Corte>J16),"Atrasado",IF(L16="","Sin fecha prevista",IF(Fecha_Corte>L16,"Atrasado",IF(L16-Fecha_Corte<=Dias_Alerta,"Próximo a vencer","En plazo"))))) -> Atrasado
A17: PA-13 | B17: C5 | C17: C5-01 | D17: Coordinador(a) General de la UGP | E17: Consultor individual | F17: 3CV | G17: Ex ante | H17: 50400 | I17: Contratado | J17: 46357 | K17: 46357 | L17: 46391 | M17: 46391 | N17: =IF(M17<>"",M17-L17,IF(L17<>"",MAX(0,Fecha_Corte-L17),"")) -> 0 | O17: =SUMIFS(F5_Contratos!$G$5:$G$200,F5_Contratos!$B$5:$B$200,A17) -> 50400 | P17: =IF(OR(I17="Contratado",I17="Cerrado"),IF(N17>0,"Contratado con atraso","Contratado a tiempo"),IF(AND(K17="",J17<>"",Fecha_Corte>J17),"Atrasado",IF(L17="","Sin fecha prevista",IF(Fecha_Corte>L17,"Atrasado",IF(L17-Fecha_Corte<=Dias_Alerta,"Próximo a vencer","En plazo"))))) -> Contratado a tiempo
A18: PA-14 | B18: C5 | C18: C5-01 | D18: Especialista Financiero | E18: Consultor individual | F18: 3CV | G18: Ex ante | H18: 48000 | I18: Contratado | J18: 46357 | K18: 46357 | L18: 46391 | M18: 46398 | N18: =IF(M18<>"",M18-L18,IF(L18<>"",MAX(0,Fecha_Corte-L18),"")) -> 7 | O18: =SUMIFS(F5_Contratos!$G$5:$G$200,F5_Contratos!$B$5:$B$200,A18) -> 48000 | P18: =IF(OR(I18="Contratado",I18="Cerrado"),IF(N18>0,"Contratado con atraso","Contratado a tiempo"),IF(AND(K18="",J18<>"",Fecha_Corte>J18),"Atrasado",IF(L18="","Sin fecha prevista",IF(Fecha_Corte>L18,"Atrasado",IF(L18-Fecha_Corte<=Dias_Alerta,"Próximo a vencer","En plazo"))))) -> Contratado con atraso
A19: PA-15 | B19: C5 | C19: C5-01 | D19: Especialista en Adquisiciones | E19: Consultor individual | F19: 3CV | G19: Ex ante | H19: 48000 | I19: Contratado | J19: 46357 | K19: 46357 | L19: 46391 | M19: 46398 | N19: =IF(M19<>"",M19-L19,IF(L19<>"",MAX(0,Fecha_Corte-L19),"")) -> 7 | O19: =SUMIFS(F5_Contratos!$G$5:$G$200,F5_Contratos!$B$5:$B$200,A19) -> 48000 | P19: =IF(OR(I19="Contratado",I19="Cerrado"),IF(N19>0,"Contratado con atraso","Contratado a tiempo"),IF(AND(K19="",J19<>"",Fecha_Corte>J19),"Atrasado",IF(L19="","Sin fecha prevista",IF(Fecha_Corte>L19,"Atrasado",IF(L19-Fecha_Corte<=Dias_Alerta,"Próximo a vencer","En plazo"))))) -> Contratado con atraso
A20: PA-16 | B20: C5 | C20: C5-01 | D20: Esp. en Planificación, Monitoreo y Seguimiento | E20: Consultor individual | F20: 3CV | G20: Ex ante | H20: 48000 | I20: Contratado | J20: 46357 | K20: 46357 | L20: 46391 | M20: 46405 | N20: =IF(M20<>"",M20-L20,IF(L20<>"",MAX(0,Fecha_Corte-L20),"")) -> 14 | O20: =SUMIFS(F5_Contratos!$G$5:$G$200,F5_Contratos!$B$5:$B$200,A20) -> 48000 | P20: =IF(OR(I20="Contratado",I20="Cerrado"),IF(N20>0,"Contratado con atraso","Contratado a tiempo"),IF(AND(K20="",J20<>"",Fecha_Corte>J20),"Atrasado",IF(L20="","Sin fecha prevista",IF(Fecha_Corte>L20,"Atrasado",IF(L20-Fecha_Corte<=Dias_Alerta,"Próximo a vencer","En plazo"))))) -> Contratado con atraso
A21: PA-17 | B21: C5 | C21: C5-01 | D21: Especialista Social | E21: Consultor individual | F21: 3CV | G21: Ex ante | H21: 48000 | I21: Contratado | J21: 46357 | K21: 46357 | L21: 46391 | M21: 46405 | N21: =IF(M21<>"",M21-L21,IF(L21<>"",MAX(0,Fecha_Corte-L21),"")) -> 14 | O21: =SUMIFS(F5_Contratos!$G$5:$G$200,F5_Contratos!$B$5:$B$200,A21) -> 48000 | P21: =IF(OR(I21="Contratado",I21="Cerrado"),IF(N21>0,"Contratado con atraso","Contratado a tiempo"),IF(AND(K21="",J21<>"",Fecha_Corte>J21),"Atrasado",IF(L21="","Sin fecha prevista",IF(Fecha_Corte>L21,"Atrasado",IF(L21-Fecha_Corte<=Dias_Alerta,"Próximo a vencer","En plazo"))))) -> Contratado con atraso
A22: PA-18 | B22: C5 | C22: C5-03 | D22: Firma auditora de estados financieros 2027 | E22: Consultoría (firma) | F22: SBCC | G22: Ex ante | H22: 85000 | I22: Publicado | J22: 46522 | K22: 46548 | L22: 46645 | N22: =IF(M22<>"",M22-L22,IF(L22<>"",MAX(0,Fecha_Corte-L22),"")) -> 0 | O22: =SUMIFS(F5_Contratos!$G$5:$G$200,F5_Contratos!$B$5:$B$200,A22) -> 0 | P22: =IF(OR(I22="Contratado",I22="Cerrado"),IF(N22>0,"Contratado con atraso","Contratado a tiempo"),IF(AND(K22="",J22<>"",Fecha_Corte>J22),"Atrasado",IF(L22="","Sin fecha prevista",IF(Fecha_Corte>L22,"Atrasado",IF(L22-Fecha_Corte<=Dias_Alerta,"Próximo a vencer","En plazo"))))) -> En plazo
A23: PA-19 | B23: C5 | C23: C5-02 | D23: Consultoría: línea base y plan de M&E | E23: Consultoría (firma) | F23: SBCC | G23: Ex ante | H23: 150000 | I23: Contratado | J23: 46412 | K23: 46414 | L23: 46461 | M23: 46468 | N23: =IF(M23<>"",M23-L23,IF(L23<>"",MAX(0,Fecha_Corte-L23),"")) -> 7 | O23: =SUMIFS(F5_Contratos!$G$5:$G$200,F5_Contratos!$B$5:$B$200,A23) -> 146000 | P23: =IF(OR(I23="Contratado",I23="Cerrado"),IF(N23>0,"Contratado con atraso","Contratado a tiempo"),IF(AND(K23="",J23<>"",Fecha_Corte>J23),"Atrasado",IF(L23="","Sin fecha prevista",IF(Fecha_Corte>L23,"Atrasado",IF(L23-Fecha_Corte<=Dias_Alerta,"Próximo a vencer","En plazo"))))) -> Contratado con atraso
A24: PA-20 | B24: C5 | C24: C5-04 | D24: Consultoría individual: gestión ambiental y social | E24: Consultor individual | F24: 3CV | G24: Ex ante | H24: 36000 | I24: Contratado | J24: 46412 | K24: 46412 | L24: 46446 | M24: 46447 | N24: =IF(M24<>"",M24-L24,IF(L24<>"",MAX(0,Fecha_Corte-L24),"")) -> 1 | O24: =SUMIFS(F5_Contratos!$G$5:$G$200,F5_Contratos!$B$5:$B$200,A24) -> 36000 | P24: =IF(OR(I24="Contratado",I24="Cerrado"),IF(N24>0,"Contratado con atraso","Contratado a tiempo"),IF(AND(K24="",J24<>"",Fecha_Corte>J24),"Atrasado",IF(L24="","Sin fecha prevista",IF(Fecha_Corte>L24,"Atrasado",IF(L24-Fecha_Corte<=Dias_Alerta,"Próximo a vencer","En plazo"))))) -> Contratado con atraso

Sheet F5_Contratos
A1: F5 · Registro y seguimiento de contratos
A2: DATOS SIMULADOS con fines de demostración metodológica — no son cifras reales del BID ni de la Dirección de Integración.
A3: Pagado = suma del libro de gastos por contrato. El saldo y el chequeo detectan pagos que excedan el monto contratado.
A4: ID contrato | B4: ID PA | C4: Actividad POA | D4: Comp. | E4: Proveedor / consultor | F4: Objeto | G4: Monto contrato | H4: Fecha firma | I4: Fin de vigencia | J4: Mecanismo de pago | K4: Pagado (USD) | L4: Saldo (USD) | M4: % pagado | N4: Vigencia | O4: Responsable de supervisión | P4: Chequeo pago ≤ contrato
A5: CT-01 | B5: PA-01 | C5: C1-01 | D5: =INDEX(P1_POA!$B$5:$B$200,MATCH(C5,P1_POA!$A$5:$A$200,0)) -> C1 | E5: Consultora Alfa (ficticia) | F5: Diseño del modelo de captación | G5: 118000 | H5: 46458 | I5: 46568 | J5: Anticipo de fondos | K5: =SUMIFS(F2_Ejecucion!$J$5:$J$500,F2_Ejecucion!$E$5:$E$500,A5) -> 118000 | L5: =G5-K5 -> 0 | M5: =K5/G5 -> 1 | N5: =IF(I5<Fecha_Corte,"Vencido",IF(I5-Fecha_Corte<=Dias_Alerta,"Por vencer","Vigente")) -> Por vencer | O5: =INDEX(P1_POA!$D$5:$D$200,MATCH(C5,P1_POA!$A$5:$A$200,0)) -> Esp. Social | P5: =IF(K5>G5,1,0) -> 0
A6: CT-02 | B6: PA-02 | C6: C1-04 | D6: =INDEX(P1_POA!$B$5:$B$200,MATCH(C6,P1_POA!$A$5:$A$200,0)) -> C1 | E6: Tecnologías Beta (ficticia) | F6: Plataforma de registro | G6: 248500 | H6: 46512 | I6: 46752 | J6: Pago directo | K6: =SUMIFS(F2_Ejecucion!$J$5:$J$500,F2_Ejecucion!$E$5:$E$500,A6) -> 149100 | L6: =G6-K6 -> 99400 | M6: =K6/G6 -> 0.6 | N6: =IF(I6<Fecha_Corte,"Vencido",IF(I6-Fecha_Corte<=Dias_Alerta,"Por vencer","Vigente")) -> Vigente | O6: =INDEX(P1_POA!$D$5:$D$200,MATCH(C6,P1_POA!$A$5:$A$200,0)) -> Esp. Planificación, M&S | P6: =IF(K6>G6,1,0) -> 0
A7: CT-03 | B7: PA-03 | C7: C1-03 | D7: =INDEX(P1_POA!$B$5:$B$200,MATCH(C7,P1_POA!$A$5:$A$200,0)) -> C1 | E7: Comunicaciones Gamma (ficticia) | F7: Campaña nacional de difusión | G7: 285000 | H7: 46505 | I7: 46660 | J7: Pago directo | K7: =SUMIFS(F2_Ejecucion!$J$5:$J$500,F2_Ejecucion!$E$5:$E$500,A7) -> 142500 | L7: =G7-K7 -> 142500 | M7: =K7/G7 -> 0.5 | N7: =IF(I7<Fecha_Corte,"Vencido",IF(I7-Fecha_Corte<=Dias_Alerta,"Por vencer","Vigente")) -> Vigente | O7: =INDEX(P1_POA!$D$5:$D$200,MATCH(C7,P1_POA!$A$5:$A$200,0)) -> Esp. Planificación, M&S | P7: =IF(K7>G7,1,0) -> 0
A8: CT-04 | B8: PA-04 | C8: C2-01 | D8: =INDEX(P1_POA!$B$5:$B$200,MATCH(C8,P1_POA!$A$5:$A$200,0)) -> C2 | E8: Consultor individual 1 (ficticio) | F8: Esquema de apoyos | G8: 58800 | H8: 46434 | I8: 46538 | J8: Anticipo de fondos | K8: =SUMIFS(F2_Ejecucion!$J$5:$J$500,F2_Ejecucion!$E$5:$E$500,A8) -> 58800 | L8: =G8-K8 -> 0 | M8: =K8/G8 -> 1 | N8: =IF(I8<Fecha_Corte,"Vencido",IF(I8-Fecha_Corte<=Dias_Alerta,"Por vencer","Vigente")) -> Vencido | O8: =INDEX(P1_POA!$D$5:$D$200,MATCH(C8,P1_POA!$A$5:$A$200,0)) -> Esp. Social | P8: =IF(K8>G8,1,0) -> 0
A9: CT-05 | B9: PA-05 | C9: C2-04 | D9: =INDEX(P1_POA!$B$5:$B$200,MATCH(C9,P1_POA!$A$5:$A$200,0)) -> C2 | E9: Fundación Delta (ficticia) | F9: Tutorías y acompañamiento | G9: 395000 | H9: 46535 | I9: 46736 | J9: Anticipo de fondos | K9: =SUMIFS(F2_Ejecucion!$J$5:$J$500,F2_Ejecucion!$E$5:$E$500,A9) -> 118500 | L9: =G9-K9 -> 276500 | M9: =K9/G9 -> 0.3 | N9: =IF(I9<Fecha_Corte,"Vencido",IF(I9-Fecha_Corte<=Dias_Alerta,"Por vencer","Vigente")) -> Vigente | O9: =INDEX(P1_POA!$D$5:$D$200,MATCH(C9,P1_POA!$A$5:$A$200,0)) -> Esp. Social | P9: =IF(K9>G9,1,0) -> 0
A10: CT-06 | B10: PA-07 | C10: C3-01 | D10: =INDEX(P1_POA!$B$5:$B$200,MATCH(C10,P1_POA!$A$5:$A$200,0)) -> C3 | E10: Estudios Épsilon (ficticia) | F10: Diagnóstico de demanda laboral | G10: 185000 | H10: 46482 | I10: 46553 | J10: Anticipo de fondos | K10: =SUMIFS(F2_Ejecucion!$J$5:$J$500,F2_Ejecucion!$E$5:$E$500,A10) -> 185000 | L10: =G10-K10 -> 0 | M10: =K10/G10 -> 1 | N10: =IF(I10<Fecha_Corte,"Vencido",IF(I10-Fecha_Corte<=Dias_Alerta,"Por vencer","Vigente")) -> Vencido | O10: =INDEX(P1_POA!$D$5:$D$200,MATCH(C10,P1_POA!$A$5:$A$200,0)) -> Esp. Planificación, M&S | P10: =IF(K10>G10,1,0) -> 0
A11: CT-07 | B11: PA-08 | C11: C3-02 | D11: =INDEX(P1_POA!$B$5:$B$200,MATCH(C11,P1_POA!$A$5:$A$200,0)) -> C3 | E11: Consultor individual 2 (ficticio) | F11: Alianzas con empleadores | G11: 68000 | H11: 46517 | I11: 46691 | J11: Anticipo de fondos | K11: =SUMIFS(F2_Ejecucion!$J$5:$J$500,F2_Ejecucion!$E$5:$E$500,A11) -> 27200 | L11: =G11-K11 -> 40800 | M11: =K11/G11 -> 0.4 | N11: =IF(I11<Fecha_Corte,"Vencido",IF(I11-Fecha_Corte<=Dias_Alerta,"Por vencer","Vigente")) -> Vigente | O11: =INDEX(P1_POA!$D$5:$D$200,MATCH(C11,P1_POA!$A$5:$A$200,0)) -> Esp. Social | P11: =IF(K11>G11,1,0) -> 0
A12: CT-08 | B12: PA-09 | C12: C4-01 | D12: =INDEX(P1_POA!$B$5:$B$200,MATCH(C12,P1_POA!$A$5:$A$200,0)) -> C4 | E12: Consultora Zeta (ficticia) | F12: Diagnóstico institucional | G12: 332000 | H12: 46462 | I12: 46538 | J12: Anticipo de fondos | K12: =SUMIFS(F2_Ejecucion!$J$5:$J$500,F2_Ejecucion!$E$5:$E$500,A12) -> 332000 | L12: =G12-K12 -> 0 | M12: =K12/G12 -> 1 | N12: =IF(I12<Fecha_Corte,"Vencido",IF(I12-Fecha_Corte<=Dias_Alerta,"Por vencer","Vigente")) -> Vencido | O12: =INDEX(P1_POA!$D$5:$D$200,MATCH(C12,P1_POA!$A$5:$A$200,0)) -> Esp. Planificación, M&S | P12: =IF(K12>G12,1,0) -> 0
A13: CT-09 | B13: PA-10 | C13: C4-02 | D13: =INDEX(P1_POA!$B$5:$B$200,MATCH(C13,P1_POA!$A$5:$A$200,0)) -> C4 | E13: Sistemas Eta (ficticia) | F13: Sistema de información de trayectorias | G13: 871000 | H13: 46539 | I13: 46721 | J13: Pago directo | K13: =SUMIFS(F2_Ejecucion!$J$5:$J$500,F2_Ejecucion!$E$5:$E$500,A13) -> 304850 | L13: =G13-K13 -> 566150 | M13: =K13/G13 -> 0.35 | N13: =IF(I13<Fecha_Corte,"Vencido",IF(I13-Fecha_Corte<=Dias_Alerta,"Por vencer","Vigente")) -> Vigente | O13: =INDEX(P1_POA!$D$5:$D$200,MATCH(C13,P1_POA!$A$5:$A$200,0)) -> Esp. Planificación, M&S | P13: =IF(K13>G13,1,0) -> 0
A14: CT-10 | B14: PA-13 | C14: C5-01 | D14: =INDEX(P1_POA!$B$5:$B$200,MATCH(C14,P1_POA!$A$5:$A$200,0)) -> C5 | E14: Coordinador(a) General UGP | F14: Consultoría individual (TDR: US$50,400) | G14: 50400 | H14: 46391 | I14: 46752 | J14: Anticipo de fondos | K14: =SUMIFS(F2_Ejecucion!$J$5:$J$500,F2_Ejecucion!$E$5:$E$500,A14) -> 25200 | L14: =G14-K14 -> 25200 | M14: =K14/G14 -> 0.5 | N14: =IF(I14<Fecha_Corte,"Vencido",IF(I14-Fecha_Corte<=Dias_Alerta,"Por vencer","Vigente")) -> Vigente | O14: =INDEX(P1_POA!$D$5:$D$200,MATCH(C14,P1_POA!$A$5:$A$200,0)) -> Coordinador General | P14: =IF(K14>G14,1,0) -> 0
A15: CT-11 | B15: PA-14 | C15: C5-01 | D15: =INDEX(P1_POA!$B$5:$B$200,MATCH(C15,P1_POA!$A$5:$A$200,0)) -> C5 | E15: Especialista Financiero | F15: Consultoría individual | G15: 48000 | H15: 46398 | I15: 46752 | J15: Anticipo de fondos | K15: =SUMIFS(F2_Ejecucion!$J$5:$J$500,F2_Ejecucion!$E$5:$E$500,A15) -> 24000 | L15: =G15-K15 -> 24000 | M15: =K15/G15 -> 0.5 | N15: =IF(I15<Fecha_Corte,"Vencido",IF(I15-Fecha_Corte<=Dias_Alerta,"Por vencer","Vigente")) -> Vigente | O15: =INDEX(P1_POA!$D$5:$D$200,MATCH(C15,P1_POA!$A$5:$A$200,0)) -> Coordinador General | P15: =IF(K15>G15,1,0) -> 0
A16: CT-12 | B16: PA-15 | C16: C5-01 | D16: =INDEX(P1_POA!$B$5:$B$200,MATCH(C16,P1_POA!$A$5:$A$200,0)) -> C5 | E16: Especialista en Adquisiciones | F16: Consultoría individual | G16: 48000 | H16: 46398 | I16: 46752 | J16: Anticipo de fondos | K16: =SUMIFS(F2_Ejecucion!$J$5:$J$500,F2_Ejecucion!$E$5:$E$500,A16) -> 24000 | L16: =G16-K16 -> 24000 | M16: =K16/G16 -> 0.5 | N16: =IF(I16<Fecha_Corte,"Vencido",IF(I16-Fecha_Corte<=Dias_Alerta,"Por vencer","Vigente")) -> Vigente | O16: =INDEX(P1_POA!$D$5:$D$200,MATCH(C16,P1_POA!$A$5:$A$200,0)) -> Coordinador General | P16: =IF(K16>G16,1,0) -> 0
... A20: CT-16 | B20: PA-20 | C20: C5-04 | D20: =INDEX(P1_POA!$B$5:$B$200,MATCH(C20,P1_POA!$A$5:$A$200,0)) -> C5 | E20: Consultor individual 3 (ficticio) | F20: Gestión ambiental y social | G20: 36000 | H20: 46447 | I20: 46736 | J20: Anticipo de fondos | K20: =SUMIFS(F2_Ejecucion!$J$5:$J$500,F2_Ejecucion!$E$5:$E$500,A20) -> 18000 | L20: =G20-K20 -> 18000 | M20: =K20/G20 -> 0.5 | N20: =IF(I20<Fecha_Corte,"Vencido",IF(I20-Fecha_Corte<=Dias_Alerta,"Por vencer","Vigente")) -> Vigente | O20: =INDEX(P1_POA!$D$5:$D$200,MATCH(C20,P1_POA!$A$5:$A$200,0)) -> Esp. Social | P20: =IF(K20>G20,1,0) -> 0

Sheet F6_Auditoria
A1: F6 · Plan de auditorías y seguimiento de recomendaciones
A2: DATOS SIMULADOS con fines de demostración metodológica — no son cifras reales del BID ni de la Dirección de Integración.
A3: Tabla 1 (fila 4): plan de auditoría y revisiones. Tabla 2 (fila 12): recomendaciones y hallazgos.
A4: ID | B4: Tipo de auditoría / revisión | C4: Período | D4: Responsable externo/interno | E4: Cierre del período | F4: Fecha límite de entrega | G4: Estado | H4: Días al vencimiento | I4: Alerta | J4: Recomendaciones | K4: Cerradas | L4: % cierre
A5: AU-01 | B5: Estados financieros auditados del Programa | C5: Ejercicio 2027 | D5: Firma auditora externa (por contratar, PA-18) | E5: 46752 | F5: =E5+Plazo_EEFF -> 46872 | G5: Planificada | H5: =IF(G5="Cerrada","",F5-Fecha_Corte) -> 304 | I5: =IF(G5="Cerrada","Cerrada",IF(F5<Fecha_Corte,"Vencida",IF(F5-Fecha_Corte<=Dias_Alerta,"Próxima","En plazo"))) -> En plazo | J5: =COUNTIFS($B$14:$B$100,A5) -> 0 | K5: =COUNTIFS($B$14:$B$100,A5,$H$14:$H$100,"Cerrada") -> 0 | L5: =IF(J5=0,"",K5/J5)
A6: AU-02 | B6: Revisión ex post de adquisiciones (expedientes) | C6: Ejercicio 2027 | D6: Revisión BID con expedientes preparados por la UGP | E6: 46721 | F6: 46736 | G6: Planificada | H6: =IF(G6="Cerrada","",F6-Fecha_Corte) -> 168 | I6: =IF(G6="Cerrada","Cerrada",IF(F6<Fecha_Corte,"Vencida",IF(F6-Fecha_Corte<=Dias_Alerta,"Próxima","En plazo"))) -> En plazo | J6: =COUNTIFS($B$14:$B$100,A6) -> 0 | K6: =COUNTIFS($B$14:$B$100,A6,$H$14:$H$100,"Cerrada") -> 0 | L6: =IF(J6=0,"",K6/J6)
A7: AU-03 | B7: Auditoría interna: transferencias a beneficiarios (muestra) | C7: Semestre 1-2027 | D7: Unidad de Auditoría Interna de la DI (supuesto) | E7: 46568 | F7: 46599 | G7: En ejecución | H7: =IF(G7="Cerrada","",F7-Fecha_Corte) -> 31 | I7: =IF(G7="Cerrada","Cerrada",IF(F7<Fecha_Corte,"Vencida",IF(F7-Fecha_Corte<=Dias_Alerta,"Próxima","En plazo"))) -> En plazo | J7: =COUNTIFS($B$14:$B$100,A7) -> 1 | K7: =COUNTIFS($B$14:$B$100,A7,$H$14:$H$100,"Cerrada") -> 0 | L7: =IF(J7=0,"",K7/J7) -> 0
A8: AU-04 | B8: Evaluación inicial de control interno de la UGP | C8: Arranque 2027 | D8: Unidad de Auditoría Interna de la DI (supuesto) | E8: 46477 | F8: 46507 | G8: Informe emitido | H8: =IF(G8="Cerrada","",F8-Fecha_Corte) -> -61 | I8: =IF(G8="Cerrada","Cerrada",IF(F8<Fecha_Corte,"Vencida",IF(F8-Fecha_Corte<=Dias_Alerta,"Próxima","En plazo"))) -> Vencida | J8: =COUNTIFS($B$14:$B$100,A8) -> 4 | K8: =COUNTIFS($B$14:$B$100,A8,$H$14:$H$100,"Cerrada") -> 3 | L8: =IF(J8=0,"",K8/J8) -> 0.75
A12: Recomendaciones y hallazgos
A13: ID rec. | B13: ID auditoría | C13: Recomendación / hallazgo | D13: Riesgo | E13: Responsable | F13: Fecha compromiso | G13: Fecha de cierre | H13: Estado | I13: Días vencida
A14: RA-01 | B14: AU-04 | C14: Formalizar el manual de funciones de los especialistas de la UGP | D14: Medio | E14: Coordinador General | F14: 46522 | G14: 46517 | H14: Cerrada | I14: =IF(H14="Cerrada",0,MAX(0,Fecha_Corte-F14)) -> 0
A15: RA-02 | B15: AU-04 | C15: Implementar lista de verificación de expediente por contrato | D15: Medio | E15: Esp. Adquisiciones | F15: 46538 | G15: 46535 | H15: Cerrada | I15: =IF(H15="Cerrada",0,MAX(0,Fecha_Corte-F15)) -> 0
A16: RA-03 | B16: AU-04 | C16: Segregar el registro y la aprobación de pagos | D16: Alto | E16: Esp. Financiero | F16: 46522 | G16: 46521 | H16: Cerrada | I16: =IF(H16="Cerrada",0,MAX(0,Fecha_Corte-F16)) -> 0
A17: RA-04 | B17: AU-04 | C17: Documentar la conciliación bancaria mensual de la cuenta del Programa | D17: Medio | E17: Esp. Financiero | F17: 46553 | H17: En proceso | I17: =IF(H17="Cerrada",0,MAX(0,Fecha_Corte-F17)) -> 15
A18: RA-05 | B18: AU-03 | C18: Completar expedientes de beneficiarios con la documentación de elegibilidad (preliminar) | D18: Alto | E18: Esp. Social | F18: 46583 | H18: Abierta | I18: =IF(H18="Cerrada",0,MAX(0,Fecha_Corte-F18)) -> 0

Sheet N1_Cumplimiento
A1: N1 · Matriz de cumplimiento normativo y contractual
A2: DATOS SIMULADOS con fines de demostración metodológica — no son cifras reales del BID ni de la Dirección de Integración.
A3: Obligaciones TÍPICAS de una operación BID. La columna «Cláusula» queda por completar al contrastar con el Contrato de Préstamo 6153/OC-ES, el Convenio 6154/GR-ES y el MOP, que no se tuvieron a la vista.
A4: ID | B4: Instrumento | C4: Obligación | D4: Cláusula / sección | E4: Frecuencia | F4: Fecha límite | G4: Estado | H4: Responsable | I4: Evidencia (expediente) | J4: Días al vencimiento | K4: Alerta | L4: Exigible a la fecha | N4: Resumen de cumplimiento | O4: Valor
A5: N-01 | B5: Contrato de Préstamo 6153/OC-ES | C5: Condiciones previas al primer desembolso cumplidas y certificadas | D5: Por verificar | E5: Única | F5: 46423 | G5: Cumplida | H5: Coordinador General | I5: EV-01 | J5: =IF(OR(G5="Cumplida",F5=""),"",F5-Fecha_Corte) | K5: =IF(G5="Cumplida","Cumplida",IF(F5="","Por evento",IF(F5<Fecha_Corte,"Vencida",IF(F5-Fecha_Corte<=Dias_Alerta,"Próxima a vencer","En plazo")))) -> Cumplida | L5: =IF(AND(F5<>"",F5<=Fecha_Corte),1,0) -> 1 | N5: Obligaciones registradas | O5: =COUNTIF($A$5:$A$200,"N-*") -> 19
A6: N-02 | B6: MOP | C6: Manual Operativo del Programa (MOP) aprobado y vigente | D6: Por verificar | E6: Única | F6: 46418 | G6: Cumplida | H6: Coordinador General | I6: EV-02 | J6: =IF(OR(G6="Cumplida",F6=""),"",F6-Fecha_Corte) | K6: =IF(G6="Cumplida","Cumplida",IF(F6="","Por evento",IF(F6<Fecha_Corte,"Vencida",IF(F6-Fecha_Corte<=Dias_Alerta,"Próxima a vencer","En plazo")))) -> Cumplida | L6: =IF(AND(F6<>"",F6<=Fecha_Corte),1,0) -> 1 | N6: Exigibles a la fecha de corte | O6: =COUNTIFS($F$5:$F$200,"<="&Fecha_Corte) -> 9
A7: N-03 | B7: Contrato de Préstamo 6153/OC-ES | C7: Cuenta bancaria específica para los recursos del Programa | D7: Por verificar | E7: Única | F7: 46423 | G7: Cumplida | H7: Esp. Financiero | I7: EV-03 | J7: =IF(OR(G7="Cumplida",F7=""),"",F7-Fecha_Corte) | K7: =IF(G7="Cumplida","Cumplida",IF(F7="","Por evento",IF(F7<Fecha_Corte,"Vencida",IF(F7-Fecha_Corte<=Dias_Alerta,"Próxima a vencer","En plazo")))) -> Cumplida | L7: =IF(AND(F7<>"",F7<=Fecha_Corte),1,0) -> 1 | N7: Cumplidas (de las exigibles) | O7: =COUNTIFS($G$5:$G$200,"Cumplida",$F$5:$F$200,"<="&Fecha_Corte) -> 8
A8: N-04 | B8: MOP | C8: Plan de Ejecución Plurianual (PEP) y POA del año aprobados | D8: Por verificar | E8: Anual | F8: 46418 | G8: Cumplida | H8: Esp. Planificación, M&S | I8: EV-04 | J8: =IF(OR(G8="Cumplida",F8=""),"",F8-Fecha_Corte) | K8: =IF(G8="Cumplida","Cumplida",IF(F8="","Por evento",IF(F8<Fecha_Corte,"Vencida",IF(F8-Fecha_Corte<=Dias_Alerta,"Próxima a vencer","En plazo")))) -> Cumplida | L8: =IF(AND(F8<>"",F8<=Fecha_Corte),1,0) -> 1 | N8: Vencidas | O8: =COUNTIF($K$5:$K$200,"Vencida") -> 1
A9: N-05 | B9: Políticas BID | C9: Plan de Adquisiciones inicial registrado con No Objeción | D9: Por verificar | E9: Única | F9: 46418 | G9: Cumplida | H9: Esp. Adquisiciones | I9: EV-05 | J9: =IF(OR(G9="Cumplida",F9=""),"",F9-Fecha_Corte) | K9: =IF(G9="Cumplida","Cumplida",IF(F9="","Por evento",IF(F9<Fecha_Corte,"Vencida",IF(F9-Fecha_Corte<=Dias_Alerta,"Próxima a vencer","En plazo")))) -> Cumplida | L9: =IF(AND(F9<>"",F9<=Fecha_Corte),1,0) -> 1 | N9: Próximas a vencer | O9: =COUNTIF($K$5:$K$200,"Próxima a vencer") -> 3
A10: N-06 | B10: Políticas BID | C10: Plan de Adquisiciones actualizado | D10: Por verificar | E10: Trimestral | F10: 46583 | G10: En proceso | H10: Esp. Adquisiciones | I10: EV-06 | J10: =IF(OR(G10="Cumplida",F10=""),"",F10-Fecha_Corte) -> 15 | K10: =IF(G10="Cumplida","Cumplida",IF(F10="","Por evento",IF(F10<Fecha_Corte,"Vencida",IF(F10-Fecha_Corte<=Dias_Alerta,"Próxima a vencer","En plazo")))) -> Próxima a vencer | L10: =IF(AND(F10<>"",F10<=Fecha_Corte),1,0) -> 0 | N10: % cumplimiento de exigibles | O10: =IF(O6=0,0,O7/O6) -> 0.88888889
A11: N-07 | B11: Contrato de Préstamo 6153/OC-ES | C11: Informe de progreso semestral al BID | D11: Por verificar | E11: Semestral | F11: 46599 | G11: En proceso | H11: Esp. Planificación, M&S | I11: EV-07 | J11: =IF(OR(G11="Cumplida",F11=""),"",F11-Fecha_Corte) -> 31 | K11: =IF(G11="Cumplida","Cumplida",IF(F11="","Por evento",IF(F11<Fecha_Corte,"Vencida",IF(F11-Fecha_Corte<=Dias_Alerta,"Próxima a vencer","En plazo")))) -> En plazo | L11: =IF(AND(F11<>"",F11<=Fecha_Corte),1,0) -> 0
A12: N-08 | B12: Contrato de Préstamo 6153/OC-ES | C12: Estados financieros auditados del ejercicio 2027 | D12: Por verificar | E12: Anual | F12: =F6_Auditoria!F5 -> 46872 | G12: Pendiente | H12: Esp. Financiero | I12: EV-08 | J12: =IF(OR(G12="Cumplida",F12=""),"",F12-Fecha_Corte) -> 304 | K12: =IF(G12="Cumplida","Cumplida",IF(F12="","Por evento",IF(F12<Fecha_Corte,"Vencida",IF(F12-Fecha_Corte<=Dias_Alerta,"Próxima a vencer","En plazo")))) -> En plazo | L12: =IF(AND(F12<>"",F12<=Fecha_Corte),1,0) -> 0
A13: N-09 | B13: Contrato de Préstamo 6153/OC-ES | C13: Justificación de anticipos hasta el umbral para solicitar uno nuevo | D13: Por verificar | E13: Continua | F13: 46583 | G13: En proceso | H13: Esp. Financiero | I13: EV-09 | J13: =IF(OR(G13="Cumplida",F13=""),"",F13-Fecha_Corte) -> 15 | K13: =IF(G13="Cumplida","Cumplida",IF(F13="","Por evento",IF(F13<Fecha_Corte,"Vencida",IF(F13-Fecha_Corte<=Dias_Alerta,"Próxima a vencer","En plazo")))) -> Próxima a vencer | L13: =IF(AND(F13<>"",F13<=Fecha_Corte),1,0) -> 0
A14: N-10 | B14: Políticas BID | C14: Revisión ex post de adquisiciones (expedientes completos) | D14: Por verificar | E14: Anual | F14: 46736 | G14: Pendiente | H14: Esp. Adquisiciones | I14: EV-10 | J14: =IF(OR(G14="Cumplida",F14=""),"",F14-Fecha_Corte) -> 168 | K14: =IF(G14="Cumplida","Cumplida",IF(F14="","Por evento",IF(F14<Fecha_Corte,"Vencida",IF(F14-Fecha_Corte<=Dias_Alerta,"Próxima a vencer","En plazo")))) -> En plazo | L14: =IF(AND(F14<>"",F14<=Fecha_Corte),1,0) -> 0
A15: N-11 | B15: Políticas BID | C15: Informe ambiental y social semestral | D15: Por verificar | E15: Semestral | F15: 46599 | G15: En proceso | H15: Esp. Social | I15: EV-11 | J15: =IF(OR(G15="Cumplida",F15=""),"",F15-Fecha_Corte) -> 31 | K15: =IF(G15="Cumplida","Cumplida",IF(F15="","Por evento",IF(F15<Fecha_Corte,"Vencida",IF(F15-Fecha_Corte<=Dias_Alerta,"Próxima a vencer","En plazo")))) -> En plazo | L15: =IF(AND(F15<>"",F15<=Fecha_Corte),1,0) -> 0
A16: N-12 | B16: Políticas BID | C16: Mecanismo de quejas y reclamos operativo | D16: Por verificar | E16: Única | F16: 46477 | G16: Cumplida | H16: Esp. Social | I16: EV-12 | J16: =IF(OR(G16="Cumplida",F16=""),"",F16-Fecha_Corte) | K16: =IF(G16="Cumplida","Cumplida",IF(F16="","Por evento",IF(F16<Fecha_Corte,"Vencida",IF(F16-Fecha_Corte<=Dias_Alerta,"Próxima a vencer","En plazo")))) -> Cumplida | L16: =IF(AND(F16<>"",F16<=Fecha_Corte),1,0) -> 1
A17: N-13 | B17: TDR / UGP | C17: Protocolo de protección de datos de las personas beneficiarias | D17: Por verificar | E17: Única | F17: 46477 | G17: Cumplida | H17: Esp. Social | I17: EV-13 | J17: =IF(OR(G17="Cumplida",F17=""),"",F17-Fecha_Corte) | K17: =IF(G17="Cumplida","Cumplida",IF(F17="","Por evento",IF(F17<Fecha_Corte,"Vencida",IF(F17-Fecha_Corte<=Dias_Alerta,"Próxima a vencer","En plazo")))) -> Cumplida | L17: =IF(AND(F17<>"",F17<=Fecha_Corte),1,0) -> 1
A18: N-14 | B18: MOP | C18: Línea base de indicadores de resultados | D18: Por verificar | E18: Única | F18: 46553 | G18: En proceso | H18: Esp. Planificación, M&S | I18: EV-14 | J18: =IF(OR(G18="Cumplida",F18=""),"",F18-Fecha_Corte) -> -15 | K18: =IF(G18="Cumplida","Cumplida",IF(F18="","Por evento",IF(F18<Fecha_Corte,"Vencida",IF(F18-Fecha_Corte<=Dias_Alerta,"Próxima a vencer","En plazo")))) -> Vencida | L18: =IF(AND(F18<>"",F18<=Fecha_Corte),1,0) -> 1
A19: N-15 | B19: TDR / UGP | C19: Informe mensual de gestión (P2-P11) | D19: Por verificar | E19: Mensual | F19: =WORKDAY(EOMONTH(Fecha_Corte,0),Plazo_Informe) -> 46573 | G19: En proceso | H19: Coordinador General | I19: EV-15 | J19: =IF(OR(G19="Cumplida",F19=""),"",F19-Fecha_Corte) -> 5 | K19: =IF(G19="Cumplida","Cumplida",IF(F19="","Por evento",IF(F19<Fecha_Corte,"Vencida",IF(F19-Fecha_Corte<=Dias_Alerta,"Próxima a vencer","En plazo")))) -> Próxima a vencer | L19: =IF(AND(F19<>"",F19<=Fecha_Corte),1,0) -> 0
A20: N-16 | B20: Políticas BID | C20: Certificación de elegibilidad e integridad GN-2350-15 de consultores contratados | D20: Por verificar | E20: Continua | F20: 46568 | G20: Cumplida | H20: Esp. Adquisiciones | I20: EV-16 | J20: =IF(OR(G20="Cumplida",F20=""),"",F20-Fecha_Corte) | K20: =IF(G20="Cumplida","Cumplida",IF(F20="","Por evento",IF(F20<Fecha_Corte,"Vencida",IF(F20-Fecha_Corte<=Dias_Alerta,"Próxima a vencer","En plazo")))) -> Cumplida | L20: =IF(AND(F20<>"",F20<=Fecha_Corte),1,0) -> 1
A21: N-17 | B21: TDR / UGP | C21: Declaración de conflicto de interés y código de conducta del equipo | D21: Por verificar | E21: Anual | F21: 46736 | G21: Pendiente | H21: Coordinador General | I21: EV-17 | J21: =IF(OR(G21="Cumplida",F21=""),"",F21-Fecha_Corte) -> 168 | K21: =IF(G21="Cumplida","Cumplida",IF(F21="","Por evento",IF(F21<Fecha_Corte,"Vencida",IF(F21-Fecha_Corte<=Dias_Alerta,"Próxima a vencer","En plazo")))) -> En plazo | L21: =IF(AND(F21<>"",F21<=Fecha_Corte),1,0) -> 0
A22: N-18 | B22: MOP | C22: No Objeción previa a cambios del MOP y reasignaciones entre categorías | D22: Por verificar | E22: Por evento | G22: Pendiente | H22: Coordinador General | I22: EV-18 | J22: =IF(OR(G22="Cumplida",F22=""),"",F22-Fecha_Corte) | K22: =IF(G22="Cumplida","Cumplida",IF(F22="","Por evento",IF(F22<Fecha_Corte,"Vencida",IF(F22-Fecha_Corte<=Dias_Alerta,"Próxima a vencer","En plazo")))) -> Por evento | L22: =IF(AND(F22<>"",F22<=Fecha_Corte),1,0) -> 0
A23: N-19 | B23: Contrato de Préstamo 6153/OC-ES | C23: Evaluación de medio término | D23: Por verificar | E23: Única | F23: 47483 | G23: Pendiente | H23: Esp. Planificación, M&S | I23: EV-19 | J23: =IF(OR(G23="Cumplida",F23=""),"",F23-Fecha_Corte) -> 915 | K23: =IF(G23="Cumplida","Cumplida",IF(F23="","Por evento",IF(F23<Fecha_Corte,"Vencida",IF(F23-Fecha_Corte<=Dias_Alerta,"Próxima a vencer","En plazo")))) -> En plazo | L23: =IF(AND(F23<>"",F23<=Fecha_Corte),1,0) -> 0

Sheet A1_Equipo
A1: A1 · Equipo de la UGP
A2: DATOS SIMULADOS con fines de demostración metodológica — no son cifras reales del BID ni de la Dirección de Integración.
A3: Plazas de la UGP según el TDR: Coordinador General, Especialistas Financiero, en Adquisiciones, en Planificación, Monitoreo y Seguimiento, Social, entre otros.
A4: Rol | B4: Plazas | C4: Función clave en el ciclo de control | D4: Estado de contratación | E4: Contrato | F4: Instrumento principal que mantiene | G4: Reporta a
A5: Coordinador General de la UGP | B5: 1 | C5: Conduce la UGP; punto focal con el BID; responsabilidad fiduciaria gerencial; decisiones y escalamiento | D5: Contratado | E5: CT-10 | F5: Tablero, informe mensual (P1-P12), matriz de compromisos | G5: Gerencia de Cooperación Institucional
A6: Especialista Financiero | B6: 1 | C6: Presupuesto, desembolsos, justificación de anticipos, contabilidad y auditorías | D6: Contratado | E6: CT-11 | F6: F1, F2, F3 y F6 | G6: Coordinador General
A7: Especialista en Adquisiciones | B7: 1 | C7: Plan de Adquisiciones, procesos, contratos y No Objeciones | D7: Contratado | E7: CT-12 | F7: F4, F5 y A3 | G7: Coordinador General
A8: Especialista en Planificación, Monitoreo y Seguimiento | B8: 1 | C8: POA/PEP, indicadores, riesgos, informes y línea base | D8: Contratado | E8: CT-13 | F8: P1_POA, P1_Resultados y P1_Riesgos | G8: Coordinador General
A9: Especialista Social | B9: 1 | C9: Focalización, inclusión, salvaguardas ambientales y sociales, quejas y protección de datos | D9: Contratado | E9: CT-14 | F9: P2 y N1 (ambiental y social) | G9: Coordinador General
A10: Apoyo administrativo y de archivo | B10: 1 | C10: Archivo físico y digital del Programa, logística y trámites | D10: Por contratar | F10: Índice de archivo del Programa | G10: Coordinador General

Sheet A1_RACI
A1: A1 · Matriz de responsabilidades (RACI) de los procesos de la UGP
A2: DATOS SIMULADOS con fines de demostración metodológica — no son cifras reales del BID ni de la Dirección de Integración.
A3: R = ejecuta · A = rinde cuentas (una sola por proceso) · C = consultado · I = informado. «A/R» = rinde cuentas y ejecuta.
A4: Proceso | B4: Coord. General | C4: Esp. Financiero | D4: Esp. Adquisic. | E4: Esp. Planif. M&S | F4: Esp. Social | G4: Gerencia Coop. Inst. | H4: Dirección General | I4: BID | J4: Chequeo (una sola A)
A5: Elaborar el PEP y el POA anual | B5: A | C5: C | D5: C | E5: R | F5: C | G5: C | H5: I | I5: C | J5: =IF(COUNTIF(B5:I5,"A*")=1,"OK","REVISAR") -> OK
A6: Actualizar el Plan de Adquisiciones | B6: A | C6: C | D6: R | E6: C | F6: C | G6: I | H6: I | I6: C | J6: =IF(COUNTIF(B6:I6,"A*")=1,"OK","REVISAR") -> OK
A7: Conducir procesos de adquisición y contratación | B7: A | C7: C | D7: R | E7: C | F7: C | G7: C | H7: I | I7: C | J7: =IF(COUNTIF(B7:I7,"A*")=1,"OK","REVISAR") -> OK
A8: Tramitar No Objeciones ante el BID | B8: A | C8: C | D8: R | E8: C | F8: C | G8: I | H8: I | I8: C | J8: =IF(COUNTIF(B8:I8,"A*")=1,"OK","REVISAR") -> OK
A9: Ejecución presupuestaria y registros contables | B9: A | C9: R | D9: C | E9: C | F9: I | G9: C | H9: I | I9: I | J9: =IF(COUNTIF(B9:I9,"A*")=1,"OK","REVISAR") -> OK
A10: Solicitudes de desembolso y justificación de anticipos | B10: A | C10: R | D10: C | E10: C | F10: I | G10: I | H10: I | I10: C | J10: =IF(COUNTIF(B10:I10,"A*")=1,"OK","REVISAR") -> OK
A11: Pagos a proveedores y consultores | B11: A | C11: R | D11: C | E11: I | F11: I | G11: I | H11: I | I11: I | J11: =IF(COUNTIF(B11:I11,"A*")=1,"OK","REVISAR") -> OK
A12: Seguimiento de indicadores y matriz de resultados | B12: A | C12: C | D12: I | E12: R | F12: C | G12: I | H12: I | I12: C | J12: =IF(COUNTIF(B12:I12,"A*")=1,"OK","REVISAR") -> OK
A13: Gestión de riesgos y plan de mitigación | B13: A | C13: C | D13: C | E13: R | F13: C | G13: I | H13: I | I13: I | J13: =IF(COUNTIF(B13:I13,"A*")=1,"OK","REVISAR") -> OK
A14: Cumplimiento ambiental y social, inclusión y protección de datos | B14: A | C14: I | D14: C | E14: C | F14: R | G14: I | H14: I | I14: C | J14: =IF(COUNTIF(B14:I14,"A*")=1,"OK","REVISAR") -> OK
A15: Informe mensual de gestión (P2-P11) | B15: A/R | C15: C | D15: C | E15: R | F15: C | G15: I | H15: I | I15: I | J15: =IF(COUNTIF(B15:I15,"A*")=1,"OK","REVISAR") -> OK
A16: Preparar misiones del BID y dar seguimiento a compromisos | B16: A | C16: C | D16: C | E16: R | F16: C | G16: I | H16: I | I16: C | J16: =IF(COUNTIF(B16:I16,"A*")=1,"OK","REVISAR") -> OK
... A18: Cierre técnico, fiduciario y administrativo | B18: A | C18: R | D18: R | E18: R | F18: R | G18: C | H18: I | I18: C | J18: =IF(COUNTIF(B18:I18,"A*")=1,"OK","REVISAR") -> OK

Sheet A2_Misiones_BID
A1: A2 · Misiones del BID y matriz de compromisos (aide-mémoire)
A2: DATOS SIMULADOS con fines de demostración metodológica — no son cifras reales del BID ni de la Dirección de Integración.
A3: Tabla 1 (fila 4): misiones. Tabla 2 (fila 13): compromisos asumidos. La UGP responde como punto focal ante el BID.
A4: ID | B4: Tipo de misión | C4: Inicio | D4: Fin | E4: Participantes (roles) | F4: Temas | G4: N.º compromisos | H4: Cumplidos | I4: % cumplimiento
A5: M-01 | B5: Misión de arranque | C5: 46433 | D5: 46435 | E5: Equipo de proyecto, especialistas fiduciarios y sectoriales (BID) | F5: Arranque, MOP, plan de adquisiciones, cuenta del Programa | G5: =COUNTIFS($B$14:$B$100,A5) -> 5 | H5: =COUNTIFS($B$14:$B$100,A5,$G$14:$G$100,"Cumplido") -> 5 | I5: =IF(G5=0,"",H5/G5) -> 1
A6: M-02 | B6: Misión de seguimiento | C6: 46524 | D6: 46528 | E6: Equipo de proyecto y especialistas fiduciarios (BID) | F6: Avance del POA, adquisiciones, anticipos y riesgos | G6: =COUNTIFS($B$14:$B$100,A6) -> 5 | H6: =COUNTIFS($B$14:$B$100,A6,$G$14:$G$100,"Cumplido") -> 1 | I6: =IF(G6=0,"",H6/G6) -> 0.2
A12: Compromisos de misión
A13: ID | B13: Misión | C13: Compromiso | D13: Responsable | E13: Fecha límite | F13: Fecha de cumplimiento | G13: Estado | H13: Días de atraso | I13: Cumplido en plazo
A14: CM-01 | B14: M-01 | C14: Presentar el Plan de Adquisiciones a 18 meses para No Objeción | D14: Esp. Adquisiciones | E14: 46446 | F14: 46437 | G14: Cumplido | H14: =IF(G14="Cumplido",MAX(0,F14-E14),MAX(0,Fecha_Corte-E14)) -> 0 | I14: =IF(G14="Cumplido",IF(F14<=E14,"Sí","No"),"") -> Sí
A15: CM-02 | B15: M-01 | C15: Entregar la matriz de resultados con línea base provisional | D15: Esp. Planificación, M&S | E15: 46477 | F15: 46476 | G15: Cumplido | H15: =IF(G15="Cumplido",MAX(0,F15-E15),MAX(0,Fecha_Corte-E15)) -> 0 | I15: =IF(G15="Cumplido",IF(F15<=E15,"Sí","No"),"") -> Sí
A16: CM-03 | B16: M-01 | C16: Abrir la cuenta bancaria exclusiva del Programa | D16: Esp. Financiero | E16: 46423 | F16: 46422 | G16: Cumplido | H16: =IF(G16="Cumplido",MAX(0,F16-E16),MAX(0,Fecha_Corte-E16)) -> 0 | I16: =IF(G16="Cumplido",IF(F16<=E16,"Sí","No"),"") -> Sí
A17: CM-04 | B17: M-01 | C17: Aprobar el manual de procedimientos fiduciarios internos | D17: Esp. Financiero | E17: 46492 | F17: 46499 | G17: Cumplido | H17: =IF(G17="Cumplido",MAX(0,F17-E17),MAX(0,Fecha_Corte-E17)) -> 7 | I17: =IF(G17="Cumplido",IF(F17<=E17,"Sí","No"),"") -> No
A18: CM-05 | B18: M-01 | C18: Presentar el marco de gestión ambiental y social | D18: Esp. Social | E18: 46507 | F18: 46505 | G18: Cumplido | H18: =IF(G18="Cumplido",MAX(0,F18-E18),MAX(0,Fecha_Corte-E18)) -> 0 | I18: =IF(G18="Cumplido",IF(F18<=E18,"Sí","No"),"") -> Sí
A19: CM-06 | B19: M-02 | C19: Subsanar observaciones al expediente de adquisición PA-02 | D19: Esp. Adquisiciones | E19: 46553 | F19: 46550 | G19: Cumplido | H19: =IF(G19="Cumplido",MAX(0,F19-E19),MAX(0,Fecha_Corte-E19)) -> 0 | I19: =IF(G19="Cumplido",IF(F19<=E19,"Sí","No"),"") -> Sí
A20: CM-07 | B20: M-02 | C20: Actualizar PEP y POA con la reprogramación del sistema de información | D20: Esp. Planificación, M&S | E20: 46568 | G20: En proceso | H20: =IF(G20="Cumplido",MAX(0,F20-E20),MAX(0,Fecha_Corte-E20)) -> 0 | I20: =IF(G20="Cumplido",IF(F20<=E20,"Sí","No"),"")
A21: CM-08 | B21: M-02 | C21: Justificar el umbral de anticipos antes de un nuevo pedido | D21: Esp. Financiero | E21: 46583 | G21: En proceso | H21: =IF(G21="Cumplido",MAX(0,F21-E21),MAX(0,Fecha_Corte-E21)) -> 0 | I21: =IF(G21="Cumplido",IF(F21<=E21,"Sí","No"),"")
A22: CM-09 | B22: M-02 | C22: Informar plan de mitigación del retraso en C4-03 y C4-04 | D22: Coordinador General | E22: 46558 | G22: Pendiente | H22: =IF(G22="Cumplido",MAX(0,F22-E22),MAX(0,Fecha_Corte-E22)) -> 10 | I22: =IF(G22="Cumplido",IF(F22<=E22,"Sí","No"),"")
A23: CM-10 | B23: M-02 | C23: Enviar el informe de línea base de indicadores | D23: Esp. Planificación, M&S | E23: 46553 | G23: En proceso | H23: =IF(G23="Cumplido",MAX(0,F23-E23),MAX(0,Fecha_Corte-E23)) -> 15 | I23: =IF(G23="Cumplido",IF(F23<=E23,"Sí","No"),"")

Sheet A3_No_Objeciones
A1: A3 · Registro de No Objeciones y solicitudes al BID
A2: DATOS SIMULADOS con fines de demostración metodológica — no son cifras reales del BID ni de la Dirección de Integración.
A3: La UGP es el canal ordinario con el BID. El plazo de referencia (Parametros: Plazo_NO) es interno, no un plazo del BID.
A4: ID | B4: Asunto | C4: Tipo | D4: Fecha de solicitud | E4: Fecha de respuesta | F4: Estado | G4: Responsable | H4: Días de trámite | I4: Plazo de referencia | J4: Observaciones
A5: NO-01 | B5: Plan de Adquisiciones inicial | C5: Plan de Adquisiciones | D5: 46407 | E5: 46414 | F5: Otorgada | G5: Esp. Adquisiciones | H5: =IF(E5<>"",E5-D5,Fecha_Corte-D5) -> 7 | I5: =IF(F5="Pendiente",IF(H5>Plazo_NO,"Pendiente fuera de referencia","Pendiente dentro de referencia"),IF(H5>Plazo_NO,"Respondida fuera de referencia","Respondida en referencia")) -> Respondida en referencia
A6: NO-02 | B6: TdR y selección de especialistas de la UGP (3CV) | C6: TdR / pliegos | D6: 46358 | E6: 46365 | F6: Otorgada | G6: Esp. Adquisiciones | H6: =IF(E6<>"",E6-D6,Fecha_Corte-D6) -> 7 | I6: =IF(F6="Pendiente",IF(H6>Plazo_NO,"Pendiente fuera de referencia","Pendiente dentro de referencia"),IF(H6>Plazo_NO,"Respondida fuera de referencia","Respondida en referencia")) -> Respondida en referencia
A7: NO-03 | B7: Pliego SBCC: consultoría del modelo de captación (PA-01) | C7: TdR / pliegos | D7: 46415 | E7: 46419 | F7: Otorgada | G7: Esp. Adquisiciones | H7: =IF(E7<>"",E7-D7,Fecha_Corte-D7) -> 4 | I7: =IF(F7="Pendiente",IF(H7>Plazo_NO,"Pendiente fuera de referencia","Pendiente dentro de referencia"),IF(H7>Plazo_NO,"Respondida fuera de referencia","Respondida en referencia")) -> Respondida en referencia
A8: NO-04 | B8: Evaluación y adjudicación CT-01 | C8: Evaluación y adjudicación | D8: 46447 | E8: 46454 | F8: Otorgada | G8: Esp. Adquisiciones | H8: =IF(E8<>"",E8-D8,Fecha_Corte-D8) -> 7 | I8: =IF(F8="Pendiente",IF(H8>Plazo_NO,"Pendiente fuera de referencia","Pendiente dentro de referencia"),IF(H8>Plazo_NO,"Respondida fuera de referencia","Respondida en referencia")) -> Respondida en referencia
A9: NO-05 | B9: Pliego LPN: plataforma de registro (PA-02) | C9: TdR / pliegos | D9: 46430 | E9: 46437 | F9: Otorgada | G9: Esp. Adquisiciones | H9: =IF(E9<>"",E9-D9,Fecha_Corte-D9) -> 7 | I9: =IF(F9="Pendiente",IF(H9>Plazo_NO,"Pendiente fuera de referencia","Pendiente dentro de referencia"),IF(H9>Plazo_NO,"Respondida fuera de referencia","Respondida en referencia")) -> Respondida en referencia
A10: NO-06 | B10: Evaluación y adjudicación CT-02 | C10: Evaluación y adjudicación | D10: 46489 | E10: 46502 | F10: Otorgada | G10: Esp. Adquisiciones | H10: =IF(E10<>"",E10-D10,Fecha_Corte-D10) -> 13 | I10: =IF(F10="Pendiente",IF(H10>Plazo_NO,"Pendiente fuera de referencia","Pendiente dentro de referencia"),IF(H10>Plazo_NO,"Respondida fuera de referencia","Respondida en referencia")) -> Respondida en referencia
A11: NO-07 | B11: Modificación del MOP: anexo de criterios de elegibilidad | C11: MOP | D11: 46461 | E11: 46489 | F11: Con observaciones | G11: Coordinador General | H11: =IF(E11<>"",E11-D11,Fecha_Corte-D11) -> 28 | I11: =IF(F11="Pendiente",IF(H11>Plazo_NO,"Pendiente fuera de referencia","Pendiente dentro de referencia"),IF(H11>Plazo_NO,"Respondida fuera de referencia","Respondida en referencia")) -> Respondida fuera de referencia | J11: El BID pidió precisar criterios de personas con discapacidad; respuesta en preparación
A12: NO-08 | B12: Pliego LPI: sistema de información de trayectorias (PA-10) | C12: TdR / pliegos | D12: 46447 | E12: 46451 | F12: Otorgada | G12: Esp. Adquisiciones | H12: =IF(E12<>"",E12-D12,Fecha_Corte-D12) -> 4 | I12: =IF(F12="Pendiente",IF(H12>Plazo_NO,"Pendiente fuera de referencia","Pendiente dentro de referencia"),IF(H12>Plazo_NO,"Respondida fuera de referencia","Respondida en referencia")) -> Respondida en referencia
A13: NO-09 | B13: Evaluación y adjudicación CT-09 | C13: Evaluación y adjudicación | D13: 46517 | E13: 46533 | F13: Otorgada | G13: Esp. Adquisiciones | H13: =IF(E13<>"",E13-D13,Fecha_Corte-D13) -> 16 | I13: =IF(F13="Pendiente",IF(H13>Plazo_NO,"Pendiente fuera de referencia","Pendiente dentro de referencia"),IF(H13>Plazo_NO,"Respondida fuera de referencia","Respondida en referencia")) -> Respondida fuera de referencia
A14: NO-10 | B14: Pliego LPI: equipamiento tecnológico (PA-11) | C14: TdR / pliegos | D14: 46519 | E14: 46535 | F14: Otorgada | G14: Esp. Adquisiciones | H14: =IF(E14<>"",E14-D14,Fecha_Corte-D14) -> 16 | I14: =IF(F14="Pendiente",IF(H14>Plazo_NO,"Pendiente fuera de referencia","Pendiente dentro de referencia"),IF(H14>Plazo_NO,"Respondida fuera de referencia","Respondida en referencia")) -> Respondida fuera de referencia
A15: NO-11 | B15: Pliego LPN: equipamiento de accesibilidad (PA-06) | C15: TdR / pliegos | D15: 46532 | E15: 46538 | F15: Otorgada | G15: Esp. Adquisiciones | H15: =IF(E15<>"",E15-D15,Fecha_Corte-D15) -> 6 | I15: =IF(F15="Pendiente",IF(H15>Plazo_NO,"Pendiente fuera de referencia","Pendiente dentro de referencia"),IF(H15>Plazo_NO,"Respondida fuera de referencia","Respondida en referencia")) -> Respondida en referencia
A16: NO-12 | B16: TdR y SBCC: capacitación a instituciones (PA-12) | C16: TdR / pliegos | D16: 46548 | F16: Pendiente | G16: Esp. Adquisiciones | H16: =IF(E16<>"",E16-D16,Fecha_Corte-D16) -> 20 | I16: =IF(F16="Pendiente",IF(H16>Plazo_NO,"Pendiente fuera de referencia","Pendiente dentro de referencia"),IF(H16>Plazo_NO,"Respondida fuera de referencia","Respondida en referencia")) -> Pendiente fuera de referencia | J16: Esperando respuesta
A17: NO-13 | B17: Reasignación entre categorías de inversión (ajuste del POA) | C17: Reasignación presupuestaria | D17: 46560 | F17: Pendiente | G17: Esp. Financiero | H17: =IF(E17<>"",E17-D17,Fecha_Corte-D17) -> 8 | I17: =IF(F17="Pendiente",IF(H17>Plazo_NO,"Pendiente fuera de referencia","Pendiente dentro de referencia"),IF(H17>Plazo_NO,"Respondida fuera de referencia","Respondida en referencia")) -> Pendiente dentro de referencia

Sheet A4_Interesados
A1: A4 · Registro y estrategia de interesados (poder / interés)
A2: DATOS SIMULADOS con fines de demostración metodológica — no son cifras reales del BID ni de la Dirección de Integración.
A3: Cuadrante: poder ≥ 4 e interés ≥ 4 → gestionar de cerca; poder ≥ 4 → mantener satisfecho; interés ≥ 4 → mantener informado; resto → monitorear.
A4: ID | B4: Interesado | C4: Rol en el Programa | D4: Poder (1-5) | E4: Interés (1-5) | F4: Actitud | G4: Cuadrante | H4: Prioridad (P×I) | I4: Estrategia de comunicación | J4: Frecuencia | K4: Responsable
A5: I-01 | B5: Banco Interamericano de Desarrollo (equipo de proyecto) | C5: Financiador; no objeciones, misiones y desembolsos | D5: 5 | E5: 5 | F5: Líder | G5: =IF(AND(D5>=4,E5>=4),"Gestionar de cerca",IF(D5>=4,"Mantener satisfecho",IF(E5>=4,"Mantener informado","Monitorear"))) -> Gestionar de cerca | H5: =D5*E5 -> 25 | I5: Informe mensual, reuniones de seguimiento y misiones | J5: Mensual | K5: Coordinador General
A6: I-02 | B6: Dirección General de la Dirección de Integración | C6: Autoridad del Organismo Ejecutor; decisiones estratégicas | D6: 5 | E6: 5 | F6: Líder | G6: =IF(AND(D6>=4,E6>=4),"Gestionar de cerca",IF(D6>=4,"Mantener satisfecho",IF(E6>=4,"Mantener informado","Monitorear"))) -> Gestionar de cerca | H6: =D6*E6 -> 25 | I6: Reunión de decisiones y alertas escaladas | J6: Mensual | K6: Coordinador General
A7: I-03 | B7: Gerencia de Cooperación Institucional | C7: Supervisión contractual y aprobación de productos de la UGP | D7: 5 | E7: 5 | F7: A favor | G7: =IF(AND(D7>=4,E7>=4),"Gestionar de cerca",IF(D7>=4,"Mantener satisfecho",IF(E7>=4,"Mantener informado","Monitorear"))) -> Gestionar de cerca | H7: =D7*E7 -> 25 | I7: Informe mensual y reunión de coordinación | J7: Semanal | K7: Coordinador General
A8: I-04 | B8: Ministerio de Hacienda | C8: Autoridad fiscal; programación y contrapartidas | D8: 4 | E8: 3 | F8: Neutral | G8: =IF(AND(D8>=4,E8>=4),"Gestionar de cerca",IF(D8>=4,"Mantener satisfecho",IF(E8>=4,"Mantener informado","Monitorear"))) -> Mantener satisfecho | H8: =D8*E8 -> 12 | I8: Informes de ejecución y proyecciones de desembolso | J8: Trimestral | K8: Esp. Financiero
A9: I-05 | B9: Ministerio de Educación, Ciencia y Tecnología | C9: Rector del sistema educativo; articulación con educación media | D9: 4 | E9: 5 | F9: A favor | G9: =IF(AND(D9>=4,E9>=4),"Gestionar de cerca",IF(D9>=4,"Mantener satisfecho",IF(E9>=4,"Mantener informado","Monitorear"))) -> Gestionar de cerca | H9: =D9*E9 -> 20 | I9: Mesa técnica y convenios | J9: Mensual | K9: Esp. Social
A10: I-06 | B10: Corte de Cuentas de la República | C10: Control externo | D10: 4 | E10: 2 | F10: Neutral | G10: =IF(AND(D10>=4,E10>=4),"Gestionar de cerca",IF(D10>=4,"Mantener satisfecho",IF(E10>=4,"Mantener informado","Monitorear"))) -> Mantener satisfecho | H10: =D10*E10 -> 8 | I10: Entrega de información y atención de requerimientos | J10: Por requerimiento | K10: Esp. Financiero
A11: I-07 | B11: Instituciones de educación postsecundaria (públicas) | C11: Receptoras de beneficiarios; fortalecimiento institucional | D11: 3 | E11: 5 | F11: A favor | G11: =IF(AND(D11>=4,E11>=4),"Gestionar de cerca",IF(D11>=4,"Mantener satisfecho",IF(E11>=4,"Mantener informado","Monitorear"))) -> Mantener informado | H11: =D11*E11 -> 15 | I11: Convenios, capacitación y mesas de coordinación | J11: Mensual | K11: Esp. Social
A12: I-08 | B12: Instituciones de educación postsecundaria (privadas) | C12: Receptoras de beneficiarios | D12: 3 | E12: 4 | F12: Neutral | G12: =IF(AND(D12>=4,E12>=4),"Gestionar de cerca",IF(D12>=4,"Mantener satisfecho",IF(E12>=4,"Mantener informado","Monitorear"))) -> Mantener informado | H12: =D12*E12 -> 12 | I12: Convocatorias y convenios | J12: Trimestral | K12: Esp. Social
A13: I-09 | B13: Empleadores y gremios | C13: Vinculación laboral de las personas graduadas | D13: 3 | E13: 4 | F13: Neutral | G13: =IF(AND(D13>=4,E13>=4),"Gestionar de cerca",IF(D13>=4,"Mantener satisfecho",IF(E13>=4,"Mantener informado","Monitorear"))) -> Mantener informado | H13: =D13*E13 -> 12 | I13: Alianzas y encuentros sectoriales | J13: Trimestral | K13: Esp. Social
A14: I-10 | B14: Organizaciones de personas con discapacidad y de sociedad civil | C14: Accesibilidad, veeduría social y mecanismo de quejas | D14: 2 | E14: 5 | F14: A favor | G14: =IF(AND(D14>=4,E14>=4),"Gestionar de cerca",IF(D14>=4,"Mantener satisfecho",IF(E14>=4,"Mantener informado","Monitorear"))) -> Mantener informado | H14: =D14*E14 -> 10 | I14: Consultas y devolución de resultados | J14: Trimestral | K14: Esp. Social
A15: I-11 | B15: Jóvenes beneficiarios y sus familias | C15: Población objetivo | D15: 2 | E15: 5 | F15: A favor | G15: =IF(AND(D15>=4,E15>=4),"Gestionar de cerca",IF(D15>=4,"Mantener satisfecho",IF(E15>=4,"Mantener informado","Monitorear"))) -> Mantener informado | H15: =D15*E15 -> 10 | I15: Canales de atención, mecanismo de quejas y comunicación directa | J15: Continua | K15: Esp. Social
A16: I-12 | B16: Proveedores y consultores | C16: Ejecutores de contratos y servicios | D16: 2 | E16: 4 | F16: Neutral | G16: =IF(AND(D16>=4,E16>=4),"Gestionar de cerca",IF(D16>=4,"Mantener satisfecho",IF(E16>=4,"Mantener informado","Monitorear"))) -> Mantener informado | H16: =D16*E16 -> 8 | I16: Reuniones de arranque y supervisión de contratos | J16: Según contrato | K16: Esp. Adquisiciones
A17: I-13 | B17: Gobiernos locales | C17: Facilitan acceso territorial y ferias de orientación | D17: 2 | E17: 3 | F17: Neutral | G17: =IF(AND(D17>=4,E17>=4),"Gestionar de cerca",IF(D17>=4,"Mantener satisfecho",IF(E17>=4,"Mantener informado","Monitorear"))) -> Monitorear | H17: =D17*E17 -> 6 | I17: Coordinación territorial | J17: Trimestral | K17: Esp. Social

Sheet A5_Calendario_Informes
A1: A5 · Calendario de productos de la consultoría (P1-P12) y habilitación de pagos
A2: DATOS SIMULADOS con fines de demostración metodológica — no son cifras reales del BID ni de la Dirección de Integración.
A3: TDR §VII y §XIII: informes mensuales a 3 días hábiles del cierre; el pago de US$4,200 se libera con la aprobación formal del informe.
A4: Código | B4: Producto | C4: Periodicidad | D4: Fecha límite | E4: Fecha de entrega | F4: Estado de entrega | G4: Conformidad | H4: Honorario USD | I4: Pago habilitado | J4: Desvío (días)
A5: P1 | B5: Plan de trabajo inicial e informe mensual de gestión | C5: Al final del primer mes de la contratación | D5: =EOMONTH(Inicio_Consultoria,0) -> 46418 | E5: 46416 | F5: =IF(E5<>"",IF(E5<=D5,"Entregado a tiempo","Entregado con retraso"),IF(D5<Fecha_Corte,"Vencido","Programado")) -> Entregado a tiempo | G5: Conforme | H5: =Pago_Mensual -> 4200 | I5: =IF(G5="Conforme","Sí","No") -> Sí | J5: =IF(E5<>"",E5-D5,"") -> -2
A6: P2 | B6: Informe mensual de gestión | C6: Mensual / tres días hábiles posteriores al cierre del mes a reportar | D6: =WORKDAY(EOMONTH(Inicio_Consultoria,1),Plazo_Informe) -> 46449 | E6: 46449 | F6: =IF(E6<>"",IF(E6<=D6,"Entregado a tiempo","Entregado con retraso"),IF(D6<Fecha_Corte,"Vencido","Programado")) -> Entregado a tiempo | G6: Conforme | H6: =Pago_Mensual -> 4200 | I6: =IF(G6="Conforme","Sí","No") -> Sí | J6: =IF(E6<>"",E6-D6,"") -> 0
A7: P3 | B7: Informe mensual de gestión | C7: Mensual / tres días hábiles posteriores al cierre del mes a reportar | D7: =WORKDAY(EOMONTH(Inicio_Consultoria,2),Plazo_Informe) -> 46482 | E7: 46483 | F7: =IF(E7<>"",IF(E7<=D7,"Entregado a tiempo","Entregado con retraso"),IF(D7<Fecha_Corte,"Vencido","Programado")) -> Entregado con retraso | G7: Conforme | H7: =Pago_Mensual -> 4200 | I7: =IF(G7="Conforme","Sí","No") -> Sí | J7: =IF(E7<>"",E7-D7,"") -> 1
A8: P4 | B8: Informe mensual de gestión | C8: Mensual / tres días hábiles posteriores al cierre del mes a reportar | D8: =WORKDAY(EOMONTH(Inicio_Consultoria,3),Plazo_Informe) -> 46512 | E8: 46512 | F8: =IF(E8<>"",IF(E8<=D8,"Entregado a tiempo","Entregado con retraso"),IF(D8<Fecha_Corte,"Vencido","Programado")) -> Entregado a tiempo | G8: Conforme | H8: =Pago_Mensual -> 4200 | I8: =IF(G8="Conforme","Sí","No") -> Sí | J8: =IF(E8<>"",E8-D8,"") -> 0
A9: P5 | B9: Informe mensual de gestión | C9: Mensual / tres días hábiles posteriores al cierre del mes a reportar | D9: =WORKDAY(EOMONTH(Inicio_Consultoria,4),Plazo_Informe) -> 46541 | E9: 46540 | F9: =IF(E9<>"",IF(E9<=D9,"Entregado a tiempo","Entregado con retraso"),IF(D9<Fecha_Corte,"Vencido","Programado")) -> Entregado a tiempo | G9: Conforme | H9: =Pago_Mensual -> 4200 | I9: =IF(G9="Conforme","Sí","No") -> Sí | J9: =IF(E9<>"",E9-D9,"") -> -1
A10: P6 | B10: Informe mensual de gestión | C10: Mensual / tres días hábiles posteriores al cierre del mes a reportar | D10: =WORKDAY(EOMONTH(Inicio_Consultoria,5),Plazo_Informe) -> 46573 | F10: =IF(E10<>"",IF(E10<=D10,"Entregado a tiempo","Entregado con retraso"),IF(D10<Fecha_Corte,"Vencido","Programado")) -> Programado | G10: Pendiente | H10: =Pago_Mensual -> 4200 | I10: =IF(G10="Conforme","Sí","No") -> No | J10: =IF(E10<>"",E10-D10,"")
A11: P7 | B11: Informe mensual de gestión | C11: Mensual / tres días hábiles posteriores al cierre del mes a reportar | D11: =WORKDAY(EOMONTH(Inicio_Consultoria,6),Plazo_Informe) -> 46603 | F11: =IF(E11<>"",IF(E11<=D11,"Entregado a tiempo","Entregado con retraso"),IF(D11<Fecha_Corte,"Vencido","Programado")) -> Programado | G11: Pendiente | H11: =Pago_Mensual -> 4200 | I11: =IF(G11="Conforme","Sí","No") -> No | J11: =IF(E11<>"",E11-D11,"")
A12: P8 | B12: Informe mensual de gestión | C12: Mensual / tres días hábiles posteriores al cierre del mes a reportar | D12: =WORKDAY(EOMONTH(Inicio_Consultoria,7),Plazo_Informe) -> 46633 | F12: =IF(E12<>"",IF(E12<=D12,"Entregado a tiempo","Entregado con retraso"),IF(D12<Fecha_Corte,"Vencido","Programado")) -> Programado | G12: Pendiente | H12: =Pago_Mensual -> 4200 | I12: =IF(G12="Conforme","Sí","No") -> No | J12: =IF(E12<>"",E12-D12,"")
A13: P9 | B13: Informe mensual de gestión | C13: Mensual / tres días hábiles posteriores al cierre del mes a reportar | D13: =WORKDAY(EOMONTH(Inicio_Consultoria,8),Plazo_Informe) -> 46665 | F13: =IF(E13<>"",IF(E13<=D13,"Entregado a tiempo","Entregado con retraso"),IF(D13<Fecha_Corte,"Vencido","Programado")) -> Programado | G13: Pendiente | H13: =Pago_Mensual -> 4200 | I13: =IF(G13="Conforme","Sí","No") -> No | J13: =IF(E13<>"",E13-D13,"")
A14: P10 | B14: Informe mensual de gestión | C14: Mensual / tres días hábiles posteriores al cierre del mes a reportar | D14: =WORKDAY(EOMONTH(Inicio_Consultoria,9),Plazo_Informe) -> 46694 | F14: =IF(E14<>"",IF(E14<=D14,"Entregado a tiempo","Entregado con retraso"),IF(D14<Fecha_Corte,"Vencido","Programado")) -> Programado | G14: Pendiente | H14: =Pago_Mensual -> 4200 | I14: =IF(G14="Conforme","Sí","No") -> No | J14: =IF(E14<>"",E14-D14,"")
A15: P11 | B15: Informe mensual de gestión | C15: Mensual / tres días hábiles posteriores al cierre del mes a reportar | D15: =WORKDAY(EOMONTH(Inicio_Consultoria,10),Plazo_Informe) -> 46724 | F15: =IF(E15<>"",IF(E15<=D15,"Entregado a tiempo","Entregado con retraso"),IF(D15<Fecha_Corte,"Vencido","Programado")) -> Programado | G15: Pendiente | H15: =Pago_Mensual -> 4200 | I15: =IF(G15="Conforme","Sí","No") -> No | J15: =IF(E15<>"",E15-D15,"")
A16: P12 | B16: Informe anual | C16: Diez días previos al cierre del año | D16: =DATE(YEAR(Inicio_Consultoria),12,31)-10 -> 46742 | F16: =IF(E16<>"",IF(E16<=D16,"Entregado a tiempo","Entregado con retraso"),IF(D16<Fecha_Corte,"Vencido","Programado")) -> Programado | G16: Pendiente | H16: =Pago_Mensual -> 4200 | I16: =IF(G16="Conforme","Sí","No") -> No | J16: =IF(E16<>"",E16-D16,"")
A18: Los feriados no se descuentan en WORKDAY; si el MOP o el contrato los excluyen, agregue la lista de feriados como tercer argumento.

Sheet A6_Informe_Mensual
A1: A6 · Informe mensual de gestión — borrador automático (contenido mínimo del TDR §VII)
A2: DATOS SIMULADOS con fines de demostración metodológica — no son cifras reales del BID ni de la Dirección de Integración.
A3: Cada línea se calcula desde las demás hojas. Los textos en azul (decisiones, prioridades) los redacta la UGP antes de entregar el informe.
A4: Sección del TDR | B4: Elemento | C4: Valor | D4: Fuente
A5: 1. Resumen ejecutivo | B5: Fecha de corte del informe | C5: =Fecha_Corte -> 46568 | D5: Parametros
A6: 1. Resumen ejecutivo | B6: Avance físico acumulado del POA | C6: =P1_Avance_FF!F10 -> 0.44792308 | D6: P1_Avance_FF
A7: 1. Resumen ejecutivo | B7: Avance físico planificado a la fecha | C7: =P1_Avance_FF!G10 -> 0.52567146 | D7: P1_Avance_FF
A8: 1. Resumen ejecutivo | B8: Ejecución financiera del POA | C8: =P1_Avance_FF!E10 -> 0.41974615 | D8: P1_Avance_FF
A9: 1. Resumen ejecutivo | B9: SPI / CPI del Programa | C9: =IF(ISNUMBER(P1_Avance_FF!J10),ROUND(P1_Avance_FF!J10,2)&" / "&ROUND(P1_Avance_FF!K10,2),"n/a") -> 0.85 / 1.07 | D9: P1_Avance_FF
A10: 1. Resumen ejecutivo | B10: Alertas críticas (rojos: actividades, riesgos altos, obligaciones y compromisos vencidos) | C10: =COUNTIF(P1_POA!$R$5:$R$200,"Rojo")+COUNTIFS(P1_Riesgos!$H$5:$H$200,"Alto",P1_Riesgos!$M$5:$M$200,"<>Cerrado")+COUNTIF(N1_Cumplimiento!$K$5:$K$200,"Vencida")+COUNTIFS(A2_Misiones_BID!$E$5:$E$100,"<"&Fecha_Corte,A2_Misiones_BID!$G$5:$G$100,"<>Cumplido",A2_Misiones_BID!$A$5:$A$100,"CM-*") -> 9 | D10: Varias hojas
A11: 1. Resumen ejecutivo | B11: Logros y decisiones requeridas (redactar) | C11: Aprobar la reprogramación de C4 y priorizar las No Objeciones pendientes | D11: Redacción UGP
A12: 2. Avance de actividades y productos vs. POA | B12: Actividades del POA | C12: =P1_Avance_FF!M10 -> 24 | D12: P1_POA
A13: 2. Avance de actividades y productos vs. POA | B13: Completadas | C13: =COUNTIF(P1_POA!$Q$5:$Q$200,"Completada") -> 4 | D13: P1_POA
A14: 2. Avance de actividades y productos vs. POA | B14: Con alerta (semáforo amarillo o rojo) | C14: =P1_Avance_FF!N10 -> 14 | D14: P1_POA
A15: 2. Avance de actividades y productos vs. POA | B15: Vencidas sin completar | C15: =COUNTIF(P1_POA!$Q$5:$Q$200,"Vencida sin completar") -> 2 | D15: P1_POA
A16: 3. Metas e indicadores | B16: Indicadores en verde | C16: =COUNTIF(P1_Resultados!$Q$5:$Q$100,"Verde") -> 3 | D16: P1_Resultados
A17: 3. Metas e indicadores | B17: Indicadores en amarillo | C17: =COUNTIF(P1_Resultados!$Q$5:$Q$100,"Amarillo") -> 10 | D17: P1_Resultados
A18: 3. Metas e indicadores | B18: Indicadores en rojo | C18: =COUNTIF(P1_Resultados!$Q$5:$Q$100,"Rojo") -> 2 | D18: P1_Resultados
A19: 3. Metas e indicadores | B19: Indicadores sin dato en el período | C19: =COUNTIF(P1_Resultados!$Q$5:$Q$100,"Sin dato") -> 3 | D19: P1_Resultados
A20: 4. Ejecución financiera y proyecciones | B20: Presupuesto total del Programa (USD) | C20: =Total_Programa -> 104000000 | D20: Parametros
A21: 4. Ejecución financiera y proyecciones | B21: Ejecutado acumulado (USD) | C21: =F1_Presupuesto_PEP!N10 -> 2728350 | D21: F1_Presupuesto_PEP
A22: 4. Ejecución financiera y proyecciones | B22: % ejecutado sobre el total | C22: =F1_Presupuesto_PEP!O10 -> 0.026234135 | D22: F1_Presupuesto_PEP
A23: 4. Ejecución financiera y proyecciones | B23: Proyectado acumulado a los trimestres cerrados (USD) | C23: =SUMIFS(F3_Plan_Financiero!$D$5:$D$20,F3_Plan_Financiero!$C$5:$C$20,"<="&Fecha_Corte) -> 2730000 | D23: F3_Plan_Financiero
A24: 4. Ejecución financiera y proyecciones | B24: Real acumulado a la fecha de corte (USD) | C24: =SUMIFS(F2_Ejecucion!$J$5:$J$500,F2_Ejecucion!$B$5:$B$500,"<="&Fecha_Corte) -> 2728350 | D24: F2_Ejecucion
A25: 4. Ejecución financiera y proyecciones | B25: Total desembolsado por el BID (USD) | C25: =F3_Desembolsos!L13 -> 2996450 | D25: F3_Desembolsos
A26: 4. Ejecución financiera y proyecciones | B26: % de anticipos justificado | C26: =F3_Desembolsos!L8 -> 0.69822917 | D26: F3_Desembolsos
A27: 4. Ejecución financiera y proyecciones | B27: Alerta de anticipos | C27: =F3_Desembolsos!L15 -> NO solicitar: justificar al 80% (faltan US$ 244250) | D27: F3_Desembolsos
A28: 5. Adquisiciones y contratos | B28: Procesos en el Plan de Adquisiciones | C28: =COUNTIF(F4_Plan_Adquisiciones!$A$5:$A$200,"PA-*") -> 20 | D28: F4_Plan_Adquisiciones
A29: 5. Adquisiciones y contratos | B29: Procesos contratados | C29: =COUNTIF(F4_Plan_Adquisiciones!$I$5:$I$200,"Contratado") -> 16 | D29: F4_Plan_Adquisiciones
A30: 5. Adquisiciones y contratos | B30: Procesos atrasados | C30: =COUNTIF(F4_Plan_Adquisiciones!$P$5:$P$200,"Atrasado") -> 1 | D30: F4_Plan_Adquisiciones
A31: 5. Adquisiciones y contratos | B31: Contratos vigentes / por vencer / vencidos | C31: =COUNTIF(F5_Contratos!$N$5:$N$200,"Vigente")&" / "&COUNTIF(F5_Contratos!$N$5:$N$200,"Por vencer")&" / "&COUNTIF(F5_Contratos!$N$5:$N$200,"Vencido") -> 11 / 2 / 3 | D31: F5_Contratos
A32: 6. Compromisos, No Objeciones y BID | B32: No Objeciones pendientes | C32: =COUNTIF(A3_No_Objeciones!$F$5:$F$200,"Pendiente") -> 2 | D32: A3_No_Objeciones
A33: 6. Compromisos, No Objeciones y BID | B33: No Objeciones pendientes fuera del plazo de referencia | C33: =COUNTIF(A3_No_Objeciones!$I$5:$I$200,"Pendiente fuera de referencia") -> 1 | D33: A3_No_Objeciones
A34: 6. Compromisos, No Objeciones y BID | B34: Compromisos con el BID vencidos | C34: =COUNTIFS(A2_Misiones_BID!$E$5:$E$100,"<"&Fecha_Corte,A2_Misiones_BID!$G$5:$G$100,"<>Cumplido",A2_Misiones_BID!$A$5:$A$100,"CM-*") -> 2 | D34: A2_Misiones_BID
A35: 7. Riesgos, incidentes y asuntos escalados | B35: Riesgos altos abiertos | C35: =COUNTIFS(P1_Riesgos!$H$5:$H$200,"Alto",P1_Riesgos!$M$5:$M$200,"<>Cerrado") -> 3 | D35: P1_Riesgos
A36: 7. Riesgos, incidentes y asuntos escalados | B36: Riesgos medios abiertos | C36: =COUNTIFS(P1_Riesgos!$H$5:$H$200,"Medio",P1_Riesgos!$M$5:$M$200,"<>Cerrado") -> 11 | D36: P1_Riesgos
A37: 7. Riesgos, incidentes y asuntos escalados | B37: Riesgo prioritario n.º 1 | C37: =INDEX(P1_Riesgos!$C$5:$C$200,MATCH(1,P1_Riesgos!$T$5:$T$200,0)) -> Retrasos en adquisiciones por observaciones en las No Objeciones | D37: P1_Riesgos
A38: 7. Riesgos, incidentes y asuntos escalados | B38: Riesgo prioritario n.º 2 | C38: =INDEX(P1_Riesgos!$C$5:$C$200,MATCH(2,P1_Riesgos!$T$5:$T$200,0)) -> Ejecución presupuestaria por debajo del PEP | D38: P1_Riesgos
A39: 7. Riesgos, incidentes y asuntos escalados | B39: Riesgo prioritario n.º 3 | C39: =INDEX(P1_Riesgos!$C$5:$C$200,MATCH(3,P1_Riesgos!$T$5:$T$200,0)) -> Exclusión de grupos prioritarios (discapacidad, madres jóvenes, retornados) | D39: P1_Riesgos
A40: 8. Cumplimiento ambiental, social, inclusión y datos | B40: Obligaciones normativas vencidas | C40: =COUNTIF(N1_Cumplimiento!$K$5:$K$200,"Vencida") -> 1 | D40: N1_Cumplimiento
A41: 8. Cumplimiento ambiental, social, inclusión y datos | B41: % de cumplimiento de obligaciones exigibles | C41: =N1_Cumplimiento!O10 -> 0.88888889 | D41: N1_Cumplimiento
A42: 8. Cumplimiento ambiental, social, inclusión y datos | B42: Beneficiarios alcanzados / meta año 1 | C42: =P2_Focalizacion!G19&" / "&P2_Focalizacion!F19 -> 2380 / 6000 | D42: P2_Focalizacion
A43: 8. Cumplimiento ambiental, social, inclusión y datos | B43: Madres jóvenes, personas con discapacidad y retornadas/os atendidas | C43: =P2_Focalizacion!H19&" / "&P2_Focalizacion!I19&" / "&P2_Focalizacion!J19 -> 223 / 90 / 75 | D43: P2_Focalizacion
A44: 9. Gestión de la UGP | B44: Informes entregados a tiempo | C44: =COUNTIF(A5_Calendario_Informes!$F$5:$F$30,"Entregado a tiempo")&" de "&COUNTIF(A5_Calendario_Informes!$F$5:$F$30,"Entregado*") -> 4 de 5 | D44: A5_Calendario_Informes
A45: 9. Gestión de la UGP | B45: Plazas de la UGP cubiertas | C45: =COUNTIF(A1_Equipo!$D$5:$D$12,"Contratado")&" de "&COUNTA(A1_Equipo!$A$5:$A$10) -> 5 de 6 | D45: A1_Equipo
A46: 9. Gestión de la UGP | B46: Recomendaciones de auditoría vencidas | C46: =COUNTIF(F6_Auditoria!$I$14:$I$100,">0") -> 1 | D46: F6_Auditoria
A47: 10-12. Próximo período, matriz y anexos | B47: Prioridades del próximo período (redactar) | C47: Cerrar adjudicaciones PA-11 y PA-12; presentar la línea base; justificar anticipos al 80 % | D47: Redacción UGP
A48: 10-12. Próximo período, matriz y anexos | B48: Anexos y archivo | C48: Enlaces a evidencia documental organizada por proceso (expediente del Programa) | D48: Redacción UGP

Sheet Listas
A1: Listas de valores (fuentes de las listas desplegables)
A2: DATOS SIMULADOS con fines de demostración metodológica — no son cifras reales del BID ni de la Dirección de Integración.
A3: Para agregar un valor, escríbalo debajo de la última fila de su lista y amplíe el rango en Datos > Validación de datos.
A4: Componente | B4: Fuente | C4: Categoria_gasto | D4: Mecanismo | E4: Estado_pago | F4: Justificado | G4: Departamento | H4: Metodo_adq | I4: Estado_adq | J4: Categoria_adq | K4: Revision | L4: Estado_cumpl | M4: Estado_compromiso | N4: Estado_NO | O4: Estado_riesgo | P4: Categoria_riesgo | Q4: Respuesta_riesgo | R4: Actitud | S4: Conformidad | T4: Escala | U4: Tipo_meta | V4: Responsable | W4: Instrumento | X4: Estado_audit | Y4: Estado_hallazgo
A5: C1 | B5: Préstamo | C5: Consultoría | D5: Anticipo de fondos | E5: Pagado | F5: Sí | G5: Nacional | H5: LPI | I5: Planificado | J5: Bienes | K5: Ex ante | L5: Pendiente | M5: Pendiente | N5: Pendiente | O5: Abierto | P5: Técnico | Q5: Mitigar | R5: Líder | S5: Conforme | T5: 1 | U5: Acumulativa | V5: Coordinador General | W5: Contrato de Préstamo 6153/OC-ES | X5: Planificada | Y5: Abierta
A6: C2 | B6: Donación | C6: Servicios de no consultoría | D6: Reembolso de gastos | E6: Por pagar | F6: No | G6: Ahuachapán | H6: LPN | I6: Preparación | J6: Obras | K6: Ex post | L6: En proceso | M6: En proceso | N6: Otorgada | O6: En mitigación | P6: Fiduciario | Q6: Evitar | R6: A favor | S6: Con observaciones | T6: 2 | U6: Nivel | V6: Esp. Financiero | W6: Convenio GR 6154/GR-ES | X6: En ejecución | Y6: En proceso
A7: C3 | C7: Bienes | D7: Pago directo | F7: N/A | G7: Cabañas | H7: Comparación de precios | I7: Publicado | J7: Servicios de no consultoría | L7: Cumplida | M7: Cumplido | N7: Con observaciones | O7: Cerrado | P7: Institucional | Q7: Transferir | R7: Neutral | S7: Pendiente | T7: 3 | V7: Esp. Adquisiciones | W7: MOP | X7: Informe emitido | Y7: Cerrada
A8: C4 | C8: Obras | G8: Chalatenango | H8: Contratación directa | I8: Evaluación | J8: Consultoría (firma) | P8: Ambiental y social | Q8: Aceptar | R8: En contra | T8: 4 | V8: Esp. Planificación, M&S | W8: Políticas BID | X8: Cerrada
A9: C5 | C9: Transferencias a beneficiarios | G9: Cuscatlán | H9: SBCC | I9: Contratado | J9: Consultor individual | P9: Cumplimiento | T9: 5 | V9: Esp. Social | W9: Normativa nacional
C10: Costos operativos | G10: La Libertad | H10: SBC | I10: Cerrado | P10: Externo | V10: Gerencia de Cooperación Institucional | W10: TDR / UGP
G11: La Paz | H11: SBMC | V11: Dirección General
G12: La Unión | H12: 3CV
G13: Morazán
G14: San Miguel
G15: San Salvador
G16: San Vicente
G17: Santa Ana
G18: Sonsonate
G19: Usulután
